Electronica Digital 1/ModuloWs2812/Comp.v
//Modulo que compara dos valores dependendiendo de lo que se requiera comparar
module Comp(
    input [15:0] a,
    input [15:0] b,
    output reg z
);

    always @(*) begin
        z = (a == b);
    end

endmodule

Electronica Digital 1/ModuloSendLeds/Control_Timer.v
// Modulo de Unidad de Control para Timer (protocolo tipo NeoPixel/WS2812)
module Control_Timer ( 
    input clk,
    input z, 
    input [1:0] sel,     
    input init_t,
    output reg dout, 
    output reg done,
    output reg rst,
    output reg inc,
    output reg [1:0]sel_tim
);

    parameter START      = 4'b0000;
    parameter CHECK1     = 4'b0001;
    parameter INIT       = 4'b0010;
    parameter CHECK2     = 4'b0011;   
    parameter T0H        = 4'b0100;
    parameter T1H        = 4'b0101;
    parameter DOUT1      = 4'b0110;
    parameter DOUT2      = 4'b0111;
    parameter DOUT3      = 4'b1000;
    parameter COUNT1     = 4'b1001;
    parameter CHECK3     = 4'b1010;
    parameter COUNT2     = 4'b1011;
    parameter COUNT3     = 4'b1100;
    parameter CHECK4     = 4'b1101;
    parameter CHECK5     = 4'b1110;
    parameter DONE       = 4'b1111;


    reg [3:0] state;

    always @(*) begin


        case (state)
            START: begin
                dout    = 0; 
                done    = 0;
                rst     = 0;
                inc     = 0;
                sel_tim = 0;               
            end

            CHECK1: begin
                dout    = 0; 
                done    = 0;
                rst     = 0;
                inc     = 0;
                sel_tim = 0;                 
            end 

            INIT: begin
                dout    = 0; 
                done    = 0;
                rst     = 1;
                inc     = 0;
                sel_tim = 0;  
            end

            CHECK2: begin
                dout    = 0; 
                done    = 0;
                rst     = 0;
                inc     = 0;
                sel_tim = 0;                 
            end

            T0H: begin
                dout    = 0; 
                done    = 0;
                rst     = 0;
                inc     = 0;
                sel_tim = 0; 
            end

            T1H: begin
                dout    = 0; 
                done    = 0;
                rst     = 0;
                inc     = 0;
                sel_tim = 1;
            end

            DOUT1: begin
                dout    = 0; 
                done    = 0;
                rst     = 0;
                inc     = 0;
                sel_tim = 2;       
            end

            DOUT2: begin
                dout    = 1; 
                done    = 0;
                rst     = 0;
                inc     = 0;
                sel_tim = 0;       
            end


            DOUT3: begin
                dout    = 0; 
                done    = 0;
                rst     = 0;
                inc     = 0;
                sel_tim = 0;       
            end

            COUNT1: begin
                dout    = 1; 
                done    = 0;
                rst     = 0;
                inc     = 1;
                sel_tim = 0;       
            end

            CHECK3: begin
                dout    = 1; 
                done    = 0;
                rst     = 0;
                inc     = 0;
                sel_tim = 0;       
            end


            COUNT2: begin
                dout    = 0; 
                done    = 0;
                rst     = 0;
                inc     = 1;
                sel_tim = 3;         
            end


            COUNT3: begin
                dout    = 0; 
                done    = 0;
                rst     = 0;
                inc     = 1;
                sel_tim = 2;    
            end

            CHECK4: begin
                dout    = 0; 
                done    = 0;
                rst     = 0;
                inc     = 0;
                sel_tim = 2;    
            end


            CHECK5: begin
                dout    = 0; 
                done    = 0;
                rst     = 0;
                inc     = 0;
                sel_tim = 3;    
            end


            DONE: begin
                dout    = 0; 
                done    = 1;
                rst     = 0;
                inc     = 0;
                sel_tim = 0; 
            end
            
            default: begin
                dout    = 0; 
                done    = 0;
                rst     = 0;
                inc     = 0;
                sel_tim = 0;                
            end
        endcase
    end


    always @(posedge clk) begin
        case (state)
            START: begin
                state <= CHECK1;
            end

            CHECK1: begin
                if (init_t == 1)
                    state <= INIT;
                else
                    state <= CHECK1;
            end

            INIT: begin
                state <= CHECK2;
            end

            CHECK2: begin
                case (sel)
                    2'b00:   state <= T0H;
                    2'b01:   state <= T1H;
                    2'b10:   state <= DOUT1;
                    default: state <= T0H;
                endcase
            end

            T0H: begin
                state <= DOUT2;
            end

            T1H: begin
                state <= DOUT2;
            end

            DOUT1: begin
                state <= DOUT3;
            end

            DOUT2: begin
                state <= COUNT1;
            end

            DOUT3: begin
                state <= COUNT3;
            end

            COUNT1: begin
                state <= CHECK3;
            end

            CHECK3: begin
                if (z)
                    state <= COUNT2;
                else
                    state <= COUNT1;
            end

            COUNT2: begin
                state <= CHECK5;
            end

            CHECK5: begin
                if (z)
                    state <= DONE;
                else
                    state <= COUNT2;
            end

            COUNT3: begin
                state <= CHECK4;
            end

            CHECK4: begin
  
                if (z)
                    state <= DONE;
                else
                    state <= COUNT3;
            end

            DONE: begin
                state <= START;
            end

            default: begin
                state <= START;
            end
        endcase
    end

endmodule

Electronica Digital 1/ModuloWs2812/Multiplex.v
// Modulo de multiplexor
module Multiplex (
    input [15:0] T0h,
    input [15:0] T1h,
    input [15:0]Res,
    input [15:0] Per,
    input[1:0]sel_tim,
    output reg [15:0] out   
);

    always @(*) begin
        case(sel_tim)
        2'b00: out =T0h;
        2'b01: out =T1h;
        2'b10: out =Res;
        2'b11: out =Per;
        default: out = T0h;
        endcase
    end

endmodule

Electronica Digital 1/ModuloTimer/Count_out.v
// Modulo de count
module Count_out (
    input clk,
    input rst,         
    input inc,     
    output reg [15:0] count_out 
);

   
    always @(negedge clk) begin
        if (rst) begin
            count_out <= 16'h0;       
        end 
        else if (inc) begin
            count_out <= count_out + 1'b1;   
        end
    end

endmodule

Electronica Digital 1/ModuloTimer/Timer.v
//Modulo Top del timer 
module Timer  (
    input init_t,
    input clk,
    input [1:0] sel,
    output dout,
    output done_t
);

    wire [15:0]out;
    wire inc;
    wire rst;
    wire z;
    parameter [15:0] T0h = 16'd10;
    parameter [15:0] T1h = 16'd20;
    parameter [15:0] Res = 16'd1250;
    parameter [15:0] Per = 16'd31;
    wire [1:0]sel_tim;
    wire [15:0]count_out;



    Count_out u_Count_out(.clk(clk),.rst(rst),.inc(inc),.count_out(count_out));

    Multiplex u_Multiplex(.T0h(T0h),.T1h(T1h),.Res(Res),.Per(Per),.sel_tim(sel_tim),.out(out));

    Control_Timer u_Control_Timer(.clk(clk),.z(z),.sel(sel),.init_t(init_t),.dout(dout),.done(done_t),.rst(rst),.inc(inc),.sel_tim(sel_tim));
    
    Comp u_Comp(.a(out),.b(count_out),.z(z));

endmodule

Electronica Digital 1/ModuloTimer/Timer_TB.v
`timescale 1ns / 1ps

module Timer_TB;

    reg clk;
    reg init_t;
    reg [1:0] sel;
    wire dout;
    wire done_t;


    Timer uut (.clk(clk),.init_t(init_t),.sel(sel),.dout(dout),.done_t(done_t));

    always begin
        #10 clk = ~clk;
    end


    initial begin
        #5000000; 
        $display("\n[ERROR] TIMEOUT: La simulación se atascó esperando done_t.");
        $display("Forzando cierre para que puedas analizar el archivo en GTKWave...");
        $finish;
    end

    initial begin
        $display("=== TESTBENCH INTEGRADO DEL TIMER ===");
        clk = 0;
        init_t = 0;
        sel = 2'b00;
        #100;

        $display("\n--- Caso de Prueba 1: Bit 0 (sel = 00) ---");
        @(posedge clk);
        sel = 2'b00;
        init_t = 1;
        @(posedge clk);
        init_t = 0;

        @(posedge done_t); 
        #40; 

        $display("\n--- Caso de Prueba 2: Bit 1 (sel = 01) ---");
        @(posedge clk);
        sel = 2'b01;
        init_t = 1;
        @(posedge clk);
        init_t = 0;

        @(posedge done_t);
        #40;

        $display("\n--- Caso de Prueba 3: Reset de Linea (sel = 10) ---");
        @(posedge clk);
        sel = 2'b10;
        init_t = 1;
        @(posedge clk);
        init_t = 0;

        @(posedge done_t); 
        #40;

        $display("\n=== SIMULACION COMPLETA DEL TIMER CONCLUIDA CON EXITO ===");
        $finish;
    end

    initial begin: TEST_CASE
        $dumpfile("Timer_TB.vcd");
        $dumpvars(-1, uut); 
    end

endmodule

Electronica Digital 1/ModuloTimer/Timer_TB.vcd
$date
	Wed Jul 15 12:39:59 2026
$end
$version
	Icarus Verilog
$end
$timescale
	1ps
$end
$scope module Timer_TB $end
$scope module uut $end
$var wire 1 ! clk $end
$var wire 1 " init_t $end
$var wire 2 # sel [1:0] $end
$var wire 1 $ z $end
$var wire 2 % sel_tim [1:0] $end
$var wire 1 & rst $end
$var wire 16 ' out [15:0] $end
$var wire 1 ( inc $end
$var wire 1 ) dout $end
$var wire 1 * done_t $end
$var wire 16 + count_out [15:0] $end
$var parameter 16 , Per $end
$var parameter 16 - Res $end
$var parameter 16 . T0h $end
$var parameter 16 / T1h $end
$scope module u_Comp $end
$var wire 16 0 b [15:0] $end
$var wire 16 1 a [15:0] $end
$var reg 1 $ z $end
$upscope $end
$scope module u_Control_Timer $end
$var wire 1 ! clk $end
$var wire 1 " init_t $end
$var wire 2 2 sel [1:0] $end
$var wire 1 $ z $end
$var parameter 4 3 CHECK1 $end
$var parameter 4 4 CHECK2 $end
$var parameter 4 5 CHECK3 $end
$var parameter 4 6 CHECK4 $end
$var parameter 4 7 CHECK5 $end
$var parameter 4 8 COUNT1 $end
$var parameter 4 9 COUNT2 $end
$var parameter 4 : COUNT3 $end
$var parameter 4 ; DONE $end
$var parameter 4 < DOUT1 $end
$var parameter 4 = DOUT2 $end
$var parameter 4 > DOUT3 $end
$var parameter 4 ? INIT $end
$var parameter 4 @ START $end
$var parameter 4 A T0H $end
$var parameter 4 B T1H $end
$var reg 1 * done $end
$var reg 1 ) dout $end
$var reg 1 ( inc $end
$var reg 1 & rst $end
$var reg 2 C sel_tim [1:0] $end
$var reg 4 D state [3:0] $end
$upscope $end
$scope module u_Count_out $end
$var wire 1 ! clk $end
$var wire 1 ( inc $end
$var wire 1 & rst $end
$var reg 16 E count_out [15:0] $end
$upscope $end
$scope module u_Multiplex $end
$var wire 16 F Per [15:0] $end
$var wire 16 G Res [15:0] $end
$var wire 16 H T0h [15:0] $end
$var wire 16 I T1h [15:0] $end
$var wire 2 J sel_tim [1:0] $end
$var reg 16 K out [15:0] $end
$upscope $end
$upscope $end
$upscope $end
$enddefinitions $end
$comment Show the parameter values. $end
$dumpall
b101 B
b100 A
b0 @
b10 ?
b1000 >
b111 =
b110 <
b1111 ;
b1100 :
b1011 9
b1001 8
b1110 7
b1101 6
b1010 5
b11 4
b1 3
b10100 /
b1010 .
b10011100010 -
b11111 ,
$end
#0
$dumpvars
b1010 K
bx J
b10100 I
b1010 H
b10011100010 G
b11111 F
bx E
bx D
bx C
b0 2
b1010 1
bx 0
bx +
x*
x)
x(
b1010 '
x&
bx %
x$
b0 #
0"
0!
$end
#10000
b0 %
b0 C
b0 J
0(
0&
0*
0)
b0 D
1!
#20000
0!
#30000
b1 D
1!
#40000
0!
#50000
1!
#60000
0!
#70000
1!
#80000
0!
#90000
1!
#100000
0!
#110000
1&
b10 D
1"
1!
#120000
0$
b0 +
b0 0
b0 E
0!
#130000
0&
b11 D
0"
1!
#140000
0!
#150000
b100 D
1!
#160000
0!
#170000
1)
b111 D
1!
#180000
0!
#190000
1(
b1001 D
1!
#200000
b1 +
b1 0
b1 E
0!
#210000
0(
b1010 D
1!
#220000
0!
#230000
1(
b1001 D
1!
#240000
b10 +
b10 0
b10 E
0!
#250000
0(
b1010 D
1!
#260000
0!
#270000
1(
b1001 D
1!
#280000
b11 +
b11 0
b11 E
0!
#290000
0(
b1010 D
1!
#300000
0!
#310000
1(
b1001 D
1!
#320000
b100 +
b100 0
b100 E
0!
#330000
0(
b1010 D
1!
#340000
0!
#350000
1(
b1001 D
1!
#360000
b101 +
b101 0
b101 E
0!
#370000
0(
b1010 D
1!
#380000
0!
#390000
1(
b1001 D
1!
#400000
b110 +
b110 0
b110 E
0!
#410000
0(
b1010 D
1!
#420000
0!
#430000
1(
b1001 D
1!
#440000
b111 +
b111 0
b111 E
0!
#450000
0(
b1010 D
1!
#460000
0!
#470000
1(
b1001 D
1!
#480000
b1000 +
b1000 0
b1000 E
0!
#490000
0(
b1010 D
1!
#500000
0!
#510000
1(
b1001 D
1!
#520000
b1001 +
b1001 0
b1001 E
0!
#530000
0(
b1010 D
1!
#540000
0!
#550000
1(
b1001 D
1!
#560000
1$
b1010 +
b1010 0
b1010 E
0!
#570000
0(
b1010 D
1!
#580000
0!
#590000
0$
b11111 '
b11111 1
b11111 K
b11 %
b11 C
b11 J
1(
0)
b1011 D
1!
#600000
b1011 +
b1011 0
b1011 E
0!
#610000
0(
b1110 D
1!
#620000
0!
#630000
1(
b1011 D
1!
#640000
b1100 +
b1100 0
b1100 E
0!
#650000
0(
b1110 D
1!
#660000
0!
#670000
1(
b1011 D
1!
#680000
b1101 +
b1101 0
b1101 E
0!
#690000
0(
b1110 D
1!
#700000
0!
#710000
1(
b1011 D
1!
#720000
b1110 +
b1110 0
b1110 E
0!
#730000
0(
b1110 D
1!
#740000
0!
#750000
1(
b1011 D
1!
#760000
b1111 +
b1111 0
b1111 E
0!
#770000
0(
b1110 D
1!
#780000
0!
#790000
1(
b1011 D
1!
#800000
b10000 +
b10000 0
b10000 E
0!
#810000
0(
b1110 D
1!
#820000
0!
#830000
1(
b1011 D
1!
#840000
b10001 +
b10001 0
b10001 E
0!
#850000
0(
b1110 D
1!
#860000
0!
#870000
1(
b1011 D
1!
#880000
b10010 +
b10010 0
b10010 E
0!
#890000
0(
b1110 D
1!
#900000
0!
#910000
1(
b1011 D
1!
#920000
b10011 +
b10011 0
b10011 E
0!
#930000
0(
b1110 D
1!
#940000
0!
#950000
1(
b1011 D
1!
#960000
b10100 +
b10100 0
b10100 E
0!
#970000
0(
b1110 D
1!
#980000
0!
#990000
1(
b1011 D
1!
#1000000
b10101 +
b10101 0
b10101 E
0!
#1010000
0(
b1110 D
1!
#1020000
0!
#1030000
1(
b1011 D
1!
#1040000
b10110 +
b10110 0
b10110 E
0!
#1050000
0(
b1110 D
1!
#1060000
0!
#1070000
1(
b1011 D
1!
#1080000
b10111 +
b10111 0
b10111 E
0!
#1090000
0(
b1110 D
1!
#1100000
0!
#1110000
1(
b1011 D
1!
#1120000
b11000 +
b11000 0
b11000 E
0!
#1130000
0(
b1110 D
1!
#1140000
0!
#1150000
1(
b1011 D
1!
#1160000
b11001 +
b11001 0
b11001 E
0!
#1170000
0(
b1110 D
1!
#1180000
0!
#1190000
1(
b1011 D
1!
#1200000
b11010 +
b11010 0
b11010 E
0!
#1210000
0(
b1110 D
1!
#1220000
0!
#1230000
1(
b1011 D
1!
#1240000
b11011 +
b11011 0
b11011 E
0!
#1250000
0(
b1110 D
1!
#1260000
0!
#1270000
1(
b1011 D
1!
#1280000
b11100 +
b11100 0
b11100 E
0!
#1290000
0(
b1110 D
1!
#1300000
0!
#1310000
1(
b1011 D
1!
#1320000
b11101 +
b11101 0
b11101 E
0!
#1330000
0(
b1110 D
1!
#1340000
0!
#1350000
1(
b1011 D
1!
#1360000
b11110 +
b11110 0
b11110 E
0!
#1370000
0(
b1110 D
1!
#1380000
0!
#1390000
1(
b1011 D
1!
#1400000
1$
b11111 +
b11111 0
b11111 E
0!
#1410000
0(
b1110 D
1!
#1420000
0!
#1430000
0$
b1010 '
b1010 1
b1010 K
b0 %
b0 C
b0 J
1*
b1111 D
1!
#1440000
0!
#1450000
0*
b0 D
1!
#1460000
0!
#1470000
b1 D
1"
b1 #
b1 2
1!
#1480000
0!
#1490000
1&
b10 D
0"
1!
#1500000
b0 +
b0 0
b0 E
0!
#1510000
0&
b11 D
1!
#1520000
0!
#1530000
b10100 '
b10100 1
b10100 K
b1 %
b1 C
b1 J
b101 D
1!
#1540000
0!
#1550000
b1010 '
b1010 1
b1010 K
b0 %
b0 C
b0 J
1)
b111 D
1!
#1560000
0!
#1570000
1(
b1001 D
1!
#1580000
b1 +
b1 0
b1 E
0!
#1590000
0(
b1010 D
1!
#1600000
0!
#1610000
1(
b1001 D
1!
#1620000
b10 +
b10 0
b10 E
0!
#1630000
0(
b1010 D
1!
#1640000
0!
#1650000
1(
b1001 D
1!
#1660000
b11 +
b11 0
b11 E
0!
#1670000
0(
b1010 D
1!
#1680000
0!
#1690000
1(
b1001 D
1!
#1700000
b100 +
b100 0
b100 E
0!
#1710000
0(
b1010 D
1!
#1720000
0!
#1730000
1(
b1001 D
1!
#1740000
b101 +
b101 0
b101 E
0!
#1750000
0(
b1010 D
1!
#1760000
0!
#1770000
1(
b1001 D
1!
#1780000
b110 +
b110 0
b110 E
0!
#1790000
0(
b1010 D
1!
#1800000
0!
#1810000
1(
b1001 D
1!
#1820000
b111 +
b111 0
b111 E
0!
#1830000
0(
b1010 D
1!
#1840000
0!
#1850000
1(
b1001 D
1!
#1860000
b1000 +
b1000 0
b1000 E
0!
#1870000
0(
b1010 D
1!
#1880000
0!
#1890000
1(
b1001 D
1!
#1900000
b1001 +
b1001 0
b1001 E
0!
#1910000
0(
b1010 D
1!
#1920000
0!
#1930000
1(
b1001 D
1!
#1940000
1$
b1010 +
b1010 0
b1010 E
0!
#1950000
0(
b1010 D
1!
#1960000
0!
#1970000
0$
b11111 '
b11111 1
b11111 K
b11 %
b11 C
b11 J
1(
0)
b1011 D
1!
#1980000
b1011 +
b1011 0
b1011 E
0!
#1990000
0(
b1110 D
1!
#2000000
0!
#2010000
1(
b1011 D
1!
#2020000
b1100 +
b1100 0
b1100 E
0!
#2030000
0(
b1110 D
1!
#2040000
0!
#2050000
1(
b1011 D
1!
#2060000
b1101 +
b1101 0
b1101 E
0!
#2070000
0(
b1110 D
1!
#2080000
0!
#2090000
1(
b1011 D
1!
#2100000
b1110 +
b1110 0
b1110 E
0!
#2110000
0(
b1110 D
1!
#2120000
0!
#2130000
1(
b1011 D
1!
#2140000
b1111 +
b1111 0
b1111 E
0!
#2150000
0(
b1110 D
1!
#2160000
0!
#2170000
1(
b1011 D
1!
#2180000
b10000 +
b10000 0
b10000 E
0!
#2190000
0(
b1110 D
1!
#2200000
0!
#2210000
1(
b1011 D
1!
#2220000
b10001 +
b10001 0
b10001 E
0!
#2230000
0(
b1110 D
1!
#2240000
0!
#2250000
1(
b1011 D
1!
#2260000
b10010 +
b10010 0
b10010 E
0!
#2270000
0(
b1110 D
1!
#2280000
0!
#2290000
1(
b1011 D
1!
#2300000
b10011 +
b10011 0
b10011 E
0!
#2310000
0(
b1110 D
1!
#2320000
0!
#2330000
1(
b1011 D
1!
#2340000
b10100 +
b10100 0
b10100 E
0!
#2350000
0(
b1110 D
1!
#2360000
0!
#2370000
1(
b1011 D
1!
#2380000
b10101 +
b10101 0
b10101 E
0!
#2390000
0(
b1110 D
1!
#2400000
0!
#2410000
1(
b1011 D
1!
#2420000
b10110 +
b10110 0
b10110 E
0!
#2430000
0(
b1110 D
1!
#2440000
0!
#2450000
1(
b1011 D
1!
#2460000
b10111 +
b10111 0
b10111 E
0!
#2470000
0(
b1110 D
1!
#2480000
0!
#2490000
1(
b1011 D
1!
#2500000
b11000 +
b11000 0
b11000 E
0!
#2510000
0(
b1110 D
1!
#2520000
0!
#2530000
1(
b1011 D
1!
#2540000
b11001 +
b11001 0
b11001 E
0!
#2550000
0(
b1110 D
1!
#2560000
0!
#2570000
1(
b1011 D
1!
#2580000
b11010 +
b11010 0
b11010 E
0!
#2590000
0(
b1110 D
1!
#2600000
0!
#2610000
1(
b1011 D
1!
#2620000
b11011 +
b11011 0
b11011 E
0!
#2630000
0(
b1110 D
1!
#2640000
0!
#2650000
1(
b1011 D
1!
#2660000
b11100 +
b11100 0
b11100 E
0!
#2670000
0(
b1110 D
1!
#2680000
0!
#2690000
1(
b1011 D
1!
#2700000
b11101 +
b11101 0
b11101 E
0!
#2710000
0(
b1110 D
1!
#2720000
0!
#2730000
1(
b1011 D
1!
#2740000
b11110 +
b11110 0
b11110 E
0!
#2750000
0(
b1110 D
1!
#2760000
0!
#2770000
1(
b1011 D
1!
#2780000
1$
b11111 +
b11111 0
b11111 E
0!
#2790000
0(
b1110 D
1!
#2800000
0!
#2810000
0$
b1010 '
b1010 1
b1010 K
b0 %
b0 C
b0 J
1*
b1111 D
1!
#2820000
0!
#2830000
0*
b0 D
1!
#2840000
0!
#2850000
b1 D
1"
b10 #
b10 2
1!
#2860000
0!
#2870000
1&
b10 D
0"
1!
#2880000
b0 +
b0 0
b0 E
0!
#2890000
0&
b11 D
1!
#2900000
0!
#2910000
b10011100010 '
b10011100010 1
b10011100010 K
b10 %
b10 C
b10 J
b110 D
1!
#2920000
0!
#2930000
b1010 '
b1010 1
b1010 K
b0 %
b0 C
b0 J
b1000 D
1!
#2940000
0!
#2950000
b10011100010 '
b10011100010 1
b10011100010 K
b10 %
b10 C
b10 J
1(
b1100 D
1!
#2960000
b1 +
b1 0
b1 E
0!
#2970000
0(
b1101 D
1!
#2980000
0!
#2990000
1(
b1100 D
1!
#3000000
b10 +
b10 0
b10 E
0!
#3010000
0(
b1101 D
1!
#3020000
0!
#3030000
1(
b1100 D
1!
#3040000
b11 +
b11 0
b11 E
0!
#3050000
0(
b1101 D
1!
#3060000
0!
#3070000
1(
b1100 D
1!
#3080000
b100 +
b100 0
b100 E
0!
#3090000
0(
b1101 D
1!
#3100000
0!
#3110000
1(
b1100 D
1!
#3120000
b101 +
b101 0
b101 E
0!
#3130000
0(
b1101 D
1!
#3140000
0!
#3150000
1(
b1100 D
1!
#3160000
b110 +
b110 0
b110 E
0!
#3170000
0(
b1101 D
1!
#3180000
0!
#3190000
1(
b1100 D
1!
#3200000
b111 +
b111 0
b111 E
0!
#3210000
0(
b1101 D
1!
#3220000
0!
#3230000
1(
b1100 D
1!
#3240000
b1000 +
b1000 0
b1000 E
0!
#3250000
0(
b1101 D
1!
#3260000
0!
#3270000
1(
b1100 D
1!
#3280000
b1001 +
b1001 0
b1001 E
0!
#3290000
0(
b1101 D
1!
#3300000
0!
#3310000
1(
b1100 D
1!
#3320000
b1010 +
b1010 0
b1010 E
0!
#3330000
0(
b1101 D
1!
#3340000
0!
#3350000
1(
b1100 D
1!
#3360000
b1011 +
b1011 0
b1011 E
0!
#3370000
0(
b1101 D
1!
#3380000
0!
#3390000
1(
b1100 D
1!
#3400000
b1100 +
b1100 0
b1100 E
0!
#3410000
0(
b1101 D
1!
#3420000
0!
#3430000
1(
b1100 D
1!
#3440000
b1101 +
b1101 0
b1101 E
0!
#3450000
0(
b1101 D
1!
#3460000
0!
#3470000
1(
b1100 D
1!
#3480000
b1110 +
b1110 0
b1110 E
0!
#3490000
0(
b1101 D
1!
#3500000
0!
#3510000
1(
b1100 D
1!
#3520000
b1111 +
b1111 0
b1111 E
0!
#3530000
0(
b1101 D
1!
#3540000
0!
#3550000
1(
b1100 D
1!
#3560000
b10000 +
b10000 0
b10000 E
0!
#3570000
0(
b1101 D
1!
#3580000
0!
#3590000
1(
b1100 D
1!
#3600000
b10001 +
b10001 0
b10001 E
0!
#3610000
0(
b1101 D
1!
#3620000
0!
#3630000
1(
b1100 D
1!
#3640000
b10010 +
b10010 0
b10010 E
0!
#3650000
0(
b1101 D
1!
#3660000
0!
#3670000
1(
b1100 D
1!
#3680000
b10011 +
b10011 0
b10011 E
0!
#3690000
0(
b1101 D
1!
#3700000
0!
#3710000
1(
b1100 D
1!
#3720000
b10100 +
b10100 0
b10100 E
0!
#3730000
0(
b1101 D
1!
#3740000
0!
#3750000
1(
b1100 D
1!
#3760000
b10101 +
b10101 0
b10101 E
0!
#3770000
0(
b1101 D
1!
#3780000
0!
#3790000
1(
b1100 D
1!
#3800000
b10110 +
b10110 0
b10110 E
0!
#3810000
0(
b1101 D
1!
#3820000
0!
#3830000
1(
b1100 D
1!
#3840000
b10111 +
b10111 0
b10111 E
0!
#3850000
0(
b1101 D
1!
#3860000
0!
#3870000
1(
b1100 D
1!
#3880000
b11000 +
b11000 0
b11000 E
0!
#3890000
0(
b1101 D
1!
#3900000
0!
#3910000
1(
b1100 D
1!
#3920000
b11001 +
b11001 0
b11001 E
0!
#3930000
0(
b1101 D
1!
#3940000
0!
#3950000
1(
b1100 D
1!
#3960000
b11010 +
b11010 0
b11010 E
0!
#3970000
0(
b1101 D
1!
#3980000
0!
#3990000
1(
b1100 D
1!
#4000000
b11011 +
b11011 0
b11011 E
0!
#4010000
0(
b1101 D
1!
#4020000
0!
#4030000
1(
b1100 D
1!
#4040000
b11100 +
b11100 0
b11100 E
0!
#4050000
0(
b1101 D
1!
#4060000
0!
#4070000
1(
b1100 D
1!
#4080000
b11101 +
b11101 0
b11101 E
0!
#4090000
0(
b1101 D
1!
#4100000
0!
#4110000
1(
b1100 D
1!
#4120000
b11110 +
b11110 0
b11110 E
0!
#4130000
0(
b1101 D
1!
#4140000
0!
#4150000
1(
b1100 D
1!
#4160000
b11111 +
b11111 0
b11111 E
0!
#4170000
0(
b1101 D
1!
#4180000
0!
#4190000
1(
b1100 D
1!
#4200000
b100000 +
b100000 0
b100000 E
0!
#4210000
0(
b1101 D
1!
#4220000
0!
#4230000
1(
b1100 D
1!
#4240000
b100001 +
b100001 0
b100001 E
0!
#4250000
0(
b1101 D
1!
#4260000
0!
#4270000
1(
b1100 D
1!
#4280000
b100010 +
b100010 0
b100010 E
0!
#4290000
0(
b1101 D
1!
#4300000
0!
#4310000
1(
b1100 D
1!
#4320000
b100011 +
b100011 0
b100011 E
0!
#4330000
0(
b1101 D
1!
#4340000
0!
#4350000
1(
b1100 D
1!
#4360000
b100100 +
b100100 0
b100100 E
0!
#4370000
0(
b1101 D
1!
#4380000
0!
#4390000
1(
b1100 D
1!
#4400000
b100101 +
b100101 0
b100101 E
0!
#4410000
0(
b1101 D
1!
#4420000
0!
#4430000
1(
b1100 D
1!
#4440000
b100110 +
b100110 0
b100110 E
0!
#4450000
0(
b1101 D
1!
#4460000
0!
#4470000
1(
b1100 D
1!
#4480000
b100111 +
b100111 0
b100111 E
0!
#4490000
0(
b1101 D
1!
#4500000
0!
#4510000
1(
b1100 D
1!
#4520000
b101000 +
b101000 0
b101000 E
0!
#4530000
0(
b1101 D
1!
#4540000
0!
#4550000
1(
b1100 D
1!
#4560000
b101001 +
b101001 0
b101001 E
0!
#4570000
0(
b1101 D
1!
#4580000
0!
#4590000
1(
b1100 D
1!
#4600000
b101010 +
b101010 0
b101010 E
0!
#4610000
0(
b1101 D
1!
#4620000
0!
#4630000
1(
b1100 D
1!
#4640000
b101011 +
b101011 0
b101011 E
0!
#4650000
0(
b1101 D
1!
#4660000
0!
#4670000
1(
b1100 D
1!
#4680000
b101100 +
b101100 0
b101100 E
0!
#4690000
0(
b1101 D
1!
#4700000
0!
#4710000
1(
b1100 D
1!
#4720000
b101101 +
b101101 0
b101101 E
0!
#4730000
0(
b1101 D
1!
#4740000
0!
#4750000
1(
b1100 D
1!
#4760000
b101110 +
b101110 0
b101110 E
0!
#4770000
0(
b1101 D
1!
#4780000
0!
#4790000
1(
b1100 D
1!
#4800000
b101111 +
b101111 0
b101111 E
0!
#4810000
0(
b1101 D
1!
#4820000
0!
#4830000
1(
b1100 D
1!
#4840000
b110000 +
b110000 0
b110000 E
0!
#4850000
0(
b1101 D
1!
#4860000
0!
#4870000
1(
b1100 D
1!
#4880000
b110001 +
b110001 0
b110001 E
0!
#4890000
0(
b1101 D
1!
#4900000
0!
#4910000
1(
b1100 D
1!
#4920000
b110010 +
b110010 0
b110010 E
0!
#4930000
0(
b1101 D
1!
#4940000
0!
#4950000
1(
b1100 D
1!
#4960000
b110011 +
b110011 0
b110011 E
0!
#4970000
0(
b1101 D
1!
#4980000
0!
#4990000
1(
b1100 D
1!
#5000000
b110100 +
b110100 0
b110100 E
0!
#5010000
0(
b1101 D
1!
#5020000
0!
#5030000
1(
b1100 D
1!
#5040000
b110101 +
b110101 0
b110101 E
0!
#5050000
0(
b1101 D
1!
#5060000
0!
#5070000
1(
b1100 D
1!
#5080000
b110110 +
b110110 0
b110110 E
0!
#5090000
0(
b1101 D
1!
#5100000
0!
#5110000
1(
b1100 D
1!
#5120000
b110111 +
b110111 0
b110111 E
0!
#5130000
0(
b1101 D
1!
#5140000
0!
#5150000
1(
b1100 D
1!
#5160000
b111000 +
b111000 0
b111000 E
0!
#5170000
0(
b1101 D
1!
#5180000
0!
#5190000
1(
b1100 D
1!
#5200000
b111001 +
b111001 0
b111001 E
0!
#5210000
0(
b1101 D
1!
#5220000
0!
#5230000
1(
b1100 D
1!
#5240000
b111010 +
b111010 0
b111010 E
0!
#5250000
0(
b1101 D
1!
#5260000
0!
#5270000
1(
b1100 D
1!
#5280000
b111011 +
b111011 0
b111011 E
0!
#5290000
0(
b1101 D
1!
#5300000
0!
#5310000
1(
b1100 D
1!
#5320000
b111100 +
b111100 0
b111100 E
0!
#5330000
0(
b1101 D
1!
#5340000
0!
#5350000
1(
b1100 D
1!
#5360000
b111101 +
b111101 0
b111101 E
0!
#5370000
0(
b1101 D
1!
#5380000
0!
#5390000
1(
b1100 D
1!
#5400000
b111110 +
b111110 0
b111110 E
0!
#5410000
0(
b1101 D
1!
#5420000
0!
#5430000
1(
b1100 D
1!
#5440000
b111111 +
b111111 0
b111111 E
0!
#5450000
0(
b1101 D
1!
#5460000
0!
#5470000
1(
b1100 D
1!
#5480000
b1000000 +
b1000000 0
b1000000 E
0!
#5490000
0(
b1101 D
1!
#5500000
0!
#5510000
1(
b1100 D
1!
#5520000
b1000001 +
b1000001 0
b1000001 E
0!
#5530000
0(
b1101 D
1!
#5540000
0!
#5550000
1(
b1100 D
1!
#5560000
b1000010 +
b1000010 0
b1000010 E
0!
#5570000
0(
b1101 D
1!
#5580000
0!
#5590000
1(
b1100 D
1!
#5600000
b1000011 +
b1000011 0
b1000011 E
0!
#5610000
0(
b1101 D
1!
#5620000
0!
#5630000
1(
b1100 D
1!
#5640000
b1000100 +
b1000100 0
b1000100 E
0!
#5650000
0(
b1101 D
1!
#5660000
0!
#5670000
1(
b1100 D
1!
#5680000
b1000101 +
b1000101 0
b1000101 E
0!
#5690000
0(
b1101 D
1!
#5700000
0!
#5710000
1(
b1100 D
1!
#5720000
b1000110 +
b1000110 0
b1000110 E
0!
#5730000
0(
b1101 D
1!
#5740000
0!
#5750000
1(
b1100 D
1!
#5760000
b1000111 +
b1000111 0
b1000111 E
0!
#5770000
0(
b1101 D
1!
#5780000
0!
#5790000
1(
b1100 D
1!
