Electronica Digital 1/ModuloDivision/Control_Div.v
module Control_Div(
    input clk,
    input rst,
    input init,
    input i_eq_zero,
    input res_min_a,
    output reg load,
    output reg assi,
    output reg subs,
    output reg decrease,
    output reg shift,
    output reg done
    );
    
    parameter START      = 4'b0000; 
    parameter CHECK1     = 4'b0001; 
    parameter LOAD       = 4'b0010; 
    parameter SHIFT      = 4'b0011; 
    parameter CHECK2     = 4'b0100; 
    parameter ASSIGN1    = 4'b0101; 
    parameter ASSIGN2    = 4'b0110; 
    parameter SUBS       = 4'b0111; 
    parameter DECREASE   = 4'b1000; 
    parameter CHECK3     = 4'b1001; 
    parameter FINISH     = 4'b1010; 
    
    reg [3:0] state;

    always @(*) begin
        case (state)

            START: begin
                load      =  0;
                shift     =  0;
                decrease  =  0;
                subs      =  0;
                assi      =  0;
                done      =  0;                   
            end

            CHECK1: begin
                load      =  0;
                shift     =  0;
                decrease  =  0;
                subs      =  0;
                assi      =  0;
                done      =  0;
            end 

            LOAD: begin
                load      =  1;
                shift     =  0;
                decrease  =  0;
                subs      =  0;
                assi      =  0;
                done      =  0; 
            end


            SHIFT: begin
                load      =  0;
                shift     =  1;
                decrease  =  0;
                subs      =  0;
                assi      =  0;
                done      =  0;  
            end

            CHECK2: begin
                load      =  0;
                shift     =  0;
                decrease  =  0;
                subs      =  0;
                assi      =  0;
                done      =  0; 
            end

            ASSIGN1: begin
                load      =  0;
                shift     =  0;
                decrease  =  0;
                subs      =  0;
                assi      =  1;
                done      =  0;  
            end

            ASSIGN2: begin
                load      =  0;
                shift     =  0;
                decrease  =  0;
                subs      =  0;
                assi      =  1;                
                done      =  0;  
            end

            SUBS: begin
                load      =  0;
                shift     =  0;
                decrease  =  0;
                subs      =  1;
                assi      =  0;
                done      =  0;    
            end

            DECREASE: begin
                load      =  0;
                shift     =  0;
                decrease  =  1;
                subs      =  0;
                assi      =  0;
                done      =  0;  
            end

            CHECK3: begin
                load      =  0;
                shift     =  0;
                decrease  =  0;
                subs      =  0;
                assi      =  0;
                done      =  0; 
            end

            FINISH: begin
                load      =  0;
                shift     =  0;
                decrease  =  0;
                subs      =  0;
                assi      =  0;
                done      =  1; 
            end

            default: begin
                load      =  0;
                shift     =  0;
                decrease  =  0;
                subs      =  0;
                assi      =  0;
                done      =  0;               
            end
        endcase
    end


 always @(posedge clk) begin
        if (rst) begin
            state <= START; 
        end 
        else begin
            case (state)
                START: begin
                    state <= CHECK1;
                end

                CHECK1: begin
                    if (init)
                        state <= LOAD;
                    else
                        state <= CHECK1;
                end

                LOAD: begin
                    state <= SHIFT; 
                end

                
                SHIFT: begin
                    state <= CHECK2; 
                end

                CHECK2: begin
                    if (res_min_a)
                        state <= ASSIGN1;
                    else
                        state <= ASSIGN2; 
                end

                ASSIGN1: begin
                     state <= DECREASE;
                end

                ASSIGN2: begin
                    state <= SUBS; 
                end
              
                SUBS: begin
                    state <= DECREASE; 
                end

                DECREASE: begin
                    state <= CHECK3; 
                end

                CHECK3: begin
                    if (i_eq_zero)
                        state <= FINISH;
                    else
                        state <= SHIFT;     
                end

                FINISH: begin
                    state <= START; 
                end
              
                default: begin
                    state <= START;
                end

            endcase
        end
    end
endmodule

Electronica Digital 1/ModuloDivision/Comp.v
//Modulo que compara dos valores dependendiendo de lo que se requiera comparar

module Comp(
    input[15:0] a,
    input [15:0] b,
    output reg igual,
    output reg menor
);

    always @(*) begin
        igual = (a == b);
        menor = (a<b); 
    end


endmodule

Electronica Digital 1/ModuloDivision/Decrease.v
// Modulo de incremento I
module Decrease (
    input clk,
    input load,         
    input decrease,     
    output reg [5:0] i 
);

   
    always @(negedge clk) begin
        if (load) begin
            i <= 4'd15;       
        end 
        else if (decrease) begin
            i <= i - 1'b1;   
        end
    end

endmodule

Electronica Digital 1/ModuloDivision/Sum.v
// Modulo de sumatoria
module Sum (
    input clk,
    input load,
    input [15:0]x,         
    input sum,          
    input [15:0] y,
    output reg [31:0] S 
);

    
    always @(negedge clk) begin
        if (load) begin
            S <= 32'h00000000;
            S <= x;    
        end 
        else if (sum) begin
            S <= S + y;          
        end
    end

endmodule

Electronica Digital 1/ModuloDivision/Complement_A2.v
// Modulo que devuelve el complemento a2 de un numero
module Complement_A2 (
    input [15:0] A,
    output  reg [15:0] CA2   
);

    always @(*) begin
        CA2 = (~A) + 1'b1;  
    end

endmodule

Electronica Digital 1/ModuloDivision/Asign.v
//Modulo asigna otro valor al arreglo Cc que tiene el cociente de la division

module Asign (
    input [15:0] arr,
    input value,
    output reg [15:0] arr_out
);

    always @(*) begin
        arr_out = arr;
        arr_out[0]=~value; 
    end


endmodule

Electronica Digital 1/ModuloDivision/Shift.v
// Modulo de corrimiento a la izquierda
module Shift(
    input clk,
    input load,
    input [31:0] arr,
    input shift,
    output reg [31:0] arr_corr 
);

  
    always @(negedge clk) begin
        if (load) begin
            arr_corr <= arr;       
        end 
        else if (shift) begin
            arr_corr <= arr_corr << 1; 
        end
       
    end

endmodule

Electronica Digital 1/ModuloDivision/Division.v
// Modulo de division
module Division ( 
    input clk,
    input rst,        
    input [15:0] A,     
    input [15:0] BCc,    
    input init,         
    output [15:0] Res,
    output [15:0] BCc_out,
    output done         
);

    wire i_eq_zero;
    wire res_min_a;
    wire [15:0]W_Res1;
    wire [15:0]W_Res2;
    wire [15:0]W_BCc;
    wire load;
    wire assi;
    wire subs;
    wire decrease;
    wire shift;
    wire [15:0]CA2;
    wire [5:0]i;  


    Shift u_Shift (.clk(clk),.load(load),.arr({W_Res1,BCc}),.shift(shift),.arr_corr({W_Res2,W_BCc}));
    Comp u_Comp_1(.a(W_Res2),.b(A),.igual(),.menor(res_min_a));
    Asign u_Asign_1(.arr(W_BCc),.value(res_min_a),.arr_out(BCc_out));
    Complement_A2 u_Complement_A2(.A(A),.CA2(CA2));

    Sum u_Substrac(.clk(clk),.load(load),.sum(subs),.x(W_Res2),.y(CA2),.S(Res));

    Decrease u_Decrease(.clk(clk),.load(load),.decrease(decrease),.i(i));
    Comp u_Comp_2(.a(i),.b(1'b0),.igual(i_eq_zero),.menor());
   
    Control_Div u_Control_Div(.clk(clk),.rst(rst),.init(init),.i_eq_zero(i_eq_zero),.res_min_a(res_min_a),
    .load(load),.assi(assi),.subs(subs),.decrease(decrease),.shift(shift),.done(done));

endmodule

Electronica Digital 1/ModuloDivision/Division_TB.v
// Modulo de prueba del divisor
`timescale 1ns / 1ps

module Division_TB;
    
    reg clk;
    reg rst;        
    reg [15:0] A;     
    reg [15:0] BCc;    
    reg init;
    wire [15:0] Res;
    wire [15:0] BCc_out;    
    wire done; 
  
    Division uut (.clk(clk),.rst(rst),.A(A),.BCc(BCc),.init(init),.Res(Res),.BCc_out(BCc_out),.done(done));

    parameter PERIOD          = 20;
    parameter real DUTY_CYCLE = 0.5;
    parameter OFFSET          = 0;
    reg [20:0] i;
    event reset_trigger;
    event reset_done_trigger;
 

   initial begin
        clk = 0;
        rst = 1;
        init = 0;
        A = 16'd122;     
        BCc = 16'd12;    
        #20;             
        
        rst = 0;
        #20;
        
        init = 1;        
        #20;             
        init = 0;        
      
        #800;
        $finish;
    end

    initial begin 
	  forever begin 
	   @ (reset_trigger);
		@ (negedge clk);
		rst = 1;
		@ (negedge clk);
		rst = 0;
		-> reset_done_trigger;
		end
	end

    initial  begin 
     #OFFSET;
     forever
       begin
         clk = 1'b0;
         #(PERIOD-(PERIOD*DUTY_CYCLE)) clk = 1'b1;
         #(PERIOD*DUTY_CYCLE);
       end
   end


initial begin
        #10 -> reset_trigger;
        @ (reset_done_trigger);
        @ (posedge clk);
        init = 0;
        @ (posedge clk);
        init = 1;
        
        for(i=0; i<2; i=i+1) begin
         @ (posedge clk);
        end

          init = 0;
          
        for(i=0; i<17; i=i+1) begin
         @ (posedge clk);
        end

   end	

    initial begin: TEST_CASE
     $dumpfile("Division_TB.vcd");
     $dumpvars(-1, uut);
     #(100000) $finish;
   end

endmodule

Electronica Digital 1/ModuloDivision/Division_TB.vcd
$date
	Wed Jun 24 08:14:40 2026
$end
$version
	Icarus Verilog
$end
$timescale
	1ps
$end
$scope module Division_TB $end
$scope module uut $end
$var wire 16 ! A [15:0] $end
$var wire 16 " BCc [15:0] $end
$var wire 16 # W_Res1 [15:0] $end
$var wire 1 $ clk $end
$var wire 1 % init $end
$var wire 1 & rst $end
$var wire 1 ' subs $end
$var wire 1 ( shift $end
$var wire 1 ) res_min_a $end
$var wire 1 * load $end
$var wire 1 + i_eq_zero $end
$var wire 6 , i [5:0] $end
$var wire 1 - done $end
$var wire 1 . decrease $end
$var wire 1 / assi $end
$var wire 16 0 W_Res2 [15:0] $end
$var wire 16 1 W_BCc [15:0] $end
$var wire 16 2 Res [15:0] $end
$var wire 16 3 CA2 [15:0] $end
$var wire 16 4 BCc_out [15:0] $end
$scope module u_Asign_1 $end
$var wire 16 5 arr [15:0] $end
$var wire 1 ) value $end
$var reg 16 6 arr_out [15:0] $end
$upscope $end
$scope module u_Comp_1 $end
$var wire 16 7 a [15:0] $end
$var wire 16 8 b [15:0] $end
$var reg 1 9 igual $end
$var reg 1 ) menor $end
$upscope $end
$scope module u_Comp_2 $end
$var wire 16 : a [15:0] $end
$var wire 16 ; b [15:0] $end
$var reg 1 + igual $end
$var reg 1 < menor $end
$upscope $end
$scope module u_Complement_A2 $end
$var wire 16 = A [15:0] $end
$var reg 16 > CA2 [15:0] $end
$upscope $end
$scope module u_Control_Div $end
$var wire 1 $ clk $end
$var wire 1 + i_eq_zero $end
$var wire 1 % init $end
$var wire 1 ) res_min_a $end
$var wire 1 & rst $end
$var parameter 4 ? ASSIGN1 $end
$var parameter 4 @ ASSIGN2 $end
$var parameter 4 A CHECK1 $end
$var parameter 4 B CHECK2 $end
$var parameter 4 C CHECK3 $end
$var parameter 4 D DECREASE $end
$var parameter 4 E FINISH $end
$var parameter 4 F LOAD $end
$var parameter 4 G SHIFT $end
$var parameter 4 H START $end
$var parameter 4 I SUBS $end
$var reg 1 / assi $end
$var reg 1 . decrease $end
$var reg 1 - done $end
$var reg 1 * load $end
$var reg 1 ( shift $end
$var reg 4 J state [3:0] $end
$var reg 1 ' subs $end
$upscope $end
$scope module u_Decrease $end
$var wire 1 $ clk $end
$var wire 1 . decrease $end
$var wire 1 * load $end
$var reg 6 K i [5:0] $end
$upscope $end
$scope module u_Shift $end
$var wire 32 L arr [31:0] $end
$var wire 1 $ clk $end
$var wire 1 * load $end
$var wire 1 ( shift $end
$var reg 32 M arr_corr [31:0] $end
$upscope $end
$scope module u_Substrac $end
$var wire 1 $ clk $end
$var wire 1 * load $end
$var wire 1 ' sum $end
$var wire 16 N x [15:0] $end
$var wire 16 O y [15:0] $end
$var reg 32 P S [31:0] $end
$upscope $end
$upscope $end
$upscope $end
$enddefinitions $end
$comment Show the parameter values. $end
$dumpall
b111 I
b0 H
b11 G
b10 F
b1010 E
b1000 D
b1001 C
b100 B
b1 A
b110 @
b101 ?
$end
#0
$dumpvars
bx P
b1111111110000110 O
bx N
bx M
bz0000000000000101 L
bx K
bx J
b1111111110000110 >
b1111010 =
x<
b0 ;
b0xxxxxx :
x9
b1111010 8
bx 7
bx 6
bx 5
bx 4
b1111111110000110 3
bx 2
bx 1
bx 0
x/
x.
x-
bx ,
x+
x*
x)
x(
x'
1&
0%
0$
bz #
b101 "
b1111010 !
$end
#10000
0-
0/
0'
0.
0(
0*
b0 J
1$
#20000
0$
1&
#30000
1$
#40000
0&
0$
1%
#50000
b1 J
0%
1$
#60000
0$
#70000
1%
1$
#80000
0$
#90000
1*
b10 J
1$
#100000
b10x 4
b10x 6
0<
0+
b101 1
b101 5
bz 0
bz 7
bz N
b1111 :
b1111 ,
b1111 K
b0xxxxxxxxxxxxxxxx P
bz0000000000000101 M
0$
#110000
1(
0*
b11 J
0%
1$
#120000
b101x 4
b101x 6
b1010 1
b1010 5
bz0 0
bz0 7
bz0 N
bz00000000000001010 M
0$
#130000
0(
b100 J
1$
#140000
0$
#150000
1/
b110 J
1$
#160000
0$
#170000
0/
1'
b111 J
1$
#180000
bx P
0$
#190000
0'
1.
b1000 J
1$
#200000
b1110 :
b1110 ,
b1110 K
0$
#210000
0.
b1001 J
1$
#220000
0$
#230000
1(
b11 J
1$
#240000
b1010x 4
b1010x 6
09
b10100 1
b10100 5
bz00 0
bz00 7
bz00 N
bz000000000000010100 M
0$
#250000
0(
b100 J
1$
#260000
0$
#270000
1/
b110 J
1$
#280000
0$
#290000
0/
1'
b111 J
1$
#300000
0$
#310000
0'
1.
b1000 J
1$
#320000
b1101 :
b1101 ,
b1101 K
0$
#330000
0.
b1001 J
1$
#340000
0$
#350000
1(
b11 J
1$
#360000
b10100x 4
b10100x 6
b101000 1
b101000 5
bz000 0
bz000 7
bz000 N
bz0000000000000101000 M
0$
#370000
0(
b100 J
1$
#380000
0$
#390000
1/
b110 J
1$
#400000
0$
#410000
0/
1'
b111 J
1$
#420000
0$
#430000
0'
1.
b1000 J
1$
#440000
b1100 :
b1100 ,
b1100 K
0$
#450000
0.
b1001 J
1$
#460000
0$
#470000
1(
b11 J
1$
#480000
b101000x 4
b101000x 6
b1010000 1
b1010000 5
bz0000 0
bz0000 7
bz0000 N
bz00000000000001010000 M
0$
#490000
0(
b100 J
1$
#500000
0$
#510000
1/
b110 J
1$
#520000
0$
#530000
0/
1'
b111 J
1$
#540000
0$
#550000
0'
1.
b1000 J
1$
#560000
b1011 :
b1011 ,
b1011 K
0$
#570000
0.
b1001 J
1$
#580000
0$
#590000
1(
b11 J
1$
#600000
b1010000x 4
b1010000x 6
b10100000 1
b10100000 5
bz00000 0
bz00000 7
bz00000 N
bz000000000000010100000 M
0$
#610000
0(
b100 J
1$
#620000
0$
#630000
1/
b110 J
1$
#640000
0$
#650000
0/
1'
b111 J
1$
#660000
0$
#670000
0'
1.
b1000 J
1$
#680000
b1010 :
b1010 ,
b1010 K
0$
#690000
0.
b1001 J
1$
#700000
0$
#710000
1(
b11 J
1$
#720000
b10100000x 4
b10100000x 6
b101000000 1
b101000000 5
bz000000 0
bz000000 7
bz000000 N
bz0000000000000101000000 M
0$
#730000
0(
b100 J
1$
#740000
0$
#750000
1/
b110 J
1$
#760000
0$
#770000
0/
1'
b111 J
1$
#780000
0$
#790000
0'
1.
b1000 J
1$
#800000
b1001 :
b1001 ,
b1001 K
0$
#810000
0.
b1001 J
1$
#820000
0$
#830000
1(
b11 J
1$
#840000
b101000000x 4
b101000000x 6
b1010000000 1
b1010000000 5
bz0000000 0
bz0000000 7
bz0000000 N
bz00000000000001010000000 M
0$
#850000
0(
b100 J
1$
