Electronica Digital 1/ModuloDivision/Control_Div.v
module Control_Div(
    input clk,
    input rst,
    input init,
    input i_eq_zero,
    input reg_div_min_a,
    output reg load,
    output reg assi,
    output reg subs,
    output reg decrease,
    output reg shift,
    output reg done
    );
    
    parameter START      = 4'b0000; 
    parameter CHECK1     = 4'b0001; 
    parameter LOAD       = 4'b0010; 
    parameter SHIFT      = 4'b0011; 
    parameter CHECK2     = 4'b0100; 
    parameter ASSIGN1    = 4'b0101; 
    parameter ASSIGN2    = 4'b0110; 
    parameter SUBS       = 4'b0111; 
    parameter DECREASE   = 4'b1000; 
    parameter CHECK3     = 4'b1001; 
    parameter FINISH     = 4'b1010; 
    
    reg [3:0] state;

    always @(*) begin
        case (state)

            START: begin
                load      =  0;
                shift     =  0;
                decrease  =  0;
                subs      =  0;
                assi      =  0;
                done      =  0;                   
            end

            CHECK1: begin
                load      =  0;
                shift     =  0;
                decrease  =  0;
                subs      =  0;
                assi      =  0;
                done      =  0;
            end 

            LOAD: begin
                load      =  1;
                shift     =  0;
                decrease  =  0;
                subs      =  0;
                assi      =  0;
                done      =  0; 
            end


            SHIFT: begin
                load      =  0;
                shift     =  1;
                decrease  =  0;
                subs      =  0;
                assi      =  0;
                done      =  0;  
            end

            CHECK2: begin
                load      =  0;
                shift     =  0;
                decrease  =  0;
                subs      =  0;
                assi      =  0;
                done      =  0; 
            end

            ASSIGN1: begin
                load      =  0;
                shift     =  0;
                decrease  =  0;
                subs      =  0;
                assi      =  1;
                done      =  0;  
            end

            ASSIGN2: begin
                load      =  0;
                shift     =  0;
                decrease  =  0;
                subs      =  0;
                assi      =  1;                
                done      =  0;  
            end

            SUBS: begin
                load      =  0;
                shift     =  0;
                decrease  =  0;
                subs      =  1;
                assi      =  0;
                done      =  0;    
            end

            DECREASE: begin
                load      =  0;
                shift     =  0;
                decrease  =  1;
                subs      =  0;
                assi      =  0;
                done      =  0;  
            end

            CHECK3: begin
                load      =  0;
                shift     =  0;
                decrease  =  0;
                subs      =  0;
                assi      =  0;
                done      =  0; 
            end

            FINISH: begin
                load      =  0;
                shift     =  0;
                decrease  =  0;
                subs      =  0;
                assi      =  0;
                done      =  1; 
            end

            default: begin
                load      =  0;
                shift     =  0;
                decrease  =  0;
                subs      =  0;
                assi      =  0;
                done      =  0;               
            end
        endcase
    end


 always @(posedge clk) begin
        if (rst) begin
            state <= START; 
        end 
        else begin
            case (state)
                START: begin
                    state <= CHECK1;
                end

                CHECK1: begin
                    if (init)
                        state <= LOAD;
                    else
                        state <= CHECK1;
                end

                LOAD: begin
                    state <= SHIFT; 
                end

                
                SHIFT: begin
                    state <= CHECK2; 
                end

                CHECK2: begin
                    if (reg_div_min_a)
                        state <= ASSIGN1;
                    else
                        state <= ASSIGN2; 
                end

                ASSIGN1: begin
                     state <= DECREASE;
                end

                ASSIGN2: begin
                    state <= SUBS; 
                end
              
                SUBS: begin
                    state <= DECREASE; 
                end

                DECREASE: begin
                    state <= CHECK3; 
                end

                CHECK3: begin
                    if (i_eq_zero)
                        state <= FINISH;
                    else
                        state <= SHIFT;     
                end

                FINISH: begin
                    state <= START; 
                end
              
                default: begin
                    state <= START;
                end

            endcase
        end
    end
endmodule

Electronica Digital 1/ModuloDivision/Comp.v
//Modulo que compara dos valores dependendiendo de lo que se requiera comparar

module Comp(
    input[15:0] a,
    input [15:0] b,
    output reg igual,
    output reg menor
);

    always @(*) begin
        igual = (a == b);
        menor = (a<b); 
    end


endmodule

Electronica Digital 1/ModuloDivision/Decrease.v
// Modulo del decremento de i 
module Decrease (
    input clk,
    input load,         
    input decrease,     
    output reg [5:0] i 
);

   
    always @(negedge clk) begin
        if (load) begin
            i <= 6'd16;         
        end 
        else if (decrease) begin
            i <= i - 1'b1;   
        end
    end

endmodule

Electronica Digital 1/ModuloDivision/Sum.v
// Modulo de sumatoria
module Sum (
    input clk,
    input load,
    input [15:0]a,         
    input sum,          
    input [15:0]b,
    output reg [15:0] S 
);

    
    always @(negedge clk) begin
        if (load) begin
            S <= a;    
        end 
        else if (sum) begin
            S <= S + b;          
        end
    end

endmodule

Electronica Digital 1/ModuloDivision/Complement_A2.v
// Modulo que devuelve el complemento a2 de un numero
module Complement_A2 (
    input [15:0] A,
    output  reg [15:0] CA2   
);

    always @(*) begin
        CA2 = (~A) + 1'b1;  
    end

endmodule

Electronica Digital 1/ModuloDivision/Asign.v
//Modulo asigna otro valor al arreglo Cc que tiene el cociente de la division

module Asign (
    input [31:0] arr,
    input value,
    output reg [31:0] arr_out
);

    always @(*) begin
        arr_out = arr;
        arr_out[0]=~value; 
    end


endmodule

Electronica Digital 1/ModuloDivision/Shift.v
// Modulo de corrimiento a la izquierda
module Shift(
    input clk,
    input load,
    input [31:0] arr,
    input shift,
    output reg [31:0] arr_corr 
);

  
    always @(negedge clk) begin
        if (load) begin
            arr_corr <= arr;       
        end 
        else if (shift) begin
            arr_corr <= arr_corr << 1; 
        end
       
    end

endmodule

Electronica Digital 1/ModuloDivision/Division.v
// Modulo de division
module Division ( 
    input clk,
    input rst,        
    input [15:0] A,     
    input [15:0] B,    
    input init,         
    output [15:0] Res,
    output [15:0] Cc,
    output done         
);
    
    wire i_eq_zero;
    wire reg_div_min_a;
    wire load;
    wire assi;
    wire subs;
    wire decrease;
    wire shift;
    wire [15:0]CA2;
    wire [31:0]Reg_Div;
    wire [5:0]i;

  

    Shift u_Shift (.clk(clk),.load(load),.arr({16'b0,B}),.shift(shift),.arr_corr(Reg_Div));
    Comp u_Comp_1(.a(Reg_Div[31:16]),.b(A),.igual(),.menor(reg_div_min_a));
    Asign u_Asign_1(.arr(Reg_Div),.value(reg_div_min_a),.arr_out(Cc));
    Complement_A2 u_Complement_A2(.A(A),.CA2(CA2));

    Sum u_Substrac(.clk(clk),.load(load),.sum(subs),.a(Reg_Div[31:16]),.b(CA2),.S(Res));

    Decrease u_Decrease(.clk(clk),.load(load),.decrease(decrease),.i(i));
    Comp u_Comp_2(.a(i),.b(1'b0),.igual(i_eq_zero),.menor());
   
    Control_Div u_Control_Div(.clk(clk),.rst(rst),.init(init),.i_eq_zero(i_eq_zero),.reg_div_min_a(reg_div_min_a),
    .load(load),.assi(assi),.subs(subs),.decrease(decrease),.shift(shift),.done(done));

endmodule

Electronica Digital 1/ModuloDivision/Division_TB.v
// Modulo de prueba del algoritmo de Division
`timescale 1ns / 1ps

module Division_TB;
    
    reg clk;
    reg rst;
    reg [15:0] A;
    reg [15:0] B;
    reg init;
    wire [15:0] Res;
    wire [15:0] Cc;
    wire done;
  
    Division uut (.clk(clk), .rst(rst), .A(A), .B(B), .init(init), .Res(Res), .Cc(Cc), .done(done));

    parameter PERIOD = 20;

    initial begin
        clk = 0;
        forever #(PERIOD/2) clk = ~clk;
    end

    initial begin

        rst = 1;
        A = 16'd12;
        B = 16'd122;
        init = 0;
        
        #(PERIOD*2);        
        rst = 0;            
        
        #(PERIOD*2);       
        
        init = 1;           
        #(PERIOD*3);
        init = 0;           
        
        #(PERIOD*30); 

        #5000;

        #(PERIOD*2);         
        $finish;
    end

    // Captura de formas de onda
    initial begin
        $dumpfile("Division_TB.vcd");
        $dumpvars(-1, uut);
        #(100000) $finish;
    end

endmodule

Electronica Digital 1/ModuloDivision/Division_TB.vcd
$date
	Thu Jun 25 11:58:11 2026
$end
$version
	Icarus Verilog
$end
$timescale
	1ps
$end
$scope module Division_TB $end
$scope module uut $end
$var wire 16 ! A [15:0] $end
$var wire 16 " B [15:0] $end
$var wire 1 # clk $end
$var wire 1 $ init $end
$var wire 1 % rst $end
$var wire 1 & subs $end
$var wire 1 ' shift $end
$var wire 1 ( reg_div_min_a $end
$var wire 1 ) load $end
$var wire 1 * i_eq_zero $end
$var wire 6 + i [5:0] $end
$var wire 1 , done $end
$var wire 1 - decrease $end
$var wire 1 . assi $end
$var wire 16 / Res [15:0] $end
$var wire 32 0 Reg_Div [31:0] $end
$var wire 16 1 Cc [15:0] $end
$var wire 16 2 CA2 [15:0] $end
$scope module u_Asign_1 $end
$var wire 1 ( value $end
$var wire 32 3 arr [31:0] $end
$var reg 32 4 arr_out [31:0] $end
$upscope $end
$scope module u_Comp_1 $end
$var wire 16 5 a [15:0] $end
$var wire 16 6 b [15:0] $end
$var reg 1 7 igual $end
$var reg 1 ( menor $end
$upscope $end
$scope module u_Comp_2 $end
$var wire 16 8 a [15:0] $end
$var wire 16 9 b [15:0] $end
$var reg 1 * igual $end
$var reg 1 : menor $end
$upscope $end
$scope module u_Complement_A2 $end
$var wire 16 ; A [15:0] $end
$var reg 16 < CA2 [15:0] $end
$upscope $end
$scope module u_Control_Div $end
$var wire 1 # clk $end
$var wire 1 * i_eq_zero $end
$var wire 1 $ init $end
$var wire 1 ( reg_div_min_a $end
$var wire 1 % rst $end
$var parameter 4 = ASSIGN1 $end
$var parameter 4 > ASSIGN2 $end
$var parameter 4 ? CHECK1 $end
$var parameter 4 @ CHECK2 $end
$var parameter 4 A CHECK3 $end
$var parameter 4 B DECREASE $end
$var parameter 4 C FINISH $end
$var parameter 4 D LOAD $end
$var parameter 4 E SHIFT $end
$var parameter 4 F START $end
$var parameter 4 G SUBS $end
$var reg 1 . assi $end
$var reg 1 - decrease $end
$var reg 1 , done $end
$var reg 1 ) load $end
$var reg 1 ' shift $end
$var reg 4 H state [3:0] $end
$var reg 1 & subs $end
$upscope $end
$scope module u_Decrease $end
$var wire 1 # clk $end
$var wire 1 - decrease $end
$var wire 1 ) load $end
$var reg 6 I i [5:0] $end
$upscope $end
$scope module u_Shift $end
$var wire 32 J arr [31:0] $end
$var wire 1 # clk $end
$var wire 1 ) load $end
$var wire 1 ' shift $end
$var reg 32 K arr_corr [31:0] $end
$upscope $end
$scope module u_Substrac $end
$var wire 16 L a [15:0] $end
$var wire 16 M b [15:0] $end
$var wire 1 # clk $end
$var wire 1 ) load $end
$var wire 1 & sum $end
$var reg 16 N S [15:0] $end
$upscope $end
$upscope $end
$upscope $end
$enddefinitions $end
$comment Show the parameter values. $end
$dumpall
b111 G
b0 F
b11 E
b10 D
b1010 C
b1000 B
b1001 A
b100 @
b1 ?
b110 >
b101 =
$end
#0
$dumpvars
bx N
b1111111111110100 M
bx L
bx K
b10010000 J
bx I
bx H
b1111111111110100 <
b1100 ;
x:
b0 9
b0xxxxxx 8
x7
b1100 6
bx 5
bx 4
bx 3
b1111111111110100 2
bx 1
bx 0
bx /
x.
x-
x,
bx +
x*
x)
x(
x'
x&
1%
0$
0#
b10010000 "
b1100 !
$end
#10000
0,
0.
0&
0-
0'
0)
b0 H
1#
#20000
0#
1%
#30000
1#
#40000
0%
0#
1$
#50000
b1 H
0$
1#
#60000
0#
#70000
1$
1#
#80000
0#
#90000
1)
b10 H
1#
#100000
1(
07
b10010000 1
0:
0*
b0 L
b0 5
b10010000 4
b1111 8
b1111 +
b1111 I
b10010000 0
b10010000 3
b10010000 K
0#
#110000
1'
0)
b11 H
0$
1#
#120000
b100100000 1
b100100000 4
b100100000 0
b100100000 3
b100100000 K
0#
#130000
0'
b100 H
1#
#140000
0#
#150000
1.
b101 H
1#
#160000
0#
#170000
0.
1-
b1000 H
1#
#180000
b1110 8
b1110 +
b1110 I
0#
#190000
0-
b1001 H
1#
#200000
0#
#210000
1'
b11 H
1#
#220000
b1001000000 1
b1001000000 4
b1001000000 0
b1001000000 3
b1001000000 K
0#
#230000
0'
b100 H
1#
#240000
0#
#250000
1.
b101 H
1#
#260000
0#
#270000
0.
1-
b1000 H
1#
#280000
b1101 8
b1101 +
b1101 I
0#
#290000
0-
b1001 H
1#
#300000
0#
#310000
1'
b11 H
1#
#320000
b10010000000 1
b10010000000 4
b10010000000 0
b10010000000 3
b10010000000 K
0#
#330000
0'
b100 H
1#
#340000
0#
#350000
1.
b101 H
1#
#360000
0#
#370000
0.
1-
b1000 H
1#
#380000
b1100 8
b1100 +
b1100 I
0#
#390000
0-
b1001 H
1#
#400000
0#
#410000
1'
b11 H
1#
#420000
b100100000000 1
b100100000000 4
b100100000000 0
b100100000000 3
b100100000000 K
0#
#430000
0'
b100 H
1#
#440000
0#
#450000
1.
b101 H
1#
#460000
0#
#470000
0.
1-
b1000 H
1#
#480000
b1011 8
b1011 +
b1011 I
0#
#490000
0-
b1001 H
1#
#500000
0#
#510000
1'
b11 H
1#
#520000
b1001000000000 1
b1001000000000 4
b1001000000000 0
b1001000000000 3
b1001000000000 K
0#
#530000
0'
b100 H
1#
#540000
0#
#550000
1.
b101 H
1#
#560000
0#
#570000
0.
1-
b1000 H
1#
#580000
b1010 8
b1010 +
b1010 I
0#
#590000
0-
b1001 H
1#
#600000
0#
#610000
1'
b11 H
1#
#620000
b10010000000000 1
b10010000000000 4
b10010000000000 0
b10010000000000 3
b10010000000000 K
0#
#630000
0'
b100 H
1#
#640000
0#
#650000
1.
b101 H
1#
#660000
0#
#670000
0.
1-
b1000 H
1#
#680000
b1001 8
b1001 +
b1001 I
0#
#690000
0-
b1001 H
1#
#700000
0#
#710000
1'
b11 H
1#
#720000
b100100000000000 1
b100100000000000 4
b100100000000000 0
b100100000000000 3
b100100000000000 K
0#
#730000
0'
b100 H
1#
#740000
0#
#750000
1.
b101 H
1#
#760000
0#
#770000
0.
1-
b1000 H
1#
#780000
b1000 8
b1000 +
b1000 I
0#
#790000
0-
b1001 H
1#
#800000
0#
#810000
1'
b11 H
1#
#820000
b1001000000000000 1
b1001000000000000 4
b1001000000000000 0
b1001000000000000 3
b1001000000000000 K
0#
#830000
0'
b100 H
1#
#840000
0#
#850000
1.
b101 H
1#
