Electronica Digital 1/ModuloDivision/Control_Div.v
module Control_Div(
    input clk,
    input rst,
    input init,
    input i_eq_zero,
    input reg_div_min_a,
    output reg load,
    output reg assi,
    output reg subs,
    output reg decrease,
    output reg shift,
    output reg done
    );
    
    parameter START      = 4'b0000; 
    parameter CHECK1     = 4'b0001; 
    parameter LOAD       = 4'b0010; 
    parameter SHIFT      = 4'b0011; 
    parameter CHECK2     = 4'b0100; 
    parameter ASSIGN1    = 4'b0101; 
    parameter ASSIGN2    = 4'b0110; 
    parameter SUBS       = 4'b0111; 
    parameter DECREASE   = 4'b1000; 
    parameter CHECK3     = 4'b1001; 
    parameter FINISH     = 4'b1010; 
    
    reg [3:0] state;

    always @(*) begin
        case (state)

            START: begin
                load      =  0;
                shift     =  0;
                decrease  =  0;
                subs      =  0;
                assi      =  0;
                done      =  0;                   
            end

            CHECK1: begin
                load      =  0;
                shift     =  0;
                decrease  =  0;
                subs      =  0;
                assi      =  0;
                done      =  0;
            end 

            LOAD: begin
                load      =  1;
                shift     =  0;
                decrease  =  0;
                subs      =  0;
                assi      =  0;
                done      =  0; 
            end


            SHIFT: begin
                load      =  0;
                shift     =  1;
                decrease  =  0;
                subs      =  0;
                assi      =  0;
                done      =  0;  
            end

            CHECK2: begin
                load      =  0;
                shift     =  0;
                decrease  =  0;
                subs      =  0;
                assi      =  0;
                done      =  0; 
            end

            ASSIGN1: begin
                load      =  0;
                shift     =  0;
                decrease  =  0;
                subs      =  0;
                assi      =  1;
                done      =  0;  
            end

            ASSIGN2: begin
                load      =  0;
                shift     =  0;
                decrease  =  0;
                subs      =  0;
                assi      =  1;                
                done      =  0;  
            end

            SUBS: begin
                load      =  0;
                shift     =  0;
                decrease  =  0;
                subs      =  1;
                assi      =  0;
                done      =  0;    
            end

            DECREASE: begin
                load      =  0;
                shift     =  0;
                decrease  =  1;
                subs      =  0;
                assi      =  0;
                done      =  0;  
            end

            CHECK3: begin
                load      =  0;
                shift     =  0;
                decrease  =  0;
                subs      =  0;
                assi      =  0;
                done      =  0; 
            end

            FINISH: begin
                load      =  0;
                shift     =  0;
                decrease  =  0;
                subs      =  0;
                assi      =  0;
                done      =  1; 
            end

            default: begin
                load      =  0;
                shift     =  0;
                decrease  =  0;
                subs      =  0;
                assi      =  0;
                done      =  0;               
            end
        endcase
    end


 always @(posedge clk) begin
        if (rst) begin
            state <= START; 
        end 
        else begin
            case (state)
                START: begin
                    state <= CHECK1;
                end

                CHECK1: begin
                    if (init)
                        state <= LOAD;
                    else
                        state <= CHECK1;
                end

                LOAD: begin
                    state <= SHIFT; 
                end

                
                SHIFT: begin
                    state <= CHECK2; 
                end

                CHECK2: begin
                    if (reg_div_min_a)
                        state <= ASSIGN1;
                    else
                        state <= ASSIGN2; 
                end

                ASSIGN1: begin
                     state <= DECREASE;
                end

                ASSIGN2: begin
                    state <= SUBS; 
                end
              
                SUBS: begin
                    state <= DECREASE; 
                end

                DECREASE: begin
                    state <= CHECK3; 
                end

                CHECK3: begin
                    if (i_eq_zero)
                        state <= FINISH;
                    else
                        state <= SHIFT;     
                end

                FINISH: begin
                    state <= START; 
                end
              
                default: begin
                    state <= START;
                end

            endcase
        end
    end
endmodule

Electronica Digital 1/ModuloDivision/Complement_A2.v
// Modulo que devuelve el complemento a2 de un numero
module Complement_A2 (
    input [15:0] A,
    output  reg [15:0] CA2   
);

    always @(*) begin
        CA2 = (~A) + 1'b1;  
    end

endmodule

Electronica Digital 1/ModuloDivision/Comp.v
//Modulo que compara dos valores dependendiendo de lo que se requiera comparar

module Comp(
    input[15:0] a,
    input [15:0] b,
    output reg igual,
    output reg menor
);

    always @(*) begin
        igual = (a == b);
        menor = (a<b); 
    end


endmodule

Electronica Digital 1/ModuloDivision/Decrease.v
// Modulo de incremento I
module Decrease (
    input clk,
    input load,         
    input decrease,     
    output reg [5:0] i 
);

   
    always @(negedge clk) begin
        if (load) begin
            i <= 6'd16;         
        end 
        else if (decrease) begin
            i <= i - 1'b1;   
        end
    end

endmodule

Electronica Digital 1/ModuloDivision/Division.v
module Division ( 
    input clk,
    input rst,        
    input [15:0] A,     
    input [15:0] B,     
    input init,         
    output [15:0] Res, 
    output [15:0] Cc,   
    output done         
);

    wire i_eq_zero;
    wire reg_div_min_a;
    wire load;
    wire assi;
    wire subs;
    wire decrease;
    wire shift;
    wire [15:0]CA2;
    reg [31:0] Reg_Div;
    wire [5:0] i;

    Comp u_Comp_1(.a(Reg_Div[31:16]),.b(A),.igual(),.menor(reg_div_min_a));

    Decrease u_Decrease(.clk(clk),.load(load),.decrease(decrease),.i(i));

    Comp u_Comp_2(.a(i),.b(16'd0),.igual(i_eq_zero),.menor());

    Complement_A2 u_Complement_A2(.A(A),.CA2(CA2));

    Control_Div u_Control_Div(.clk(clk),.rst(rst),.init(init),.i_eq_zero(i_eq_zero),.reg_div_min_a(reg_div_min_a),.load(load),.assi(assi),.subs(subs),
    .decrease(decrease),.shift(shift),.done(done));
    
    
    always @(negedge clk or posedge rst) begin
        if (rst) begin
            Reg_Div <= 32'd0;
        end
        else if (load) begin
            Reg_Div <= {16'b0, B};
        end
        else if (shift) begin
            Reg_Div <= Reg_Div << 1;
        end
        else if (subs) begin
            Reg_Div[31:16] <= Reg_Div[31:16] + CA2;
        end
        else if (assi) begin

            if (reg_div_min_a)begin
             Reg_Div[0] <= 0;
            end
            else begin
                Reg_Div[0] <= 1;
            end

        end
    end

    assign Cc  = Reg_Div[15:0];
    assign Res = Reg_Div[31:16];

endmodule

Electronica Digital 1/ModuloDivision/Division_TB.v
// Modulo de prueba del algoritmo de Division
`timescale 1ns / 1ps

module Division_TB;
    
    reg clk;
    reg rst;
    reg [15:0] A;
    reg [15:0] B;
    reg init;
    wire [15:0] Res;
    wire [15:0] Cc;
    wire done;
  
    Division uut (.clk(clk), .rst(rst), .A(A), .B(B), .init(init), .Res(Res), .Cc(Cc), .done(done));

    parameter PERIOD = 20;

    initial begin
        clk = 0;
        forever #(PERIOD/2) clk = ~clk;
    end

    initial begin

        rst = 1;
        A = 16'd12;
        B = 16'd122;
        init = 0;
        
        #(PERIOD*2);        
        rst = 0;            
        
        #(PERIOD*2);       
        
        init = 1;           
        #(PERIOD*3);
        init = 0;           
        
        #(PERIOD*30); 

        #5000;

        #(PERIOD*2);         
        $finish;
    end

    // Captura de formas de onda
    initial begin
        $dumpfile("Division_TB.vcd");
        $dumpvars(-1, uut);
        #(100000) $finish;
    end

endmodule

Electronica Digital 1/ModuloDivision/Division_TB.vcd
$date
	Tue Jun 30 08:10:09 2026
$end
$version
	Icarus Verilog
$end
$timescale
	1ps
$end
$scope module Division_TB $end
$scope module uut $end
$var wire 16 ! A [15:0] $end
$var wire 16 " B [15:0] $end
$var wire 1 # clk $end
$var wire 1 $ init $end
$var wire 1 % rst $end
$var wire 1 & subs $end
$var wire 1 ' shift $end
$var wire 1 ( reg_div_min_a $end
$var wire 1 ) load $end
$var wire 1 * i_eq_zero $end
$var wire 6 + i [5:0] $end
$var wire 1 , done $end
$var wire 1 - decrease $end
$var wire 1 . assi $end
$var wire 16 / Res [15:0] $end
$var wire 16 0 Cc [15:0] $end
$var wire 16 1 CA2 [15:0] $end
$var reg 32 2 Reg_Div [31:0] $end
$scope module u_Comp_1 $end
$var wire 16 3 a [15:0] $end
$var wire 16 4 b [15:0] $end
$var reg 1 5 igual $end
$var reg 1 ( menor $end
$upscope $end
$scope module u_Comp_2 $end
$var wire 16 6 a [15:0] $end
$var wire 16 7 b [15:0] $end
$var reg 1 * igual $end
$var reg 1 8 menor $end
$upscope $end
$scope module u_Complement_A2 $end
$var wire 16 9 A [15:0] $end
$var reg 16 : CA2 [15:0] $end
$upscope $end
$scope module u_Control_Div $end
$var wire 1 # clk $end
$var wire 1 * i_eq_zero $end
$var wire 1 $ init $end
$var wire 1 ( reg_div_min_a $end
$var wire 1 % rst $end
$var parameter 4 ; ASSIGN1 $end
$var parameter 4 < ASSIGN2 $end
$var parameter 4 = CHECK1 $end
$var parameter 4 > CHECK2 $end
$var parameter 4 ? CHECK3 $end
$var parameter 4 @ DECREASE $end
$var parameter 4 A FINISH $end
$var parameter 4 B LOAD $end
$var parameter 4 C SHIFT $end
$var parameter 4 D START $end
$var parameter 4 E SUBS $end
$var reg 1 . assi $end
$var reg 1 - decrease $end
$var reg 1 , done $end
$var reg 1 ) load $end
$var reg 1 ' shift $end
$var reg 4 F state [3:0] $end
$var reg 1 & subs $end
$upscope $end
$scope module u_Decrease $end
$var wire 1 # clk $end
$var wire 1 - decrease $end
$var wire 1 ) load $end
$var reg 6 G i [5:0] $end
$upscope $end
$upscope $end
$upscope $end
$enddefinitions $end
$comment Show the parameter values. $end
$dumpall
b111 E
b0 D
b11 C
b10 B
b1010 A
b1000 @
b1001 ?
b100 >
b1 =
b110 <
b101 ;
$end
#0
$dumpvars
bx G
bx F
b1111111111110100 :
b1100 9
x8
b0 7
b0xxxxxx 6
05
b1100 4
b0 3
b0 2
b1111111111110100 1
b0 0
b0 /
x.
x-
x,
bx +
x*
x)
1(
x'
x&
1%
0$
0#
b10010000 "
b1100 !
$end
#10000
0,
0.
0&
0-
0'
0)
b0 F
1#
#20000
0#
1%
#30000
1#
#40000
0%
0#
1$
#50000
b1 F
0$
1#
#60000
0#
#70000
1$
1#
#80000
0#
#90000
1)
b10 F
1#
#100000
08
0*
b10010000 0
b10000 6
b10000 +
b10000 G
b10010000 2
0#
#110000
1'
0)
b11 F
0$
1#
#120000
b100100000 0
b100100000 2
0#
#130000
0'
b100 F
1#
#140000
0#
#150000
1.
b101 F
1#
#160000
0#
#170000
0.
1-
b1000 F
1#
#180000
b1111 6
b1111 +
b1111 G
0#
#190000
0-
b1001 F
1#
#200000
0#
#210000
1'
b11 F
1#
#220000
b1001000000 0
b1001000000 2
0#
#230000
0'
b100 F
1#
#240000
0#
#250000
1.
b101 F
1#
#260000
0#
#270000
0.
1-
b1000 F
1#
#280000
b1110 6
b1110 +
b1110 G
0#
#290000
0-
b1001 F
1#
#300000
0#
#310000
1'
b11 F
1#
#320000
b10010000000 0
b10010000000 2
0#
#330000
0'
b100 F
1#
#340000
0#
#350000
1.
b101 F
1#
#360000
0#
#370000
0.
1-
b1000 F
1#
#380000
b1101 6
b1101 +
b1101 G
0#
#390000
0-
b1001 F
1#
#400000
0#
#410000
1'
b11 F
1#
#420000
b100100000000 0
b100100000000 2
0#
#430000
0'
b100 F
1#
#440000
0#
#450000
1.
b101 F
1#
#460000
0#
#470000
0.
1-
b1000 F
1#
#480000
b1100 6
b1100 +
b1100 G
0#
#490000
0-
b1001 F
1#
#500000
0#
#510000
1'
b11 F
1#
#520000
b1001000000000 0
b1001000000000 2
0#
#530000
0'
b100 F
1#
#540000
0#
#550000
1.
b101 F
1#
#560000
0#
#570000
0.
1-
b1000 F
1#
#580000
b1011 6
b1011 +
b1011 G
0#
#590000
0-
b1001 F
1#
#600000
0#
#610000
1'
b11 F
1#
#620000
b10010000000000 0
b10010000000000 2
0#
#630000
0'
b100 F
1#
#640000
0#
#650000
1.
b101 F
1#
#660000
0#
#670000
0.
1-
b1000 F
1#
#680000
b1010 6
b1010 +
b1010 G
0#
#690000
0-
b1001 F
1#
#700000
0#
#710000
1'
b11 F
1#
#720000
b100100000000000 0
b100100000000000 2
0#
#730000
0'
b100 F
1#
#740000
0#
#750000
1.
b101 F
1#
#760000
0#
#770000
0.
1-
b1000 F
1#
#780000
b1001 6
b1001 +
b1001 G
0#
#790000
0-
b1001 F
1#
#800000
0#
#810000
1'
b11 F
1#
#820000
b1001000000000000 0
b1001000000000000 2
0#
#830000
0'
b100 F
1#
#840000
0#
#850000
1.
b101 F
1#
