Electronica Digital 1/ModuloDoubleDabble/Control_DoubleDabble.v
// Modulo de Unidad de Control para el algoritmo Double Dabble
// Version corregida: en vez de CHECK2->SUM1->CHECK3->SUM2->CHECK4->SUM3
// (que ademas perdia la correccion porque se capturaba con sum=0),
// aqui hay UN SOLO estado ADD donde los 3 digitos se corrigen en
// paralelo (Shift.v aplica update[2:0] a los 3 al mismo tiempo),
// y un estado SHIFT separado que solo desplaza.
module Control_DoubleDabble(
    input clk,
    input rst,
    input init,
    input i_eq_n,          // vienen de Increase.v (contador en 0)
    output reg load,
    output reg shift,
    output reg sum,
    output reg increase,
    output reg done
    );

    parameter START = 3'b000;
    parameter SHIFT  = 3'b001;
    parameter CHECK  = 3'b010;
    parameter SUM    = 3'b011;
    parameter FINISH = 3'b100;
    reg [2:0] state;

    always @(posedge clk or posedge rst) begin
        if (rst) begin
            state <= START;
        end
        else begin
            case (state)
                START: begin
                    if (init)
                        state <= SHIFT;
                    else
                        state <= START;
                end

                SHIFT: begin
                    state <= CHECK;
                end

                CHECK: begin
                    if (i_eq_n)
                        state <= FINISH;
                    else
                        state <= SUM;
                end

                SUM: begin
                    state <= SHIFT;
                end

                FINISH: begin
                    state <= START;
                end

                default: begin
                    state <= START;
                end
            endcase
        end
    end

    always @(*) begin
        case (state)
            START: begin
                load  = 1;    // carga A y resetea el contador
                shift = 0;
                sum   = 0;
                increase   = 0;
                done  = 0;
            end

            SHIFT: begin
                load  = 0;
                shift = 1;
                sum   = 0;
                increase   = 1;    // desplaza y decrementa el contador juntos
                done  = 0;
            end

            CHECK: begin
                load  = 0;
                shift = 0;
                sum   = 0;
                increase   = 0;
                done  = 0;
            end

            SUM: begin
                load  = 0;
                shift = 0;
                sum   = 1;    // corrige a1,a2,a3 EN PARALELO
                increase   = 0;
                done  = 0;
            end

            FINISH: begin
                load  = 0;
                shift = 0;
                sum   = 0;
                increase   = 0;
                done  = 1;
            end

            default: begin
                load  = 0;
                shift = 0;
                sum   = 0;
                increase   = 0;
                done  = 0;
            end
        endcase
    end

endmodule

Electronica Digital 1/ModuloDoubleDabble/Increase.v
// Contador de iteraciones del algoritmo.
// Antes contaba HACIA ARRIBA y se comparaba contra una constante (16)
// usando el modulo Comp de 16 bits -- con un contador de 4 bits eso
// nunca llegaba a coincidir y el algoritmo se quedaba pegado.
// Ahora cuenta HACIA ABAJO desde 10 (numero de bits de A) y expone
// directamente la bandera "Zero" cuando termina.
module Increase (
    input clk,
    input load,
    input increase,          // antes "increase"; ahora decrementa
    output i_eq_n
);
     // 10 desplazamientos, uno por bit de A[9:0]
    reg [4:0] i;
    assign i_eq_n = (i == 4'd10);

    always @(posedge clk) begin
        if (load)
            i <= 4'd0;
        else if (increase)
            i <= i + 1'b1;
    end
endmodule

Electronica Digital 1/ModuloDoubleDabble/Sum.v
// Modulo de correccion: suma 3 a un digito BCD
// (antes mezclaba la comparacion y la suma en un solo modulo con
//  puertos de 16/32 bits que no correspondian al ancho real de un digito;
//  ahora solo suma, y Comp.v decide si aplicar el resultado)
module Sum (
    input  [3:0] a,
    output [3:0] S
);
    assign S = a + 4'd3;
endmodule

Electronica Digital 1/ModuloDoubleDabble/Comp.v
// Modulo comparador de un digito BCD contra 5
// (antes comparaba dos valores de 16 bits para dos cosas distintas:
//  el chequeo de correccion y el conteo de iteraciones; ahora solo
//  hace el chequeo de correccion, y el conteo lo hace Increase.v)
module Comp (
    input  [3:0] a,
    output mayor     // 1 si a >= 5
);
    assign mayor = (a >= 4'd5);

endmodule

Electronica Digital 1/ModuloDoubleDabble/Shift.v
// Registro de desplazamiento + correccion BCD
// Contiene {a3, a2, a1, A} en un solo registro interno de 22 bits.
// "load" carga A; "shift" desplaza todo 1 bit; "add" aplica la
// correccion +3 a los 3 digitos EN PARALELO (cada uno controlado
// por su propio bit de "update", que viene de los 3 Comp externos).
module Shift(
    input clk,
    input load,
    input shift,
    input sum,
    input [2:0] update,        // update[2]->a3, update[1]->a2, update[0]->a1
    input [9:0] A,
    input [11:0] in_bcd,        // {a3,a2,a1} ya corregidos (+3)
    output [11:0] arr_corr       // {a3,a2,a1} actuales
);
    reg [21:0] alldata;          // {a3(4), a2(4), a1(4), A(10)}
    assign arr_corr = alldata[21:10];

    always @(posedge clk) begin
        if (load) begin
            alldata[21:10] <= 12'b0;
            alldata[9:0]   <= A;
        end
        else if (shift) begin
            alldata <= alldata << 1;
        end
        else if (sum) begin
            if (update[2]) alldata[21:18] <= in_bcd[11:8];   // a3
            if (update[1]) alldata[17:14] <= in_bcd[7:4];    // a2
            if (update[0]) alldata[13:10] <= in_bcd[3:0];    // a1
        end
    end
endmodule

Electronica Digital 1/ModuloDoubleDabble/DoubleDabble.v
// Modulo top del algoritmo DoubleDabble (version corregida: a1, a2 y a3
// se corrigen EN PARALELO en un solo estado ADD, en vez de turnarse en
// tres estados separados como en la version original)
module DoubleDabble (
    input clk,
    input rst,
    input [9:0] A,
    input init,
    output [3:0] a1,
    output [3:0] a2,
    output [3:0] a3,
    output done
);

    wire load;
    wire shift;
    wire sum;
    wire increase;
    wire i_eq_n;
    wire [11:0] bcd_reg;    // {a3, a2, a1} actuales
    wire [11:0] bcd_add;    // {a3, a2, a1} ya corregidos (+3)
    wire m_a1, m_a2, m_a3;  // 1 si el digito correspondiente es >= 5

    Shift u_Shift (.clk(clk), .load(load), .shift(shift), .sum(sum),
                   .update({m_a3, m_a2, m_a1}), .A(A), .in_bcd(bcd_add),
                   .arr_corr(bcd_reg));

    Comp u_Comp_a1 (.a(bcd_reg[3:0]),   .mayor(m_a1));
    Comp u_Comp_a2 (.a(bcd_reg[7:4]),   .mayor(m_a2));
    Comp u_Comp_a3 (.a(bcd_reg[11:8]),  .mayor(m_a3));

    Sum u_Sum_a1 (.a(bcd_reg[3:0]),  .S(bcd_add[3:0]));
    Sum u_Sum_a2 (.a(bcd_reg[7:4]),  .S(bcd_add[7:4]));
    Sum u_Sum_a3 (.a(bcd_reg[11:8]), .S(bcd_add[11:8]));

    Increase u_Increase (.clk(clk), .load(load), .increase(increase), .i_eq_n(i_eq_n));

    Control_DoubleDabble u_Control_DoubleDabble (.clk(clk), .rst(rst), .init(init),
                          .i_eq_n(i_eq_n), .load(load), .shift(shift), .sum(sum),
                          .increase(increase), .done(done));

    assign A = 
    assign a1 = bcd_reg[3:0];
    assign a2 = bcd_reg[7:4];
    assign a3 = bcd_reg[11:8];

endmodule

Electronica Digital 1/ModuloDoubleDabble/DoubleDabble_TB.v
// Modulo de prueba del algoritmo double dabble 
`timescale 1ns / 1ps

module DoubleDabble_TB;
    
    reg clk;
    reg rst;        
    reg [15:0] A;        
    reg init;         
    wire [3:0] a1;
    wire [3:0] a2;
    wire [3:0] a3;    
    wire done;  
  
    DoubleDabble uut (.clk(clk),.rst(rst),.A(A),.init(init),.a1(a1),.a2(a2),.a3(a3),.done(done));

    parameter PERIOD          = 20;
    parameter real DUTY_CYCLE = 0.5;
    parameter OFFSET          = 0;
    reg [20:0] i;
    event reset_trigger;
    event reset_done_trigger;
 

    initial begin  
      clk = 0; rst = 1; init = 0; A = 10'd399;
    end

    initial begin 
	  forever begin 
	   @ (reset_trigger);
		@ (negedge clk);
		rst = 1;
		@ (negedge clk);
		rst = 0;
		-> reset_done_trigger;
		end
	end

    initial  begin 
     #OFFSET;
     forever
       begin
         clk = 1'b0;
         #(PERIOD-(PERIOD*DUTY_CYCLE)) clk = 1'b1;
         #(PERIOD*DUTY_CYCLE);
       end
   end


initial begin
        #10 -> reset_trigger;
        @ (reset_done_trigger);
        @ (posedge clk);
        init = 0;
        @ (posedge clk);
        init = 1;
        
        for(i=0; i<2; i=i+1) begin
         @ (posedge clk);
        end

          init = 0;
          
        for(i=0; i<17; i=i+1) begin
         @ (posedge clk);
        end

   end	

    initial begin: TEST_CASE
     $dumpfile("DoubleDabble_TB.vcd");
     $dumpvars(-1, uut);
     #(100000) $finish;
   end

endmodule

Electronica Digital 1/ModuloDoubleDabble/DoubleDabble_TB.vcd
$date
	Wed Jul  8 08:43:33 2026
$end
$version
	Icarus Verilog
$end
$timescale
	1ps
$end
$scope module DoubleDabble_TB $end
$scope module uut $end
$var wire 10 ! A [9:0] $end
$var wire 1 " clk $end
$var wire 1 # init $end
$var wire 1 $ rst $end
$var wire 1 % sum $end
$var wire 1 & shift $end
$var wire 1 ' m_a3 $end
$var wire 1 ( m_a2 $end
$var wire 1 ) m_a1 $end
$var wire 1 * load $end
$var wire 1 + increase $end
$var wire 1 , i_eq_n $end
$var wire 1 - done $end
$var wire 12 . bcd_reg [11:0] $end
$var wire 12 / bcd_add [11:0] $end
$var wire 4 0 a3 [3:0] $end
$var wire 4 1 a2 [3:0] $end
$var wire 4 2 a1 [3:0] $end
$scope module u_Comp_a1 $end
$var wire 4 3 a [3:0] $end
$var wire 1 ) mayor $end
$upscope $end
$scope module u_Comp_a2 $end
$var wire 4 4 a [3:0] $end
$var wire 1 ( mayor $end
$upscope $end
$scope module u_Comp_a3 $end
$var wire 4 5 a [3:0] $end
$var wire 1 ' mayor $end
$upscope $end
$scope module u_Control_DoubleDabble $end
$var wire 1 " clk $end
$var wire 1 # init $end
$var wire 1 $ rst $end
$var wire 1 , i_eq_n $end
$var parameter 3 6 CHECK $end
$var parameter 3 7 FINISH $end
$var parameter 3 8 SHIFT $end
$var parameter 3 9 START $end
$var parameter 3 : SUM $end
$var reg 1 - done $end
$var reg 1 + increase $end
$var reg 1 * load $end
$var reg 1 & shift $end
$var reg 3 ; state [2:0] $end
$var reg 1 % sum $end
$upscope $end
$scope module u_Increase $end
$var wire 1 " clk $end
$var wire 1 + increase $end
$var wire 1 * load $end
$var wire 1 , i_eq_n $end
$var reg 5 < i [4:0] $end
$upscope $end
$scope module u_Shift $end
$var wire 10 = A [9:0] $end
$var wire 1 " clk $end
$var wire 12 > in_bcd [11:0] $end
$var wire 1 * load $end
$var wire 1 & shift $end
$var wire 1 % sum $end
$var wire 3 ? update [2:0] $end
$var wire 12 @ arr_corr [11:0] $end
$var reg 22 A alldata [21:0] $end
$upscope $end
$scope module u_Sum_a1 $end
$var wire 4 B a [3:0] $end
$var wire 4 C S [3:0] $end
$upscope $end
$scope module u_Sum_a2 $end
$var wire 4 D a [3:0] $end
$var wire 4 E S [3:0] $end
$upscope $end
$scope module u_Sum_a3 $end
$var wire 4 F a [3:0] $end
$var wire 4 G S [3:0] $end
$upscope $end
$upscope $end
$upscope $end
$enddefinitions $end
$comment Show the parameter values. $end
$dumpall
b11 :
b0 9
b1 8
b100 7
b10 6
$end
#0
$dumpvars
bx G
bx F
bx E
bx D
bx C
bx B
bx A
bx @
bx ?
bx >
b110001111 =
bx <
b0 ;
bx 5
bx 4
bx 3
bx 2
bx 1
bx 0
bx /
bx .
0-
x,
0+
1*
x)
x(
x'
0&
0%
1$
0#
0"
b110001111 !
$end
#10000
b0 0
b0 1
b0 2
b11 G
b0 F
b11 E
b0 D
b1100110011 /
b1100110011 >
b11 C
b0 B
0'
b0 5
0(
b0 4
b0 ?
0)
b0 3
b0 .
b0 @
b110001111 A
0,
b0 <
1"
#20000
0"
#30000
1"
#40000
0$
0"
#50000
1"
#60000
0"
#70000
1+
1&
0*
b1 ;
1#
1"
#80000
0"
#90000
0+
0&
b10 ;
b1100011110 A
b1 <
1"
#100000
0"
#110000
1%
b11 ;
0#
1"
#120000
0"
#130000
1+
0%
1&
b1 ;
1"
#140000
0"
#150000
b1 2
b1100110100 /
b1100110100 >
b100 C
b1 B
b1 3
0+
0&
b1 .
b1 @
b10 ;
b10 <
b11000111100 A
1"
#160000
0"
#170000
1%
b11 ;
1"
#180000
0"
#190000
1+
0%
1&
b1 ;
1"
#200000
0"
#210000
b11 2
b1100110110 /
b1100110110 >
b110 C
b11 B
b11 3
0+
0&
b11 .
b11 @
b10 ;
b110001111000 A
b11 <
1"
#220000
0"
#230000
1%
b11 ;
1"
#240000
0"
#250000
1+
0%
1&
b1 ;
1"
#260000
0"
#270000
b110 2
b1100111001 /
b1100111001 >
b1001 C
b110 B
b1 ?
1)
b110 3
0+
0&
b110 .
b110 @
b10 ;
b100 <
b1100011110000 A
1"
#280000
0"
#290000
1%
b11 ;
1"
#300000
0"
#310000
b1001 2
b1100111100 /
b1100111100 >
b1100 C
b1001 B
b1001 3
1+
0%
1&
b1001 .
b1001 @
b1 ;
b10010011110000 A
1"
#320000
0"
#330000
b1 1
b10 2
b100 E
b1 D
b1101000101 /
b1101000101 >
b101 C
b10 B
b1 4
b0 ?
0)
b10 3
0+
0&
b10010 .
b10010 @
b10 ;
b100100111100000 A
b101 <
1"
#340000
0"
#350000
1%
b11 ;
1"
#360000
0"
#370000
1+
0%
1&
b1 ;
1"
#380000
0"
#390000
b10 1
b100 2
b101 E
b10 D
b1101010111 /
b1101010111 >
b111 C
b100 B
b10 4
b100 3
0+
0&
b100100 .
b100100 @
b10 ;
b110 <
b1001001111000000 A
1"
#400000
0"
#410000
1%
b11 ;
1"
#420000
0"
#430000
1+
0%
1&
b1 ;
1"
#440000
0"
#450000
b100 1
b1001 2
b111 E
b100 D
b1101111100 /
b1101111100 >
b1100 C
b1001 B
b100 4
b1 ?
1)
b1001 3
0+
0&
b1001001 .
b1001001 @
b10 ;
b10010011110000000 A
b111 <
1"
#460000
0"
#470000
1%
b11 ;
1"
#480000
0"
#490000
b1100 2
b1101111111 /
b1101111111 >
b1111 C
b1100 B
b1100 3
1+
0%
1&
b1001100 .
b1001100 @
b1 ;
b10011001110000000 A
1"
#500000
0"
#510000
b1001 1
b1001 2
b1100 E
b1001 D
b1111001100 /
b1111001100 >
b1100 C
b1001 B
b11 ?
1(
b1001 4
b1001 3
0+
0&
b10011001 .
b10011001 @
b10 ;
b1000 <
b100110011100000000 A
1"
#520000
0"
#530000
1%
b11 ;
1"
#540000
0"
#550000
b1100 1
b1100 2
b1111 E
b1100 D
b1111111111 /
b1111111111 >
b1111 C
b1100 B
b1100 4
b1100 3
1+
0%
1&
b11001100 .
b11001100 @
b1 ;
b110011001100000000 A
1"
#560000
0"
#570000
b1 0
b1001 1
b1001 2
b100 G
b1 F
b1100 E
b1001 D
b10011001100 /
b10011001100 >
b1100 C
b1001 B
b1 5
b1001 4
b1001 3
0+
0&
b110011001 .
b110011001 @
b10 ;
b1100110011000000000 A
b1001 <
1"
#580000
0"
#590000
1%
b11 ;
1"
#600000
0"
#610000
b1100 1
b1100 2
b1111 E
b1100 D
b10011111111 /
b10011111111 >
b1111 C
b1100 B
b1100 4
b1100 3
1+
0%
1&
b111001100 .
b111001100 @
b1 ;
b1110011001000000000 A
1"
#620000
0"
#630000
b11 0
b1001 1
b1001 2
b110 G
b11 F
b1100 E
b1001 D
b11011001100 /
b11011001100 >
b1100 C
b1001 B
b11 5
b1001 4
b1001 3
0+
0&
b1110011001 .
b1110011001 @
b10 ;
1,
b1010 <
b11100110010000000000 A
1"
#640000
0"
#650000
1-
b100 ;
1"
#660000
0"
#670000
0-
1*
b0 ;
1"
#680000
0"
#690000
b0 0
b0 1
b0 2
b11 G
b0 F
b11 E
b0 D
b1100110011 /
b1100110011 >
b11 C
b0 B
b0 5
0(
b0 4
b0 ?
0)
b0 3
b0 .
b0 @
b110001111 A
0,
b0 <
1"
