Electronica Digital 1/ModuloDoubleDabbleInverso/Control_DoubleDabble_Inverso.v
// Unidad de Control para BCD -> Binario.
// El orden shift-luego-resta YA ERA correcto en tu version; lo que
// arreglamos es que ahora los 3 digitos se corrigen en UN SOLO
// estado SUBS (en paralelo), en vez de CHECK2->SUBS1->CHECK3->SUBS2->CHECK4->SUBS3.
module Control_DoubleDabble_Inverso(
    input clk,
    input rst,
    input init,
    input Zero,          // desde Increase.v (contador en 0)
    output reg load,
    output reg shift,
    output reg subs,
    output reg dec,
    output reg done
    );

    parameter START    = 3'b000;
    parameter CHECK1   = 3'b001;
    parameter LOAD     = 3'b010;
    parameter SHIFT    = 3'b011;
    parameter SUBS     = 3'b100;
    parameter INCREASE = 3'b101;
    parameter CHECK5   = 3'b110;
    parameter FINISH   = 3'b111;
    reg [2:0] state;

    always @(posedge clk or posedge rst) begin
        if (rst) begin
            state <= START;
        end
        else begin
            case (state)
                START:    state <= CHECK1;
                CHECK1:   state <= init ? LOAD : CHECK1;
                LOAD:     state <= SHIFT;
                SHIFT:    state <= SUBS;
                SUBS:     state <= INCREASE;
                INCREASE: state <= CHECK5;
                CHECK5:   state <= Zero ? FINISH : SHIFT;
                FINISH:   state <= START;
                default:  state <= START;
            endcase
        end
    end

    always @(*) begin
        load  = 0;
        shift = 0;
        subs  = 0;
        dec   = 0;
        done  = 0;
        case (state)
            LOAD:     load  = 1;
            SHIFT:    shift = 1;
            SUBS:     subs  = 1;   // corrige a1,a2,a3 EN PARALELO
            INCREASE: dec   = 1;
            FINISH:   done  = 1;
        endcase
    end

endmodule

Electronica Digital 1/ModuloDoubleDabbleInverso/Increase.v
// Contador de iteraciones (cuenta hacia abajo desde 10, uno por bit de A)
module Increase (
    input clk,
    input rst,
    input load,
    input dec,
    output Zero
);
    parameter N = 10;
    reg [4:0] count;
    assign Zero = (count == 0);

    always @(posedge clk or posedge rst) begin
        if (rst)
            count <= 5'd0;
        else if (load)
            count <= N[4:0];
        else if (dec)
            count <= count - 1'b1;
    end
endmodule

Electronica Digital 1/ModuloDoubleDabbleInverso/Substrac.v
// Modulo de la resta 
module Substrac(
    input  [3:0] a,
    output [3:0] S
);
    assign S = a - 4'd3;
endmodule

Electronica Digital 1/ModuloDoubleDabbleInverso/Comp.v
// Comparador de un digito BCD (4 bits) contra 8
module Comp (
    input  [3:0] a,
    output mayor      // 1 si a >= 8
);
    assign mayor = (a >= 4'd8);
endmodule

Electronica Digital 1/ModuloDoubleDabbleInverso/Shift.v
// Registro de desplazamiento para BCD -> Binario.
// Carga los 3 digitos BCD en la parte alta y 0 en la parte baja
// (que ira acumulando el resultado binario). En cada "shift" se
// desplaza TODO a la derecha; en cada "subs" se corrige (-3) a los
// digitos que lo necesiten, LOS 3 EN PARALELO segun "update".
module Shift(
    input clk,
    input load,
    input shift,
    input subs,
    input [2:0] update,      // update[2]->a3, update[1]->a2, update[0]->a1
    input [3:0] a1,
    input [3:0] a2,
    input [3:0] a3,
    input [11:0] in_bcd,      // {a3,a2,a1} ya corregidos (-3)
    output [11:0] arr_corr,    // {a3,a2,a1} actuales (para Comp/Substrac)
    output [9:0]  A            // resultado binario (valido cuando done=1)
);
    reg [21:0] alldata;         // {a3(4), a2(4), a1(4), binario(10)}
    assign arr_corr = alldata[21:10];
    assign A = alldata[9:0];

    always @(posedge clk) begin
        if (load) begin
            alldata[21:10] <= {a3, a2, a1};
            alldata[9:0]   <= 10'b0;
        end
        else if (shift) begin
            alldata <= alldata >> 1;
        end
        else if (subs) begin
            if (update[2]) alldata[21:18] <= in_bcd[11:8];   // a3
            if (update[1]) alldata[17:14] <= in_bcd[7:4];    // a2
            if (update[0]) alldata[13:10] <= in_bcd[3:0];    // a1
        end
    end
endmodule

Electronica Digital 1/ModuloDoubleDabbleInverso/DoubleDabble_Inverso.v
// Top del algoritmo DoubleDabble Inverso (BCD -> Binario).
// OJO: a diferencia de tu version anterior, aqui a1,a2,a3 son
// ENTRADAS (los 3 digitos BCD) y A es la SALIDA (el binario resultante).
// Esa era la inconsistencia real: un conversor BCD->binario no puede
// tener el binario como entrada.
module DoubleDabble_Inverso (
    input clk,
    input rst,
    input init,
    input [3:0] a1,
    input [3:0] a2,
    input [3:0] a3,
    output [9:0] A,
    output done
);

    wire load;
    wire shift;
    wire subs;
    wire dec;
    wire Zero;
    wire [11:0] bcd_reg;   // {a3,a2,a1} actuales
    wire [11:0] bcd_sub;   // {a3,a2,a1} ya corregidos (-3)
    wire m_a1, m_a2, m_a3; // 1 si el digito correspondiente es >= 8

    Shift u_Shift (.clk(clk), .load(load), .shift(shift), .subs(subs),
                   .update({m_a3, m_a2, m_a1}), .a1(a1), .a2(a2), .a3(a3),
                   .in_bcd(bcd_sub), .arr_corr(bcd_reg), .A(A));

    // un Comp y un Substrac por digito, los 3 en paralelo cada ciclo
    Comp u_Comp_a1 (.a(bcd_reg[3:0]),   .mayor(m_a1));
    Comp u_Comp_a2 (.a(bcd_reg[7:4]),   .mayor(m_a2));
    Comp u_Comp_a3 (.a(bcd_reg[11:8]),  .mayor(m_a3));

    Substrac u_Sub_a1 (.a(bcd_reg[3:0]),  .S(bcd_sub[3:0]));
    Substrac u_Sub_a2 (.a(bcd_reg[7:4]),  .S(bcd_sub[7:4]));
    Substrac u_Sub_a3 (.a(bcd_reg[11:8]), .S(bcd_sub[11:8]));

    Increase u_Increase (.clk(clk), .rst(rst), .load(load), .dec(dec), .Zero(Zero));

    Control_DoubleDabble_Inverso u_Control (.clk(clk), .rst(rst), .init(init),
                          .Zero(Zero), .load(load), .shift(shift), .subs(subs),
                          .dec(dec), .done(done));

endmodule

Electronica Digital 1/ModuloDoubleDabbleInverso/DoubleDabble_Inverso_TB.v
// Modulo de prueba del algoritmo double dabble inverso (BCD -> Binario)
`timescale 1ns / 1ps

module DoubleDabble_Inverso_TB;

    reg clk;
    reg rst;
    reg init;
    reg [3:0] a1, a2, a3;   // ahora son ENTRADA: los digitos BCD
    wire [9:0] A;           // ahora es SALIDA: el binario resultante
    wire done;

    DoubleDabble_Inverso uut (.clk(clk), .rst(rst), .init(init),
                              .a1(a1), .a2(a2), .a3(a3), .A(A), .done(done));

    parameter PERIOD = 20;
    reg [20:0] i;
    event reset_trigger;
    event reset_done_trigger;

    initial begin
        clk = 0; rst = 1; init = 0;
        // 255 en BCD: a3=2, a2=5, a1=5
        a3 = 4'd2; a2 = 4'd5; a1 = 4'd5;
    end

    initial begin
        forever begin
            @(reset_trigger);
            @(negedge clk); rst = 1;
            @(negedge clk); rst = 0;
            -> reset_done_trigger;
        end
    end

    initial begin
        forever begin
            clk = 1'b0; #(PERIOD/2);
            clk = 1'b1; #(PERIOD/2);
        end
    end

    initial begin
        #10 -> reset_trigger;
        @(reset_done_trigger);
        @(posedge clk); init = 0;
        @(posedge clk); init = 1;
        @(posedge clk); init = 0;

        wait (done);
        $display("BCD a1=%d a2=%d a3=%d  ->  Binario A=%d", a1, a2, a3, A);
        #20;
        $finish;
    end

    initial begin: TEST_CASE
        $dumpfile("DoubleDabble_Inverso_TB.vcd");
        $dumpvars(-1, uut);
        #(100000) $finish;
    end

endmodule

Electronica Digital 1/ModuloDoubleDabbleInverso/DoubleDabble_Inverso_TB.vcd
$date
	Wed Jul  8 09:39:09 2026
$end
$version
	Icarus Verilog
$end
$timescale
	1ps
$end
$scope module DoubleDabble_Inverso_TB $end
$scope module uut $end
$var wire 4 ! a1 [3:0] $end
$var wire 4 " a2 [3:0] $end
$var wire 4 # a3 [3:0] $end
$var wire 1 $ clk $end
$var wire 1 % init $end
$var wire 1 & rst $end
$var wire 1 ' subs $end
$var wire 1 ( shift $end
$var wire 1 ) m_a3 $end
$var wire 1 * m_a2 $end
$var wire 1 + m_a1 $end
$var wire 1 , load $end
$var wire 1 - done $end
$var wire 1 . dec $end
$var wire 12 / bcd_sub [11:0] $end
$var wire 12 0 bcd_reg [11:0] $end
$var wire 1 1 Zero $end
$var wire 10 2 A [9:0] $end
$scope module u_Comp_a1 $end
$var wire 4 3 a [3:0] $end
$var wire 1 + mayor $end
$upscope $end
$scope module u_Comp_a2 $end
$var wire 4 4 a [3:0] $end
$var wire 1 * mayor $end
$upscope $end
$scope module u_Comp_a3 $end
$var wire 4 5 a [3:0] $end
$var wire 1 ) mayor $end
$upscope $end
$scope module u_Control $end
$var wire 1 $ clk $end
$var wire 1 % init $end
$var wire 1 & rst $end
$var wire 1 1 Zero $end
$var parameter 3 6 CHECK1 $end
$var parameter 3 7 CHECK5 $end
$var parameter 3 8 FINISH $end
$var parameter 3 9 INCREASE $end
$var parameter 3 : LOAD $end
$var parameter 3 ; SHIFT $end
$var parameter 3 < START $end
$var parameter 3 = SUBS $end
$var reg 1 . dec $end
$var reg 1 - done $end
$var reg 1 , load $end
$var reg 1 ( shift $end
$var reg 3 > state [2:0] $end
$var reg 1 ' subs $end
$upscope $end
$scope module u_Increase $end
$var wire 1 $ clk $end
$var wire 1 . dec $end
$var wire 1 , load $end
$var wire 1 & rst $end
$var wire 1 1 Zero $end
$var parameter 32 ? N $end
$var reg 5 @ count [4:0] $end
$upscope $end
$scope module u_Shift $end
$var wire 4 A a1 [3:0] $end
$var wire 4 B a2 [3:0] $end
$var wire 4 C a3 [3:0] $end
$var wire 1 $ clk $end
$var wire 12 D in_bcd [11:0] $end
$var wire 1 , load $end
$var wire 1 ( shift $end
$var wire 1 ' subs $end
$var wire 3 E update [2:0] $end
$var wire 12 F arr_corr [11:0] $end
$var wire 10 G A [9:0] $end
$var reg 22 H alldata [21:0] $end
$upscope $end
$scope module u_Sub_a1 $end
$var wire 4 I a [3:0] $end
$var wire 4 J S [3:0] $end
$upscope $end
$scope module u_Sub_a2 $end
$var wire 4 K a [3:0] $end
$var wire 4 L S [3:0] $end
$upscope $end
$scope module u_Sub_a3 $end
$var wire 4 M a [3:0] $end
$var wire 4 N S [3:0] $end
$upscope $end
$upscope $end
$upscope $end
$enddefinitions $end
$comment Show the parameter values. $end
$dumpall
b1010 ?
b100 =
b0 <
b11 ;
b10 :
b101 9
b111 8
b110 7
b1 6
$end
#0
$dumpvars
bx N
bx M
bx L
bx K
bx J
bx I
bx H
bx G
bx F
bx E
bx D
b10 C
b101 B
b101 A
b0 @
b0 >
bx 5
bx 4
bx 3
bx 2
11
bx 0
bx /
0.
0-
0,
x+
x*
x)
0(
0'
1&
0%
0$
b10 #
b101 "
b101 !
$end
#10000
1$
#20000
0$
#30000
1$
#40000
0&
0$
#50000
b1 >
1$
#60000
0$
#70000
1,
b10 >
1%
1$
#80000
0$
#90000
b1111 N
b10 M
b10 L
b101 K
b111100100010 /
b111100100010 D
b10 J
b101 I
0)
b10 5
0*
b101 4
b0 E
0+
b101 3
1(
0,
b0 2
b0 G
b1001010101 0
b1001010101 F
b11 >
01
b1010 @
b10010101010000000000 H
0%
1$
#100000
0$
#110000
b1110 N
b1 M
b1111 L
b10 K
b111011110111 /
b111011110111 D
b111 J
b1010 I
b1 5
b10 4
b1 E
1+
b1010 3
1'
0(
b100101010 0
b100101010 F
b1000000000 2
b1000000000 G
b100 >
b1001010101000000000 H
1$
#120000
0$
#130000
b111011110100 /
b111011110100 D
b100 J
b111 I
b0 E
0+
b111 3
1.
0'
b100100111 0
b100100111 F
b101 >
b1001001111000000000 H
1$
#140000
0$
#150000
0.
b1001 @
b110 >
1$
#160000
0$
#170000
1(
b11 >
1$
#180000
0$
#190000
b1101 N
b0 M
b110 L
b1001 K
b110101100000 /
b110101100000 D
b0 J
b11 I
b0 5
b10 E
1*
b1001 4
b11 3
1'
0(
b10010011 0
b10010011 F
b1100000000 2
b1100000000 G
b100 >
b100100111100000000 H
1$
#200000
0$
#210000
b110100110000 /
b110100110000 D
b11 L
b110 K
b0 E
0*
b110 4
1.
0'
b1100011 0
b1100011 F
b101 >
b11000111100000000 H
1$
#220000
0$
#230000
0.
b1000 @
b110 >
1$
#240000
0$
#250000
1(
b11 >
1$
#260000
0$
#270000
b0 L
b11 K
b110100001110 /
b110100001110 D
b1110 J
b1 I
b11 4
b1 3
1'
0(
b110001 0
b110001 F
b1110000000 2
b1110000000 G
b100 >
b1100011110000000 H
1$
#280000
0$
#290000
1.
0'
b101 >
1$
#300000
0$
#310000
0.
b111 @
b110 >
1$
#320000
0$
#330000
1(
b11 >
1$
#340000
0$
#350000
b1110 L
b1 K
b110111100101 /
b110111100101 D
b101 J
b1000 I
b1 4
b1 E
1+
b1000 3
1'
0(
b11000 0
b11000 F
b1111000000 2
b1111000000 G
b100 >
b110001111000000 H
1$
#360000
0$
#370000
b110111100010 /
b110111100010 D
b10 J
b101 I
b0 E
0+
b101 3
1.
0'
b10101 0
b10101 F
b101 >
b101011111000000 H
1$
#380000
0$
#390000
0.
b110 @
b110 >
1$
#400000
0$
#410000
1(
b11 >
1$
#420000
0$
#430000
b1101 L
b0 K
b110111010111 /
b110111010111 D
b111 J
b1010 I
b0 4
b1 E
1+
b1010 3
1'
0(
b1010 0
b1010 F
b1111100000 2
b1111100000 G
b100 >
b10101111100000 H
1$
#440000
0$
#450000
b110111010100 /
b110111010100 D
b100 J
b111 I
b0 E
0+
b111 3
1.
0'
b111 0
b111 F
b101 >
b1111111100000 H
1$
#460000
0$
#470000
0.
b101 @
b110 >
1$
#480000
0$
#490000
1(
b11 >
1$
#500000
0$
#510000
b110111010000 /
b110111010000 D
b0 J
b11 I
b11 3
1'
0(
b11 0
b11 F
b1111110000 2
b1111110000 G
b100 >
b111111110000 H
1$
#520000
0$
#530000
1.
0'
b101 >
1$
#540000
0$
#550000
0.
b100 @
b110 >
1$
#560000
0$
#570000
1(
b11 >
1$
#580000
0$
#590000
b110111011110 /
b110111011110 D
b1110 J
b1 I
b1 3
1'
0(
b1 0
b1 F
b1111111000 2
b1111111000 G
b100 >
b11111111000 H
1$
#600000
0$
#610000
1.
0'
b101 >
1$
#620000
0$
#630000
0.
b11 @
b110 >
1$
#640000
0$
#650000
1(
b11 >
1$
#660000
0$
#670000
b110111011101 /
b110111011101 D
b1101 J
b0 I
b0 3
1'
0(
b0 0
b0 F
b1111111100 2
b1111111100 G
b100 >
b1111111100 H
1$
#680000
0$
#690000
1.
0'
b101 >
1$
#700000
0$
#710000
0.
b10 @
b110 >
1$
#720000
0$
#730000
1(
b11 >
1$
#740000
0$
#750000
1'
0(
b111111110 2
b111111110 G
b100 >
b111111110 H
1$
#760000
0$
#770000
1.
0'
b101 >
1$
#780000
0$
#790000
0.
b1 @
b110 >
1$
#800000
0$
#810000
1(
b11 >
1$
#820000
0$
#830000
1'
0(
b11111111 2
b11111111 G
b100 >
b11111111 H
1$
#840000
0$
#850000
1.
0'
b101 >
1$
#860000
0$
#870000
0.
11
b0 @
b110 >
1$
#880000
0$
#890000
1-
b111 >
1$
#900000
0$
#910000
0-
b0 >
1$
