Electronica Digital 1/ModuloWs2812/Comp.v
//Modulo que compara dos valores dependendiendo de lo que se requiera comparar
module Comp(
    input [15:0] a,
    input [15:0] b,
    output reg z
);

    always @(*) begin
        z = (a == b);
    end

endmodule

Electronica Digital 1/ModuloSendLeds/Control_Timer.v
// Modulo de Unidad de Control para Timer (protocolo tipo NeoPixel/WS2812)
module Control_Timer ( 
    input clk,
    input z, 
    input [1:0] sel,     
    input init_t,
    output reg dout, 
    output reg done,
    output reg rst,
    output reg inc,
    output reg [1:0]sel_tim
);

    parameter START      = 4'b0000;
    parameter CHECK1     = 4'b0001;
    parameter INIT       = 4'b0010;
    parameter CHECK2     = 4'b0011;   
    parameter T0H        = 4'b0100;
    parameter T1H        = 4'b0101;
    parameter DOUT1      = 4'b0110;
    parameter DOUT2      = 4'b0111;
    parameter DOUT3      = 4'b1000;
    parameter COUNT1     = 4'b1001;
    parameter CHECK3     = 4'b1010;
    parameter COUNT2     = 4'b1011;
    parameter COUNT3     = 4'b1100;
    parameter CHECK4     = 4'b1101;
    parameter CHECK5     = 4'b1110;
    parameter DONE       = 4'b1111;


    reg [3:0] state;

    always @(*) begin


        case (state)
            START: begin
                dout    = 0; 
                done    = 0;
                rst     = 0;
                inc     = 0;
                sel_tim = 0;               
            end

            CHECK1: begin
                dout    = 0; 
                done    = 0;
                rst     = 0;
                inc     = 0;
                sel_tim = 0;                 
            end 

            INIT: begin
                dout    = 0; 
                done    = 0;
                rst     = 1;
                inc     = 0;
                sel_tim = 0;  
            end

            CHECK2: begin
                dout    = 0; 
                done    = 0;
                rst     = 0;
                inc     = 0;
                sel_tim = 0;                 
            end

            T0H: begin
                dout    = 0; 
                done    = 0;
                rst     = 0;
                inc     = 0;
                sel_tim = 0; 
            end

            T1H: begin
                dout    = 0; 
                done    = 0;
                rst     = 0;
                inc     = 0;
                sel_tim = 1;
            end

            DOUT1: begin
                dout    = 0; 
                done    = 0;
                rst     = 0;
                inc     = 0;
                sel_tim = 2;       
            end

            DOUT2: begin
                dout    = 1; 
                done    = 0;
                rst     = 0;
                inc     = 0;
                sel_tim = 0;       
            end


            DOUT3: begin
                dout    = 0; 
                done    = 0;
                rst     = 0;
                inc     = 0;
                sel_tim = 0;       
            end

            COUNT1: begin
                dout    = 1; 
                done    = 0;
                rst     = 0;
                inc     = 1;
                sel_tim = 0;       
            end

            CHECK3: begin
                dout    = 1; 
                done    = 0;
                rst     = 0;
                inc     = 0;
                sel_tim = 0;       
            end


            COUNT2: begin
                dout    = 0; 
                done    = 0;
                rst     = 0;
                inc     = 1;
                sel_tim = 3;         
            end


            COUNT3: begin
                dout    = 0; 
                done    = 0;
                rst     = 0;
                inc     = 1;
                sel_tim = 2;    
            end

            CHECK4: begin
                dout    = 0; 
                done    = 0;
                rst     = 0;
                inc     = 0;
                sel_tim = 2;    
            end


            CHECK5: begin
                dout    = 0; 
                done    = 0;
                rst     = 0;
                inc     = 0;
                sel_tim = 3;    
            end


            DONE: begin
                dout    = 0; 
                done    = 1;
                rst     = 0;
                inc     = 0;
                sel_tim = 0; 
            end
            
            default: begin
                dout    = 0; 
                done    = 0;
                rst     = 0;
                inc     = 0;
                sel_tim = 0;                
            end
        endcase
    end


    always @(posedge clk) begin
        case (state)
            START: begin
                state <= CHECK1;
            end

            CHECK1: begin
                if (init_t == 1)
                    state <= INIT;
                else
                    state <= CHECK1;
            end

            INIT: begin
                state <= CHECK2;
            end

            CHECK2: begin
                case (sel)
                    2'b00:   state <= T0H;
                    2'b01:   state <= T1H;
                    2'b10:   state <= DOUT1;
                    default: state <= T0H;
                endcase
            end

            T0H: begin
                state <= DOUT2;
            end

            T1H: begin
                state <= DOUT2;
            end

            DOUT1: begin
                state <= DOUT3;
            end

            DOUT2: begin
                state <= COUNT1;
            end

            DOUT3: begin
                state <= COUNT3;
            end

            COUNT1: begin
                state <= CHECK3;
            end

            CHECK3: begin
                if (z)
                    state <= COUNT2;
                else
                    state <= COUNT1;
            end

            COUNT2: begin
                state <= CHECK5;
            end

            CHECK5: begin
                if (z)
                    state <= DONE;
                else
                    state <= COUNT2;
            end

            COUNT3: begin
                state <= CHECK4;
            end

            CHECK4: begin
  
                if (z)
                    state <= DONE;
                else
                    state <= COUNT3;
            end

            DONE: begin
                state <= START;
            end

            default: begin
                state <= START;
            end
        endcase
    end

endmodule

Electronica Digital 1/ModuloWs2812/Multiplex.v
// Modulo de multiplexor
module Multiplex (
    input [15:0] T0h,
    input [15:0] T1h,
    input [15:0]Res,
    input [15:0] Per,
    input[1:0]sel_tim,
    output reg [15:0] out   
);

    always @(*) begin
        case(sel_tim)
        2'b00: out =T0h;
        2'b01: out =T1h;
        2'b10: out =Res;
        2'b11: out =Per;
        default: out = T0h;
        endcase
    end

endmodule

Electronica Digital 1/ModuloTimer/Count_out.v
// Modulo de count
module Count_out (
    input clk,
    input rst,         
    input inc,     
    output reg [15:0] count_out 
);

   
    always @(negedge clk) begin
        if (rst) begin
            count_out <= 16'h0;       
        end 
        else if (inc) begin
            count_out <= count_out + 1'b1;   
        end
    end

endmodule

Electronica Digital 1/ModuloSendLeds/Timer.v
//Modulo Top del timer 
module Timer  (
    input init_t,
    input clk,
    input [1:0] sel,
    output dout,
    output done_t
);

    wire [15:0]out;
    wire inc;
    wire rst;
    wire z;
    parameter [15:0] T0h = 16'd10;
    parameter [15:0] T1h = 16'd20;
    parameter [15:0] Res = 16'd1250;
    parameter [15:0] Per = 16'd31;
    wire [1:0]sel_tim;
    wire [15:0]count_out;



    Count_out u_Count_out(.clk(clk),.rst(rst),.inc(inc),.count_out(count_out));

    Multiplex u_Multiplex(.T0h(T0h),.T1h(T1h),.Res(Res),.Per(Per),.sel_tim(sel_tim),.out(out));

    Control_Timer u_Control_Timer(.clk(clk),.z(z),.sel(sel),.init_t(init_t),.dout(dout),.done(done_t),.rst(rst),.inc(inc),.sel_tim(sel_tim));
    
    Comp u_Comp(.a(out),.b(count_out),.z(z));

endmodule

Electronica Digital 1/ModuloSendLeds/Control_Ws2812.v
// Modulo de Unidad de Control para algoritmo de raiz cuadrada
module Control_Ws2812 ( 
    input clk,
    input msb,
    input init,  
    input rst_cmd,
    input done_t,
    input [15:0]z,
    output reg sh,
    output reg init_t,
    output reg [1:0] sel,
    output reg dec,
    output reg ld,
    output reg done
    );

    parameter START        = 4'b0000;
    parameter CHECK1       = 4'b0001;
    parameter LOAD         = 4'b0010; 
    parameter CASE         = 4'b0011;   
    parameter RGB1         = 4'b0100;   
    parameter RGB2         = 4'b0101;   
    parameter RES          = 4'b0110;   
    parameter COUNT        = 4'b0111;   
    parameter CHECK2       = 4'b1000;   
    parameter DONE         = 4'b1001;    

    reg [3:0] state;

    always @(*) begin
        case (state)
            START: begin
                sh      = 0;
                init_t  = 0;
                sel     = 0;
                dec     = 0;
                ld      = 0;
                done    = 0;                
            end

            CHECK1: begin
                sh      = 0;
                init_t  = 0;
                sel     = 0;
                dec     = 0;
                ld      = 0;
                done    = 0;                
            end

            LOAD: begin
                sh      = 0;
                init_t  = 0;
                sel     = 0;
                dec     = 0;
                ld      = 1;
                done    = 0;                
            end

            CASE: begin
                sh      = 0;
                init_t  = 0;
                sel     = 0;
                dec     = 0;
                ld      = 0;
                done    = 0;                
            end

            RGB1: begin
                sh      = 0;
                init_t  = 1;
                sel     = 1;
                dec     = 0;
                ld      = 0;
                done    = 0;                
            end

            RGB2: begin
                sh      = 0;
                init_t  = 1;
                sel     = 0;
                dec     = 0;
                ld      = 0;
                done    = 0;                
            end

            RES: begin
                sh      = 0;
                init_t  = 1;
                sel     = 2;
                dec     = 0;
                ld      = 0;
                done    = 0;                
            end

            COUNT: begin
                sh      = 1;
                init_t  = 0;
                sel     = 0;
                dec     = 1;
                ld      = 0;
                done    = 0;                
            end

            CHECK2: begin
                sh      = 0;
                init_t  = 0;
                sel     = 0;
                dec     = 0;
                ld      = 0;
                done    = 0;                
            end

            DONE: begin
                sh      = 0;
                init_t  = 0;
                sel     = 0;
                dec     = 0;
                ld      = 0;
                done    = 1;                
            end

            default: begin
                sh      = 0;
                init_t  = 0;
                sel     = 0;
                dec     = 0;
                ld      = 0;
                done    = 0;                
            end
        endcase
    end

    always @(posedge clk) begin
        case (state)
            START: begin
                state <= CHECK1;
            end

            CHECK1: begin
                if (init)
                    state <= LOAD;
                else
                    state <= CHECK1;
            end

            LOAD: begin
                state <= CASE;
            end

            CASE: begin
                if (rst_cmd)
                    state <= RES;
                else if (msb)
                    state <= RGB1;
                else
                    state <= RGB2;
            end

            RGB1: begin
                state <= COUNT;
            end

            RGB2: begin
                state <= COUNT;
            end

            COUNT: begin
                state <= CHECK2;
            end

            CHECK2: begin
                if (z==0)
                    state <= DONE;
                else
                    state <= CASE; 
            end

            RES: begin
                state <= DONE;
            end

            DONE: begin
                state <= START;
            end

            default: begin
                state <= START;
            end
        endcase
    end

endmodule

Electronica Digital 1/ModuloWs2812/Count.v
// Modulo de count
module Count(
    input clk,
    input ld,         
    input dec,     
    output reg [15:0] z
);

   
    always @(negedge clk) begin
        if (ld) begin
            z <= 16'h0;       
        end 
        else if (dec) begin
            z <= z - 1'b1;   
        end
    end

endmodule

Electronica Digital 1/ModuloSendLeds/Shift.v
// Modulo de corrimiento a la izquierda
module Shift(
    input clk,
    input ld,
    input [23:0] RGB,
    input sh,
    output reg [23:0] corr 
);

  
    always @(negedge clk ) begin
        if (ld) begin
            corr <= RGB;       
        end 
        else if (sh) begin
            corr <= corr << 1; 
        end
       
    end

endmodule

Electronica Digital 1/ModuloSendLeds/Ws2812.v
module Ws2812 (
    input clk,
    input [23:0] RGB,
    input init,
    input rst_cmd,
    output dout,
    output done
);
    wire ld;
    wire init_t;
    wire sh;
    wire [15:0]z;
    wire [1:0] sel;
    wire dec;
    wire [23:0] corr;
    wire done_t;

    Shift u_Shift(.clk(clk),.ld(ld),.RGB(RGB),.sh(sh),.corr(corr));

    Count u_Count(.clk(clk),.ld(ld),.dec(dec),.z(z));

    Control_Ws2812 u_Control_Ws2812(.clk(clk),.msb(corr[23]),.init(init),.rst_cmd(rst_cmd),.done_t(done_t),.z(z),.sh(sh),.init_t(init_t),.sel(sel)
    ,.dec(dec),.ld(ld),.done(done));

    Timer u_Timer(.init_t(init_t),.clk(clk),.sel(sel),.dout(dout),.done_t(done_t));

endmodule

Electronica Digital 1/ModuloWs2812/Ws2812_TB.v
`timescale 1ns / 1ps

module Ws2812_TB;

    reg clk;
    reg [23:0] RGB;
    reg init;
    reg rst_cmd;
    wire dout;
    wire done;


    Ws2812 uut (.clk(clk),.RGB(RGB),.init(init),.rst_cmd(rst_cmd),.dout(dout),.done(done));

    always #10 clk = ~clk;

    initial begin
        #1000000;
        $display("TIMEOUT de seguridad activado.");
        $finish;
    end

    initial begin
        $display("=== TESTBENCH TOP MODULE WS2812 ===");
        clk = 0; RGB = 24'hFF00AA; init = 0; rst_cmd = 0;
        #50;

        $display("Iniciando transmisión de color...");
        @(negedge clk);
        init = 1;
        @(negedge clk);
        init = 0;

        @(posedge done);
        $display("Transmisión finalizada.");

        #100;
        $finish;
    end

    initial begin: TEST_CASE
        $dumpfile("Ws2812_TB.vcd");
        $dumpvars(-1, uut);
    end
endmodule

Electronica Digital 1/ModuloWs2812/Ws2812_TB.vcd
$date
	Wed Jul 15 13:35:25 2026
$end
$version
	Icarus Verilog
$end
$timescale
	1ps
$end
$scope module Ws2812_TB $end
$scope module uut $end
$var wire 24 ! RGB [23:0] $end
$var wire 1 " clk $end
$var wire 1 # init $end
$var wire 1 $ rst_cmd $end
$var wire 16 % z [15:0] $end
$var wire 1 & sh $end
$var wire 2 ' sel [1:0] $end
$var wire 1 ( ld $end
$var wire 1 ) init_t $end
$var wire 1 * dout $end
$var wire 1 + done_t $end
$var wire 1 , done $end
$var wire 1 - dec $end
$var wire 24 . corr [23:0] $end
$scope module u_Control_Ws2812 $end
$var wire 1 " clk $end
$var wire 1 # init $end
$var wire 1 / msb $end
$var wire 1 $ rst_cmd $end
$var wire 16 0 z [15:0] $end
$var wire 1 + done_t $end
$var parameter 4 1 CASE $end
$var parameter 4 2 CHECK1 $end
$var parameter 4 3 CHECK2 $end
$var parameter 4 4 COUNT $end
$var parameter 4 5 DONE $end
$var parameter 4 6 LOAD $end
$var parameter 4 7 RES $end
$var parameter 4 8 RGB1 $end
$var parameter 4 9 RGB2 $end
$var parameter 4 : START $end
$var reg 1 - dec $end
$var reg 1 , done $end
$var reg 1 ) init_t $end
$var reg 1 ( ld $end
$var reg 2 ; sel [1:0] $end
$var reg 1 & sh $end
$var reg 4 < state [3:0] $end
$upscope $end
$scope module u_Count $end
$var wire 1 " clk $end
$var wire 1 - dec $end
$var wire 1 ( ld $end
$var reg 16 = z [15:0] $end
$upscope $end
$scope module u_Shift $end
$var wire 24 > RGB [23:0] $end
$var wire 1 " clk $end
$var wire 1 ( ld $end
$var wire 1 & sh $end
$var reg 24 ? corr [23:0] $end
$upscope $end
$scope module u_Timer $end
$var wire 1 " clk $end
$var wire 1 ) init_t $end
$var wire 2 @ sel [1:0] $end
$var wire 1 A z $end
$var wire 2 B sel_tim [1:0] $end
$var wire 1 C rst $end
$var wire 16 D out [15:0] $end
$var wire 1 E inc $end
$var wire 1 * dout $end
$var wire 1 + done_t $end
$var wire 16 F count_out [15:0] $end
$var parameter 16 G Per $end
$var parameter 16 H Res $end
$var parameter 16 I T0h $end
$var parameter 16 J T1h $end
$scope module u_Comp $end
$var wire 16 K b [15:0] $end
$var wire 16 L a [15:0] $end
$var reg 1 A z $end
$upscope $end
$scope module u_Control_Timer $end
$var wire 1 " clk $end
$var wire 1 ) init_t $end
$var wire 2 M sel [1:0] $end
$var wire 1 A z $end
$var parameter 4 N CHECK1 $end
$var parameter 4 O CHECK2 $end
$var parameter 4 P CHECK3 $end
$var parameter 4 Q CHECK4 $end
$var parameter 4 R CHECK5 $end
$var parameter 4 S COUNT1 $end
$var parameter 4 T COUNT2 $end
$var parameter 4 U COUNT3 $end
$var parameter 4 V DONE $end
$var parameter 4 W DOUT1 $end
$var parameter 4 X DOUT2 $end
$var parameter 4 Y DOUT3 $end
$var parameter 4 Z INIT $end
$var parameter 4 [ START $end
$var parameter 4 \ T0H $end
$var parameter 4 ] T1H $end
$var reg 1 + done $end
$var reg 1 * dout $end
$var reg 1 E inc $end
$var reg 1 C rst $end
$var reg 2 ^ sel_tim [1:0] $end
$var reg 4 _ state [3:0] $end
$upscope $end
$scope module u_Count_out $end
$var wire 1 " clk $end
$var wire 1 E inc $end
$var wire 1 C rst $end
$var reg 16 ` count_out [15:0] $end
$upscope $end
$scope module u_Multiplex $end
$var wire 16 a Per [15:0] $end
$var wire 16 b Res [15:0] $end
$var wire 16 c T0h [15:0] $end
$var wire 16 d T1h [15:0] $end
$var wire 2 e sel_tim [1:0] $end
$var reg 16 f out [15:0] $end
$upscope $end
$upscope $end
$upscope $end
$upscope $end
$enddefinitions $end
$comment Show the parameter values. $end
$dumpall
b101 ]
b100 \
b0 [
b10 Z
b1000 Y
b111 X
b110 W
b1111 V
b1100 U
b1011 T
b1001 S
b1110 R
b1101 Q
b1010 P
b11 O
b1 N
b10100 J
b1010 I
b10011100010 H
b11111 G
b0 :
b101 9
b100 8
b110 7
b10 6
b1001 5
b111 4
b1000 3
b1 2
b11 1
$end
#0
$dumpvars
b1010 f
bx e
b10100 d
b1010 c
b10011100010 b
b11111 a
bx `
bx _
bx ^
bx M
b1010 L
bx K
bx F
xE
b1010 D
xC
bx B
xA
bx @
bx ?
b111111110000000010101010 >
bx =
bx <
bx ;
bx 0
x/
bx .
x-
x,
x+
x*
x)
x(
bx '
x&
bx %
0$
0#
0"
b111111110000000010101010 !
$end
#10000
0,
0(
0-
b0 '
b0 ;
b0 @
b0 M
0)
0&
b0 B
b0 ^
b0 e
0E
0C
0+
0*
b0 <
b0 _
1"
#20000
0"
#30000
b1 _
b1 <
1"
#40000
0"
#50000
1"
#60000
1#
0"
#70000
1(
b10 <
1"
#80000
1/
b111111110000000010101010 .
b111111110000000010101010 ?
b10111 %
b10111 0
b10111 =
0#
0"
#90000
0(
b11 <
1"
#100000
0"
#110000
b1 '
b1 ;
b1 @
b1 M
1)
b100 <
1"
#120000
0"
#130000
1-
b0 '
b0 ;
b0 @
b0 M
0)
1&
1C
b111 <
b10 _
1"
#140000
0A
b0 F
b0 K
b0 `
b10110 %
b10110 0
b10110 =
b111111100000000101010100 .
b111111100000000101010100 ?
0"
#150000
0C
0-
0&
b11 _
b1000 <
1"
#160000
0"
#170000
b11 <
b100 _
1"
#180000
0"
#190000
1*
b1 '
b1 ;
b1 @
b1 M
1)
b111 _
b100 <
1"
#200000
0"
#210000
1-
b0 '
b0 ;
b0 @
b0 M
0)
1&
1E
b111 <
b1001 _
1"
#220000
b1 F
b1 K
b1 `
b10101 %
b10101 0
b10101 =
b111111000000001010101000 .
b111111000000001010101000 ?
0"
#230000
0E
0-
0&
b1010 _
b1000 <
1"
#240000
0"
#250000
1E
b11 <
b1001 _
1"
#260000
b10 F
b10 K
b10 `
0"
#270000
0E
b1 '
b1 ;
b1 @
b1 M
1)
b1010 _
b100 <
1"
#280000
0"
#290000
1-
b0 '
b0 ;
b0 @
b0 M
0)
1&
1E
b111 <
b1001 _
1"
#300000
b11 F
b11 K
b11 `
b10100 %
b10100 0
b10100 =
b111110000000010101010000 .
b111110000000010101010000 ?
0"
#310000
0E
0-
0&
b1010 _
b1000 <
1"
#320000
0"
#330000
1E
b11 <
b1001 _
1"
#340000
b100 F
b100 K
b100 `
0"
#350000
0E
b1 '
b1 ;
b1 @
b1 M
1)
b1010 _
b100 <
1"
#360000
0"
#370000
1-
b0 '
b0 ;
b0 @
b0 M
0)
1&
1E
b111 <
b1001 _
1"
#380000
b101 F
b101 K
b101 `
b10011 %
b10011 0
b10011 =
b111100000000101010100000 .
b111100000000101010100000 ?
0"
#390000
0E
0-
0&
b1010 _
b1000 <
1"
#400000
0"
#410000
1E
b11 <
b1001 _
1"
#420000
b110 F
b110 K
b110 `
0"
#430000
0E
b1 '
b1 ;
b1 @
b1 M
1)
b1010 _
b100 <
1"
#440000
0"
#450000
1-
b0 '
b0 ;
b0 @
b0 M
0)
1&
1E
b111 <
b1001 _
1"
#460000
b111 F
b111 K
b111 `
b10010 %
b10010 0
b10010 =
b111000000001010101000000 .
b111000000001010101000000 ?
0"
#470000
0E
0-
0&
b1010 _
b1000 <
1"
#480000
0"
#490000
1E
b11 <
b1001 _
1"
#500000
b1000 F
b1000 K
b1000 `
0"
#510000
0E
b1 '
b1 ;
b1 @
b1 M
1)
b1010 _
b100 <
1"
#520000
0"
#530000
1-
b0 '
b0 ;
b0 @
b0 M
0)
1&
1E
b111 <
b1001 _
1"
#540000
b1001 F
b1001 K
b1001 `
b10001 %
b10001 0
b10001 =
b110000000010101010000000 .
b110000000010101010000000 ?
0"
#550000
0E
0-
0&
b1010 _
b1000 <
1"
#560000
0"
#570000
1E
b11 <
b1001 _
1"
#580000
1A
b1010 F
b1010 K
b1010 `
0"
#590000
0E
b1 '
b1 ;
b1 @
b1 M
1)
b1010 _
b100 <
1"
#600000
0"
#610000
0A
b11111 D
b11111 L
b11111 f
1-
b0 '
b0 ;
b0 @
b0 M
0)
1&
b11 B
b11 ^
b11 e
1E
0*
b111 <
b1011 _
1"
#620000
b1011 F
b1011 K
b1011 `
b10000 %
b10000 0
b10000 =
b100000000101010100000000 .
b100000000101010100000000 ?
0"
#630000
0E
0-
0&
b1110 _
b1000 <
1"
#640000
0"
#650000
1E
b11 <
b1011 _
1"
#660000
b1100 F
b1100 K
b1100 `
0"
#670000
0E
b1 '
b1 ;
b1 @
b1 M
1)
b1110 _
b100 <
1"
#680000
0"
#690000
1-
b0 '
b0 ;
b0 @
b0 M
0)
1&
1E
b111 <
b1011 _
1"
#700000
0/
b1101 F
b1101 K
b1101 `
b1111 %
b1111 0
b1111 =
b1010101000000000 .
b1010101000000000 ?
0"
#710000
0E
0-
0&
b1110 _
b1000 <
1"
#720000
0"
#730000
1E
b11 <
b1011 _
1"
#740000
b1110 F
b1110 K
b1110 `
0"
#750000
0E
1)
b1110 _
b101 <
1"
#760000
0"
#770000
1-
0)
1&
1E
b111 <
b1011 _
1"
#780000
b1111 F
b1111 K
b1111 `
b1110 %
b1110 0
b1110 =
b10101010000000000 .
b10101010000000000 ?
0"
#790000
0E
0-
0&
b1110 _
b1000 <
1"
#800000
0"
#810000
1E
b11 <
b1011 _
1"
#820000
b10000 F
b10000 K
b10000 `
0"
#830000
0E
1)
b1110 _
b101 <
1"
#840000
0"
#850000
1-
0)
1&
1E
b111 <
b1011 _
1"
#860000
b10001 F
b10001 K
b10001 `
b1101 %
b1101 0
b1101 =
b101010100000000000 .
b101010100000000000 ?
0"
#870000
0E
0-
0&
b1110 _
b1000 <
1"
#880000
0"
#890000
1E
b11 <
b1011 _
1"
#900000
b10010 F
b10010 K
b10010 `
0"
#910000
0E
1)
b1110 _
b101 <
1"
#920000
0"
#930000
1-
0)
1&
1E
b111 <
b1011 _
1"
#940000
b10011 F
b10011 K
b10011 `
b1100 %
b1100 0
b1100 =
b1010101000000000000 .
b1010101000000000000 ?
0"
#950000
0E
0-
0&
b1110 _
b1000 <
1"
#960000
0"
#970000
1E
b11 <
b1011 _
1"
#980000
b10100 F
b10100 K
b10100 `
0"
#990000
0E
1)
b1110 _
b101 <
1"
#1000000
0"
#1010000
1-
0)
1&
1E
b111 <
b1011 _
1"
#1020000
b10101 F
b10101 K
b10101 `
b1011 %
b1011 0
b1011 =
b10101010000000000000 .
b10101010000000000000 ?
0"
#1030000
0E
0-
0&
b1110 _
b1000 <
1"
#1040000
0"
#1050000
1E
b11 <
b1011 _
1"
#1060000
b10110 F
b10110 K
b10110 `
0"
#1070000
0E
1)
b1110 _
b101 <
1"
#1080000
0"
#1090000
1-
0)
1&
1E
b111 <
b1011 _
1"
#1100000
b10111 F
b10111 K
b10111 `
b1010 %
b1010 0
b1010 =
b101010100000000000000 .
b101010100000000000000 ?
0"
#1110000
0E
0-
0&
b1110 _
b1000 <
1"
#1120000
0"
#1130000
1E
b11 <
b1011 _
1"
#1140000
b11000 F
b11000 K
b11000 `
0"
#1150000
0E
1)
b1110 _
b101 <
1"
#1160000
0"
#1170000
1-
0)
1&
1E
b111 <
b1011 _
1"
#1180000
b11001 F
b11001 K
b11001 `
b1001 %
b1001 0
b1001 =
b1010101000000000000000 .
b1010101000000000000000 ?
0"
#1190000
0E
0-
0&
b1110 _
b1000 <
1"
#1200000
0"
#1210000
1E
b11 <
b1011 _
1"
#1220000
b11010 F
b11010 K
b11010 `
0"
#1230000
0E
1)
b1110 _
b101 <
1"
#1240000
0"
#1250000
1-
0)
1&
1E
b111 <
b1011 _
1"
#1260000
b11011 F
b11011 K
b11011 `
b1000 %
b1000 0
b1000 =
b10101010000000000000000 .
b10101010000000000000000 ?
0"
#1270000
0E
0-
0&
b1110 _
b1000 <
1"
#1280000
0"
#1290000
1E
b11 <
b1011 _
1"
#1300000
b11100 F
b11100 K
b11100 `
0"
#1310000
0E
1)
b1110 _
b101 <
1"
#1320000
0"
#1330000
1-
0)
1&
1E
b111 <
b1011 _
1"
#1340000
1/
b11101 F
b11101 K
b11101 `
b111 %
b111 0
b111 =
b101010100000000000000000 .
b101010100000000000000000 ?
0"
#1350000
0E
0-
0&
b1110 _
b1000 <
1"
#1360000
0"
#1370000
1E
b11 <
b1011 _
1"
#1380000
b11110 F
b11110 K
b11110 `
0"
#1390000
0E
b1 '
b1 ;
b1 @
b1 M
1)
b1110 _
b100 <
1"
#1400000
0"
#1410000
1-
b0 '
b0 ;
b0 @
b0 M
0)
1&
1E
b111 <
b1011 _
1"
#1420000
1A
0/
b11111 F
b11111 K
b11111 `
b110 %
b110 0
b110 =
b10101000000000000000000 .
b10101000000000000000000 ?
0"
#1430000
0E
0-
0&
b1110 _
b1000 <
1"
#1440000
0"
#1450000
0A
b1010 D
b1010 L
b1010 f
b0 B
b0 ^
b0 e
1+
b11 <
b1111 _
1"
#1460000
0"
#1470000
0+
1)
b0 _
b101 <
1"
#1480000
0"
#1490000
1-
0)
1&
b111 <
b1 _
1"
#1500000
1/
b101 %
b101 0
b101 =
b101010000000000000000000 .
b101010000000000000000000 ?
0"
#1510000
0-
0&
b1000 <
1"
#1520000
0"
#1530000
b11 <
1"
#1540000
0"
#1550000
b1 '
b1 ;
b1 @
b1 M
1)
b100 <
1"
#1560000
0"
#1570000
1-
b0 '
b0 ;
b0 @
b0 M
0)
1&
1C
b111 <
b10 _
1"
#1580000
0/
b0 F
b0 K
b0 `
b100 %
b100 0
b100 =
b10100000000000000000000 .
b10100000000000000000000 ?
0"
#1590000
0C
0-
0&
b11 _
b1000 <
1"
#1600000
0"
#1610000
b11 <
b100 _
1"
#1620000
0"
#1630000
1*
1)
b111 _
b101 <
1"
#1640000
0"
#1650000
1-
0)
1&
1E
b111 <
b1001 _
1"
#1660000
1/
b1 F
b1 K
b1 `
b11 %
b11 0
b11 =
b101000000000000000000000 .
b101000000000000000000000 ?
0"
#1670000
0E
0-
0&
b1010 _
b1000 <
1"
#1680000
0"
#1690000
1E
b11 <
b1001 _
1"
#1700000
b10 F
b10 K
b10 `
0"
#1710000
0E
b1 '
b1 ;
b1 @
b1 M
1)
b1010 _
b100 <
1"
#1720000
0"
#1730000
1-
b0 '
b0 ;
b0 @
b0 M
0)
1&
1E
b111 <
b1001 _
1"
#1740000
0/
b11 F
b11 K
b11 `
b10 %
b10 0
b10 =
b10000000000000000000000 .
b10000000000000000000000 ?
0"
#1750000
0E
0-
0&
b1010 _
b1000 <
1"
#1760000
0"
#1770000
1E
b11 <
b1001 _
1"
#1780000
b100 F
b100 K
b100 `
0"
#1790000
0E
1)
b1010 _
b101 <
1"
#1800000
0"
#1810000
1-
0)
1&
1E
b111 <
b1001 _
1"
#1820000
1/
b101 F
b101 K
b101 `
b1 %
b1 0
b1 =
b100000000000000000000000 .
b100000000000000000000000 ?
0"
#1830000
0E
0-
0&
b1010 _
b1000 <
1"
#1840000
0"
#1850000
1E
b11 <
b1001 _
1"
#1860000
b110 F
b110 K
b110 `
0"
#1870000
0E
b1 '
b1 ;
b1 @
b1 M
1)
b1010 _
b100 <
1"
#1880000
0"
#1890000
1-
b0 '
b0 ;
b0 @
b0 M
0)
1&
1E
b111 <
b1001 _
1"
#1900000
0/
b111 F
b111 K
b111 `
b0 %
b0 0
b0 =
b0 .
b0 ?
0"
#1910000
0E
0-
0&
b1010 _
b1000 <
1"
#1920000
0"
#1930000
1,
1E
b1001 <
b1001 _
1"
#1940000
b1000 F
b1000 K
b1000 `
0"
#1950000
0E
0,
b1010 _
b0 <
1"
#1960000
0"
#1970000
1E
b1 <
b1001 _
1"
#1980000
b1001 F
b1001 K
b1001 `
0"
#1990000
0E
b1010 _
1"
#2000000
0"
#2010000
1E
b1001 _
1"
#2020000
1A
b1010 F
b1010 K
b1010 `
0"
#2030000
0E
b1010 _
1"
