Electronica Digital 1/ModuloRaizCuadrada/Control_RaizCuadrada.v
// Modulo de Unidad de Control para algoritmo de raiz cuadrada
module Control_RaizCuadrada ( 
    input clk,
    input rst,  
    input i_eq_zero,
    input resp_more_eq_op,
    input init, 
    output reg load,
    output reg assi,
    output reg root_bit,   // valor fijo (0 o 1) que se escribe en Rf[0] cuando assi=1
    output reg subs,
    output reg decrease,
    output reg shift,
    output reg done
    );

    parameter START    = 4'b0000;
    parameter CHECK1   = 4'b0001;
    parameter LOAD     = 4'b0010;
    parameter SHIFT1   = 4'b0011;   
    parameter SHIFT2   = 4'b0100;
    parameter ASSIGN1  = 4'b0101;   
    parameter CHECK2   = 4'b0110;
    parameter ASSIGN2  = 4'b0111;
    parameter SUBSTRAC = 4'b1000;
    parameter ASSIGN3  = 4'b1001;
    parameter DECREASE = 4'b1010;   
    parameter CHECK3   = 4'b1011;
    parameter FINISH   = 4'b1100;

    reg [3:0] state;

    always @(*) begin
        load       = 0;
        shift      = 0;
        decrease   = 0;
        assi       = 0;
        root_bit   = 0;
        subs       = 0;
        done       = 0;

        case (state)
            LOAD:     load  = 1;
            // SHIFT1 es puente: solo SHIFT2 corre los registros, para que
            // el primer bloque de 2 bits no se corra el doble que los demas.
            SHIFT2:   shift = 1;
            SUBSTRAC: subs  = 1;
            // El bit de la raiz se escribe DESPUES de decidir (no en ASSIGN1),
            // y con un valor fijo por rama: no se relee la comparacion en vivo
            // porque despues de restar, Resp ya cambio y esa lectura ya no
            // corresponde a la decision que se tomo en CHECK2.
            ASSIGN2:  begin assi = 1; root_bit = 0; end  // no hubo resta -> bit 0
            ASSIGN3:  begin assi = 1; root_bit = 1; end  // hubo resta   -> bit 1
            DECREASE: decrease = 1;
            FINISH:   done  = 1;
            default: ; // START, CHECK1, SHIFT1, ASSIGN1, CHECK2, CHECK3: sin senal
        endcase
    end

    always @(posedge clk) begin
        if (rst) begin
            state <= START; 
        end 
        else begin
            case (state)
                START:    state <= CHECK1;
                CHECK1:   state <= init ? LOAD : CHECK1;
                LOAD:     state <= SHIFT1;
                SHIFT1:   state <= SHIFT2;
                SHIFT2:   state <= ASSIGN1;
                ASSIGN1:  state <= CHECK2;
                // se resta cuando Resp >= Op
                CHECK2:   state <= resp_more_eq_op ? SUBSTRAC : ASSIGN2;
                ASSIGN2:  state <= DECREASE;
                SUBSTRAC: state <= ASSIGN3;
                ASSIGN3:  state <= DECREASE;
                DECREASE: state <= CHECK3;
                CHECK3:   state <= i_eq_zero ? FINISH : SHIFT2;
                FINISH:   state <= START;
                default:  state <= START;
            endcase
        end
    end

endmodule

Electronica Digital 1/ModuloRaizCuadrada/Reg_Rf.v
// Registro de la raiz (Rf).
//  - load : reinicia Rf a 0
//  - assi : corre 1 bit a la izquierda E inserta el nuevo bit en un solo paso
//           (Rf <= {Rf[12:0], value}). Asi "Op = {Rf,01}" siempre usa el Rf
//           tal como quedo en la iteracion anterior, sin corrimiento previo.
module Reg_Rf (
    input clk,
    input rst,
    input load,
    input assi,
    input value,
    output reg [13:0] Rf
);

    always @(negedge clk or posedge rst) begin
        if (rst) begin
            Rf <= 14'd0;
        end
        else if (load) begin
            Rf <= 14'd0;
        end
        else if (assi) begin
            Rf <= {Rf[12:0], value};
        end
    end

endmodule

Electronica Digital 1/ModuloRaizCuadrada/Reg_RA.v
// Registro combinado Resp:A (32 bits).
//  - load : carga A en la mitad baja, Resp en 0
//  - shift: corre 2 bits a la izquierda (se procesan 2 bits de A por iteracion)
//  - subs : resta el divisor de prueba Op de la mitad alta (Resp)
module Reg_RA (
    input clk,
    input rst,
    input load,
    input shift,
    input subs,
    input [15:0] A,
    input [15:0] Op,
    output reg [31:0] RA
);

    always @(negedge clk or posedge rst) begin
        if (rst) begin
            RA <= 32'd0;
        end
        else if (load) begin
            RA <= {16'd0, A};
        end
        else if (shift) begin
            RA <= RA << 2;
        end
        else if (subs) begin
            RA[31:16] <= RA[31:16] - Op;
        end
    end

endmodule

Electronica Digital 1/ModuloRaizCuadrada/Decrease.v
// Modulo de incremento I
module Decrease (
    input clk,
    input load,         
    input decrease,     
    output reg [5:0] i 
);

   
    always @(negedge clk) begin
        if (load) begin
            i <= 6'd8;         
        end 
        else if (decrease) begin
            i <= i - 1'b1;   
        end
    end

endmodule

Electronica Digital 1/ModuloRaizCuadrada/Comp.v
//Modulo que compara dos valores dependendiendo de lo que se requiera comparar

module Comp(
    input [15:0] a,
    input [15:0] b,
    output reg igual,
    output reg mayor
);

    always @(*) begin
        igual = (a == b);
        mayor = (a > b);
    end

endmodule

Electronica Digital 1/ModuloRaizCuadrada/RaizCuadrada.v
module Raiz_Cuadrada (
    input clk,
    input rst,        
    input [15:0] A,         
    input init,         
    output [13:0] Rf,    
    output done   
);

    wire resp_eq_op;
    wire resp_gt_op;
    wire resp_more_eq_op;
    wire i_eq_zero;
    wire load;
    wire shift;      // corre solo Reg_RA (2 bits por iteracion)
    wire subs;
    wire assi;
    wire root_bit;
    wire decrease;
    wire [5:0]  i;
    wire [31:0] RA;
    wire [15:0] Op = {Rf, 2'b01};   // usa el Rf tal como quedo en la iteracion anterior

    Comp u_Comp_1(.a(RA[31:16]), .b(Op), .igual(resp_eq_op), .mayor(resp_gt_op));
    assign resp_more_eq_op = resp_eq_op | resp_gt_op;   // Resp >= Op

    Comp u_Comp_2(.a(i), .b(16'd0), .igual(i_eq_zero), .mayor());

    Decrease u_Decrease(.clk(clk), .load(load), .decrease(decrease), .i(i));

    Reg_RA u_Reg_RA(.clk(clk), .rst(rst), .load(load), .shift(shift), .subs(subs), .A(A), .Op(Op), .RA(RA));

    Reg_Rf u_Reg_Rf(.clk(clk), .rst(rst), .load(load), .assi(assi), .value(root_bit), .Rf(Rf));

    Control_RaizCuadrada u_Control_RaizCuadrada (
        .clk(clk), .rst(rst), .i_eq_zero(i_eq_zero), .resp_more_eq_op(resp_more_eq_op),
        .init(init), .load(load), .assi(assi), .root_bit(root_bit), .subs(subs),
        .decrease(decrease), .shift(shift), .done(done)
    );

endmodule

Electronica Digital 1/ModuloRaizCuadrada/RaizCuadrada_TB.v
`timescale 1ns / 1ps

module RaizCuadrada_TB;

    reg  clk;
    reg  rst;
    reg  [15:0] A;
    reg  init;
    wire [13:0] Rf;
    wire done;

    integer errors = 0;
    integer tests  = 0;

    Raiz_Cuadrada uut (
        .clk(clk), .rst(rst), .A(A), .init(init), .Rf(Rf), .done(done)
    );

    parameter PERIOD = 20;

    // Generacion de reloj
    initial begin
        clk = 0;
        forever #(PERIOD/2) clk = ~clk;
    end

    // Raiz cuadrada entera de referencia (solo para el testbench, NO sintetizable)
    function [13:0] isqrt;
        input [15:0] value;
        integer r;
        begin
            r = 0;
            while ((r + 1) * (r + 1) <= value)
                r = r + 1;
            isqrt = r[13:0];
        end
    endfunction

    // Corre un caso: carga A, dispara init, espera "done" y compara Rf
    task run_test;
        input [15:0] value;
        reg   [13:0] expected;
        begin
            expected = isqrt(value);
            tests = tests + 1;

            A = value;
            @(negedge clk);
            init = 1;
            @(negedge clk);
            init = 0;

            wait (done == 1'b1);
            @(negedge clk);

            if (Rf !== expected) begin
                errors = errors + 1;
                $display("FALLO  A=%0d  Rf=%0d  esperado=%0d", value, Rf, expected);
            end
            else begin
                $display("OK     A=%0d  ->  raiz=%0d", value, Rf);
            end

            @(negedge clk);
        end
    endtask

    initial begin
        rst  = 1;
        A    = 0;
        init = 0;
        repeat (2) @(negedge clk);
        rst = 0;
        repeat (2) @(negedge clk);

        run_test(16'd0);      // raiz exacta = 0
        run_test(16'd1);      // raiz exacta = 1
        run_test(16'd4);      // raiz exacta = 2
        run_test(16'd8);      // no exacta -> 2 (resto 4)
        run_test(16'd9);      // raiz exacta = 3
        run_test(16'd15);     // no exacta -> 3 (resto 6)
        run_test(16'd16);     // raiz exacta = 4
        run_test(16'd255);    // no exacta -> 15 (resto 30)
        run_test(16'd1000);   // no exacta -> 31 (resto 39)
        run_test(16'd65535);  // maximo de 16 bits -> 255 (resto 510)

        $display("----------------------------------------");
        if (errors == 0)
            $display("TODAS LAS PRUEBAS PASARON (%0d/%0d)", tests, tests);
        else
            $display("%0d de %0d PRUEBAS FALLARON", errors, tests);

        $finish;
    end

    // Captura de formas de onda
    initial begin
        $dumpfile("RaizCuadrada_TB.vcd");
        $dumpvars(-1, uut);
    end

endmodule

Electronica Digital 1/ModuloRaizCuadrada/RaizCuadrada_TB.vcd
$date
	Tue Jul  7 14:57:59 2026
$end
$version
	Icarus Verilog
$end
$timescale
	1ps
$end
$scope module RaizCuadrada_TB $end
$scope module uut $end
$var wire 16 ! A [15:0] $end
$var wire 1 " clk $end
$var wire 1 # init $end
$var wire 1 $ resp_more_eq_op $end
$var wire 1 % rst $end
$var wire 1 & subs $end
$var wire 1 ' shift $end
$var wire 1 ( root_bit $end
$var wire 1 ) resp_gt_op $end
$var wire 1 * resp_eq_op $end
$var wire 1 + load $end
$var wire 1 , i_eq_zero $end
$var wire 6 - i [5:0] $end
$var wire 1 . done $end
$var wire 1 / decrease $end
$var wire 1 0 assi $end
$var wire 14 1 Rf [13:0] $end
$var wire 32 2 RA [31:0] $end
$var wire 16 3 Op [15:0] $end
$scope module u_Comp_1 $end
$var wire 16 4 a [15:0] $end
$var wire 16 5 b [15:0] $end
$var reg 1 * igual $end
$var reg 1 ) mayor $end
$upscope $end
$scope module u_Comp_2 $end
$var wire 16 6 a [15:0] $end
$var wire 16 7 b [15:0] $end
$var reg 1 , igual $end
$var reg 1 8 mayor $end
$upscope $end
$scope module u_Control_RaizCuadrada $end
$var wire 1 " clk $end
$var wire 1 , i_eq_zero $end
$var wire 1 # init $end
$var wire 1 $ resp_more_eq_op $end
$var wire 1 % rst $end
$var parameter 4 9 ASSIGN1 $end
$var parameter 4 : ASSIGN2 $end
$var parameter 4 ; ASSIGN3 $end
$var parameter 4 < CHECK1 $end
$var parameter 4 = CHECK2 $end
$var parameter 4 > CHECK3 $end
$var parameter 4 ? DECREASE $end
$var parameter 4 @ FINISH $end
$var parameter 4 A LOAD $end
$var parameter 4 B SHIFT1 $end
$var parameter 4 C SHIFT2 $end
$var parameter 4 D START $end
$var parameter 4 E SUBSTRAC $end
$var reg 1 0 assi $end
$var reg 1 / decrease $end
$var reg 1 . done $end
$var reg 1 + load $end
$var reg 1 ( root_bit $end
$var reg 1 ' shift $end
$var reg 4 F state [3:0] $end
$var reg 1 & subs $end
$upscope $end
$scope module u_Decrease $end
$var wire 1 " clk $end
$var wire 1 / decrease $end
$var wire 1 + load $end
$var reg 6 G i [5:0] $end
$upscope $end
$scope module u_Reg_RA $end
$var wire 16 H A [15:0] $end
$var wire 16 I Op [15:0] $end
$var wire 1 " clk $end
$var wire 1 + load $end
$var wire 1 % rst $end
$var wire 1 ' shift $end
$var wire 1 & subs $end
$var reg 32 J RA [31:0] $end
$upscope $end
$scope module u_Reg_Rf $end
$var wire 1 0 assi $end
$var wire 1 " clk $end
$var wire 1 + load $end
$var wire 1 % rst $end
$var wire 1 ( value $end
$var reg 14 K Rf [13:0] $end
$upscope $end
$upscope $end
$upscope $end
$enddefinitions $end
$comment Show the parameter values. $end
$dumpall
b1000 E
b0 D
b100 C
b11 B
b10 A
b1100 @
b1010 ?
b1011 >
b110 =
b1 <
b1001 ;
b111 :
b101 9
$end
#0
$dumpvars
b0 K
b0 J
b1 I
b0 H
bx G
bx F
x8
b0 7
b0xxxxxx 6
b1 5
b0 4
b1 3
b0 2
b0 1
x0
x/
x.
bx -
x,
x+
0*
0)
x(
x'
x&
1%
0$
0#
0"
b0 !
$end
#10000
0.
0&
0(
00
0/
0'
0+
b0 F
1"
#20000
0"
#30000
1"
#40000
0%
0"
#50000
b1 F
1"
#60000
0"
#70000
1"
#80000
0"
#90000
1"
#100000
1#
0"
#110000
1+
b10 F
1"
#120000
18
0,
b1000 6
b1000 -
b1000 G
0#
0"
#130000
0+
b11 F
1"
#140000
0"
#150000
1'
b100 F
1"
#160000
0"
#170000
0'
b101 F
1"
#180000
0"
#190000
b110 F
1"
#200000
0"
#210000
10
b111 F
1"
#220000
0"
#230000
1/
00
b1010 F
1"
#240000
b111 6
b111 -
b111 G
0"
#250000
0/
b1011 F
1"
#260000
0"
#270000
1'
b100 F
1"
#280000
0"
#290000
0'
b101 F
1"
#300000
0"
#310000
b110 F
1"
#320000
0"
#330000
10
b111 F
1"
#340000
0"
#350000
1/
00
b1010 F
1"
#360000
b110 6
b110 -
b110 G
0"
#370000
0/
b1011 F
1"
#380000
0"
#390000
1'
b100 F
1"
#400000
0"
#410000
0'
b101 F
1"
#420000
0"
#430000
b110 F
1"
#440000
0"
#450000
10
b111 F
1"
#460000
0"
#470000
1/
00
b1010 F
1"
#480000
b101 6
b101 -
b101 G
0"
#490000
0/
b1011 F
1"
#500000
0"
#510000
1'
b100 F
1"
#520000
0"
#530000
0'
b101 F
1"
#540000
0"
#550000
b110 F
1"
#560000
0"
#570000
10
b111 F
1"
#580000
0"
#590000
1/
00
b1010 F
1"
#600000
b100 6
b100 -
b100 G
0"
#610000
0/
b1011 F
1"
#620000
0"
#630000
1'
b100 F
1"
#640000
0"
#650000
0'
b101 F
1"
#660000
0"
#670000
b110 F
1"
#680000
0"
#690000
10
b111 F
1"
#700000
0"
#710000
1/
00
b1010 F
1"
#720000
b11 6
b11 -
b11 G
0"
#730000
0/
b1011 F
1"
#740000
0"
#750000
1'
b100 F
1"
#760000
0"
#770000
0'
b101 F
1"
#780000
0"
#790000
b110 F
1"
#800000
0"
#810000
10
b111 F
1"
#820000
0"
#830000
1/
00
b1010 F
1"
#840000
b10 6
b10 -
b10 G
0"
#850000
0/
b1011 F
1"
#860000
0"
#870000
1'
b100 F
1"
#880000
0"
#890000
0'
b101 F
1"
#900000
0"
#910000
b110 F
1"
#920000
0"
#930000
10
b111 F
1"
#940000
0"
#950000
1/
00
b1010 F
1"
#960000
b1 6
b1 -
b1 G
0"
#970000
0/
b1011 F
1"
#980000
0"
#990000
1'
b100 F
1"
#1000000
0"
#1010000
0'
b101 F
1"
#1020000
0"
#1030000
b110 F
1"
#1040000
0"
#1050000
10
b111 F
1"
#1060000
0"
#1070000
1/
00
b1010 F
1"
#1080000
08
1,
b0 6
b0 -
b0 G
0"
#1090000
0/
b1011 F
1"
#1100000
0"
#1110000
1.
b1100 F
1"
#1120000
0"
#1130000
0.
b0 F
1"
#1140000
b1 !
b1 H
0"
#1150000
b1 F
1"
#1160000
1#
0"
#1170000
1+
b10 F
1"
#1180000
18
0,
b1 2
b1 J
b1000 6
b1000 -
b1000 G
0#
0"
#1190000
0+
b11 F
1"
#1200000
0"
#1210000
1'
b100 F
1"
#1220000
b100 2
b100 J
0"
#1230000
0'
b101 F
1"
#1240000
0"
#1250000
b110 F
1"
#1260000
0"
#1270000
10
b111 F
1"
#1280000
0"
#1290000
1/
00
b1010 F
1"
#1300000
b111 6
b111 -
b111 G
0"
#1310000
0/
b1011 F
1"
#1320000
0"
#1330000
1'
b100 F
1"
#1340000
b10000 2
b10000 J
0"
#1350000
0'
b101 F
1"
#1360000
0"
#1370000
b110 F
1"
#1380000
0"
#1390000
10
b111 F
1"
#1400000
0"
#1410000
1/
00
b1010 F
1"
#1420000
b110 6
b110 -
b110 G
0"
#1430000
0/
b1011 F
1"
#1440000
0"
#1450000
1'
b100 F
1"
#1460000
b1000000 2
b1000000 J
0"
#1470000
0'
b101 F
1"
#1480000
0"
#1490000
b110 F
1"
#1500000
0"
#1510000
10
b111 F
1"
#1520000
0"
#1530000
1/
00
b1010 F
1"
#1540000
b101 6
b101 -
b101 G
0"
#1550000
0/
b1011 F
1"
#1560000
0"
#1570000
1'
b100 F
1"
#1580000
b100000000 2
b100000000 J
0"
#1590000
0'
b101 F
1"
#1600000
0"
#1610000
b110 F
1"
#1620000
0"
#1630000
10
b111 F
1"
#1640000
0"
#1650000
1/
00
b1010 F
1"
#1660000
b100 6
b100 -
b100 G
0"
#1670000
0/
b1011 F
1"
#1680000
0"
#1690000
1'
b100 F
1"
#1700000
b10000000000 2
b10000000000 J
0"
#1710000
0'
b101 F
1"
#1720000
0"
#1730000
b110 F
1"
#1740000
0"
#1750000
10
b111 F
1"
#1760000
0"
#1770000
1/
00
b1010 F
1"
#1780000
b11 6
b11 -
b11 G
0"
#1790000
0/
b1011 F
1"
#1800000
0"
#1810000
1'
b100 F
1"
#1820000
b1000000000000 2
b1000000000000 J
0"
#1830000
0'
b101 F
1"
#1840000
0"
#1850000
b110 F
1"
#1860000
0"
#1870000
10
b111 F
1"
#1880000
0"
#1890000
1/
00
b1010 F
1"
#1900000
b10 6
b10 -
b10 G
0"
#1910000
0/
b1011 F
1"
#1920000
0"
#1930000
1'
b100 F
1"
#1940000
b100000000000000 2
b100000000000000 J
0"
#1950000
0'
b101 F
1"
#1960000
0"
#1970000
b110 F
1"
#1980000
0"
#1990000
10
b111 F
1"
#2000000
0"
#2010000
1/
00
b1010 F
1"
#2020000
b1 6
b1 -
b1 G
0"
#2030000
0/
b1011 F
1"
#2040000
0"
#2050000
1'
b100 F
1"
#2060000
1$
1*
b1 4
b10000000000000000 2
b10000000000000000 J
0"
#2070000
0'
b101 F
1"
#2080000
0"
#2090000
b110 F
1"
#2100000
0"
#2110000
1&
b1000 F
1"
#2120000
0$
0*
b0 4
b0 2
b0 J
0"
#2130000
1(
10
0&
b1001 F
1"
#2140000
b101 3
b101 5
b101 I
b1 1
b1 K
0"
#2150000
1/
0(
00
b1010 F
1"
#2160000
08
1,
b0 6
b0 -
b0 G
0"
#2170000
0/
b1011 F
1"
#2180000
0"
#2190000
1.
b1100 F
1"
#2200000
0"
#2210000
0.
b0 F
1"
#2220000
b100 !
b100 H
0"
#2230000
b1 F
1"
#2240000
1#
0"
#2250000
1+
b10 F
1"
#2260000
18
0,
b1 3
b1 5
b1 I
b0 1
b0 K
b100 2
b100 J
b1000 6
b1000 -
b1000 G
0#
0"
#2270000
0+
b11 F
1"
#2280000
0"
#2290000
1'
b100 F
1"
#2300000
b10000 2
b10000 J
0"
#2310000
0'
b101 F
1"
#2320000
0"
#2330000
b110 F
1"
#2340000
0"
#2350000
10
b111 F
1"
#2360000
0"
#2370000
1/
00
b1010 F
1"
#2380000
b111 6
b111 -
b111 G
0"
#2390000
0/
b1011 F
1"
#2400000
0"
#2410000
1'
b100 F
1"
#2420000
b1000000 2
b1000000 J
0"
#2430000
0'
b101 F
1"
#2440000
0"
#2450000
b110 F
1"
#2460000
0"
#2470000
10
b111 F
1"
#2480000
0"
#2490000
1/
00
b1010 F
1"
#2500000
b110 6
b110 -
b110 G
0"
#2510000
0/
b1011 F
1"
#2520000
0"
#2530000
1'
b100 F
1"
#2540000
b100000000 2
b100000000 J
0"
#2550000
0'
b101 F
1"
#2560000
0"
#2570000
b110 F
1"
#2580000
0"
#2590000
10
b111 F
1"
#2600000
0"
#2610000
1/
00
b1010 F
1"
#2620000
b101 6
b101 -
b101 G
0"
#2630000
0/
b1011 F
1"
#2640000
0"
#2650000
1'
b100 F
1"
#2660000
b10000000000 2
b10000000000 J
0"
#2670000
0'
b101 F
1"
#2680000
0"
#2690000
b110 F
1"
#2700000
0"
#2710000
10
b111 F
1"
#2720000
0"
#2730000
1/
00
b1010 F
1"
#2740000
b100 6
b100 -
b100 G
0"
#2750000
0/
b1011 F
1"
#2760000
0"
#2770000
1'
b100 F
1"
#2780000
b1000000000000 2
b1000000000000 J
0"
#2790000
0'
b101 F
1"
#2800000
0"
#2810000
b110 F
1"
#2820000
0"
#2830000
10
b111 F
1"
#2840000
0"
#2850000
1/
00
b1010 F
1"
#2860000
b11 6
b11 -
b11 G
0"
#2870000
0/
b1011 F
1"
#2880000
0"
#2890000
1'
b100 F
1"
#2900000
b100000000000000 2
b100000000000000 J
0"
#2910000
0'
b101 F
1"
#2920000
0"
#2930000
b110 F
1"
#2940000
0"
#2950000
10
b111 F
1"
#2960000
0"
#2970000
1/
00
b1010 F
1"
#2980000
b10 6
b10 -
b10 G
0"
#2990000
0/
b1011 F
1"
#3000000
0"
#3010000
1'
b100 F
1"
#3020000
1$
1*
b1 4
b10000000000000000 2
b10000000000000000 J
0"
#3030000
0'
b101 F
1"
#3040000
0"
#3050000
b110 F
1"
#3060000
0"
#3070000
1&
b1000 F
1"
#3080000
0$
0*
b0 4
b0 2
b0 J
0"
#3090000
1(
10
0&
b1001 F
1"
#3100000
b101 3
b101 5
b101 I
b1 1
b1 K
0"
#3110000
1/
0(
00
b1010 F
1"
#3120000
b1 6
b1 -
b1 G
0"
#3130000
0/
b1011 F
1"
#3140000
0"
#3150000
1'
b100 F
1"
#3160000
0"
#3170000
0'
b101 F
1"
#3180000
0"
#3190000
b110 F
1"
#3200000
0"
#3210000
10
b111 F
1"
#3220000
b1001 3
b1001 5
b1001 I
b10 1
b10 K
0"
#3230000
1/
00
b1010 F
1"
#3240000
08
1,
b0 6
b0 -
b0 G
0"
#3250000
0/
b1011 F
1"
#3260000
0"
#3270000
1.
b1100 F
1"
#3280000
0"
#3290000
0.
b0 F
1"
#3300000
b1000 !
b1000 H
0"
#3310000
b1 F
1"
#3320000
1#
0"
#3330000
1+
b10 F
1"
#3340000
18
0,
b1 3
b1 5
b1 I
b0 1
b0 K
b1000 2
b1000 J
b1000 6
b1000 -
b1000 G
0#
0"
#3350000
0+
b11 F
1"
#3360000
0"
#3370000
1'
b100 F
1"
#3380000
b100000 2
b100000 J
0"
#3390000
0'
b101 F
1"
#3400000
0"
#3410000
b110 F
1"
#3420000
0"
#3430000
10
b111 F
1"
#3440000
0"
#3450000
1/
00
b1010 F
1"
#3460000
b111 6
b111 -
b111 G
0"
#3470000
0/
b1011 F
1"
#3480000
0"
#3490000
1'
b100 F
1"
#3500000
b10000000 2
b10000000 J
0"
#3510000
0'
b101 F
1"
#3520000
0"
#3530000
b110 F
1"
#3540000
0"
#3550000
10
b111 F
1"
#3560000
0"
#3570000
1/
00
b1010 F
1"
#3580000
b110 6
b110 -
b110 G
0"
#3590000
0/
b1011 F
1"
#3600000
0"
#3610000
1'
b100 F
1"
#3620000
b1000000000 2
b1000000000 J
0"
#3630000
0'
b101 F
1"
#3640000
0"
#3650000
b110 F
1"
#3660000
0"
#3670000
10
b111 F
1"
#3680000
0"
#3690000
1/
00
b1010 F
1"
#3700000
b101 6
b101 -
b101 G
0"
#3710000
0/
b1011 F
1"
#3720000
0"
#3730000
1'
b100 F
1"
#3740000
b100000000000 2
b100000000000 J
0"
#3750000
0'
b101 F
1"
#3760000
0"
#3770000
b110 F
1"
#3780000
0"
#3790000
10
b111 F
1"
#3800000
0"
#3810000
1/
00
b1010 F
1"
#3820000
b100 6
b100 -
b100 G
0"
#3830000
0/
b1011 F
1"
#3840000
0"
#3850000
1'
b100 F
1"
#3860000
b10000000000000 2
b10000000000000 J
0"
#3870000
0'
b101 F
1"
#3880000
0"
#3890000
b110 F
1"
#3900000
0"
#3910000
10
b111 F
1"
#3920000
0"
#3930000
1/
00
b1010 F
1"
#3940000
b11 6
b11 -
b11 G
0"
#3950000
0/
b1011 F
1"
#3960000
0"
#3970000
1'
b100 F
1"
#3980000
b1000000000000000 2
b1000000000000000 J
0"
#3990000
0'
b101 F
1"
#4000000
0"
#4010000
b110 F
1"
#4020000
0"
#4030000
10
b111 F
1"
#4040000
0"
#4050000
1/
00
b1010 F
1"
#4060000
b10 6
b10 -
b10 G
0"
#4070000
0/
b1011 F
1"
#4080000
0"
#4090000
1'
b100 F
1"
#4100000
1$
1)
b10 4
b100000000000000000 2
b100000000000000000 J
0"
#4110000
0'
b101 F
1"
#4120000
0"
#4130000
b110 F
1"
#4140000
0"
#4150000
1&
b1000 F
1"
#4160000
0)
1*
b1 4
b10000000000000000 2
b10000000000000000 J
0"
#4170000
1(
10
0&
b1001 F
1"
#4180000
0$
0*
b101 3
b101 5
b101 I
b1 1
b1 K
0"
#4190000
1/
0(
00
b1010 F
1"
#4200000
b1 6
b1 -
b1 G
0"
#4210000
0/
b1011 F
1"
#4220000
0"
#4230000
1'
b100 F
1"
#4240000
b100 4
b1000000000000000000 2
b1000000000000000000 J
0"
#4250000
0'
b101 F
1"
#4260000
0"
#4270000
b110 F
1"
#4280000
0"
#4290000
10
b111 F
1"
#4300000
b1001 3
b1001 5
b1001 I
b10 1
b10 K
0"
#4310000
1/
00
b1010 F
1"
#4320000
08
1,
b0 6
b0 -
b0 G
0"
#4330000
0/
b1011 F
1"
#4340000
0"
#4350000
1.
b1100 F
1"
#4360000
0"
#4370000
0.
b0 F
1"
#4380000
b1001 !
b1001 H
0"
#4390000
b1 F
1"
#4400000
1#
0"
#4410000
1+
b10 F
1"
#4420000
b0 4
18
0,
b1 3
b1 5
b1 I
b0 1
b0 K
b1001 2
b1001 J
b1000 6
b1000 -
b1000 G
0#
0"
#4430000
0+
b11 F
1"
#4440000
0"
#4450000
1'
b100 F
1"
#4460000
b100100 2
b100100 J
0"
#4470000
0'
b101 F
1"
#4480000
0"
#4490000
b110 F
1"
#4500000
0"
#4510000
10
b111 F
1"
#4520000
0"
#4530000
1/
00
b1010 F
1"
#4540000
b111 6
b111 -
b111 G
0"
#4550000
0/
b1011 F
1"
#4560000
0"
#4570000
1'
b100 F
1"
#4580000
b10010000 2
b10010000 J
0"
#4590000
0'
b101 F
1"
#4600000
0"
#4610000
b110 F
1"
#4620000
0"
#4630000
10
b111 F
1"
#4640000
0"
#4650000
1/
00
b1010 F
1"
#4660000
b110 6
b110 -
b110 G
0"
#4670000
0/
b1011 F
1"
#4680000
0"
#4690000
1'
b100 F
1"
#4700000
b1001000000 2
b1001000000 J
0"
#4710000
0'
b101 F
1"
#4720000
0"
#4730000
b110 F
1"
#4740000
0"
#4750000
10
b111 F
1"
#4760000
0"
#4770000
1/
00
b1010 F
1"
#4780000
b101 6
b101 -
b101 G
0"
#4790000
0/
b1011 F
1"
#4800000
0"
#4810000
1'
b100 F
1"
#4820000
b100100000000 2
b100100000000 J
0"
#4830000
0'
b101 F
1"
#4840000
0"
#4850000
b110 F
1"
#4860000
0"
#4870000
10
b111 F
1"
#4880000
0"
#4890000
1/
00
b1010 F
1"
#4900000
b100 6
b100 -
b100 G
0"
#4910000
0/
b1011 F
1"
#4920000
0"
#4930000
1'
b100 F
1"
#4940000
b10010000000000 2
b10010000000000 J
0"
#4950000
0'
b101 F
1"
#4960000
0"
#4970000
b110 F
1"
#4980000
0"
#4990000
10
b111 F
1"
#5000000
0"
#5010000
1/
00
b1010 F
1"
#5020000
b11 6
b11 -
b11 G
0"
#5030000
0/
b1011 F
1"
#5040000
0"
#5050000
1'
b100 F
1"
#5060000
b1001000000000000 2
b1001000000000000 J
0"
#5070000
0'
b101 F
1"
#5080000
0"
#5090000
b110 F
1"
#5100000
0"
#5110000
10
b111 F
1"
#5120000
0"
#5130000
1/
00
b1010 F
1"
#5140000
b10 6
b10 -
b10 G
0"
#5150000
0/
b1011 F
1"
#5160000
0"
#5170000
1'
b100 F
1"
#5180000
1$
1)
b10 4
b100100000000000000 2
b100100000000000000 J
0"
#5190000
0'
b101 F
1"
#5200000
0"
#5210000
b110 F
1"
#5220000
0"
#5230000
1&
b1000 F
1"
#5240000
0)
1*
b1 4
b10100000000000000 2
b10100000000000000 J
0"
#5250000
1(
10
0&
b1001 F
1"
#5260000
0$
0*
b101 3
b101 5
b101 I
b1 1
b1 K
0"
#5270000
1/
0(
00
b1010 F
1"
#5280000
b1 6
b1 -
b1 G
0"
#5290000
0/
b1011 F
1"
#5300000
0"
#5310000
1'
b100 F
1"
#5320000
1$
1*
b101 4
b1010000000000000000 2
b1010000000000000000 J
0"
#5330000
0'
b101 F
1"
#5340000
0"
#5350000
b110 F
1"
#5360000
0"
#5370000
1&
b1000 F
1"
#5380000
0$
0*
b0 4
b0 2
b0 J
0"
#5390000
1(
10
0&
b1001 F
1"
#5400000
b1101 3
b1101 5
b1101 I
b11 1
b11 K
0"
#5410000
1/
0(
00
b1010 F
1"
#5420000
08
1,
b0 6
b0 -
b0 G
0"
#5430000
0/
b1011 F
1"
#5440000
0"
#5450000
1.
b1100 F
1"
#5460000
0"
#5470000
0.
b0 F
1"
#5480000
b1111 !
b1111 H
0"
#5490000
b1 F
1"
#5500000
1#
0"
#5510000
1+
b10 F
1"
#5520000
18
0,
b1111 2
b1111 J
b1 3
b1 5
b1 I
b0 1
b0 K
b1000 6
b1000 -
b1000 G
0#
0"
#5530000
0+
b11 F
1"
#5540000
0"
#5550000
1'
b100 F
1"
#5560000
b111100 2
b111100 J
0"
#5570000
0'
b101 F
1"
#5580000
0"
#5590000
b110 F
1"
#5600000
0"
#5610000
10
b111 F
1"
#5620000
0"
#5630000
1/
00
b1010 F
1"
#5640000
b111 6
b111 -
b111 G
0"
#5650000
0/
b1011 F
1"
#5660000
0"
#5670000
1'
b100 F
1"
#5680000
b11110000 2
b11110000 J
0"
#5690000
0'
b101 F
1"
#5700000
0"
#5710000
b110 F
1"
#5720000
0"
#5730000
10
b111 F
1"
#5740000
0"
#5750000
1/
00
b1010 F
1"
#5760000
b110 6
b110 -
b110 G
0"
#5770000
0/
b1011 F
1"
#5780000
0"
#5790000
1'
b100 F
1"
#5800000
b1111000000 2
b1111000000 J
0"
#5810000
0'
b101 F
1"
#5820000
0"
#5830000
b110 F
1"
#5840000
0"
#5850000
10
b111 F
1"
#5860000
0"
#5870000
1/
00
b1010 F
1"
#5880000
b101 6
b101 -
b101 G
0"
#5890000
0/
b1011 F
1"
#5900000
0"
#5910000
1'
b100 F
1"
#5920000
b111100000000 2
b111100000000 J
0"
#5930000
0'
b101 F
1"
#5940000
0"
#5950000
b110 F
1"
#5960000
0"
#5970000
10
b111 F
1"
#5980000
0"
#5990000
1/
00
b1010 F
1"
#6000000
b100 6
b100 -
b100 G
0"
