Electronica Digital 1/ModuloRaizCuadrada/Control_RaizCuadrada.v
// Modulo de Unidad de Control para algoritmo de raiz cuadrada
module Control_RaizCuadrada ( 
    input clk,
    input rst,  
    input i_eq_zero,
    input resp_more_eq_op,
    input init, 
    output reg load,
    output reg assi,
    output reg root_bit,   // valor fijo (0 o 1) que se escribe en Rf[0] cuando assi=1
    output reg subs,
    output reg decrease,
    output reg shift,
    output reg done
    );

    parameter START    = 4'b0000;
    parameter CHECK1   = 4'b0001;
    parameter LOAD     = 4'b0010;
    parameter SHIFT1   = 4'b0011;   
    parameter SHIFT2   = 4'b0100;
    parameter ASSIGN1  = 4'b0101;   
    parameter CHECK2   = 4'b0110;
    parameter ASSIGN2  = 4'b0111;
    parameter SUBSTRAC = 4'b1000;
    parameter ASSIGN3  = 4'b1001;
    parameter DECREASE = 4'b1010;   
    parameter CHECK3   = 4'b1011;
    parameter FINISH   = 4'b1100;

    reg [3:0] state;

    always @(*) begin
        load       = 0;
        shift      = 0;
        decrease   = 0;
        assi       = 0;
        root_bit   = 0;
        subs       = 0;
        done       = 0;

        case (state)
            LOAD:     load  = 1;
            // SHIFT1 es puente: solo SHIFT2 corre los registros, para que
            // el primer bloque de 2 bits no se corra el doble que los demas.
            SHIFT2:   shift = 1;
            SUBSTRAC: subs  = 1;
            // El bit de la raiz se escribe DESPUES de decidir (no en ASSIGN1),
            // y con un valor fijo por rama: no se relee la comparacion en vivo
            // porque despues de restar, Resp ya cambio y esa lectura ya no
            // corresponde a la decision que se tomo en CHECK2.
            ASSIGN2:  begin assi = 1; root_bit = 0; end  // no hubo resta -> bit 0
            ASSIGN3:  begin assi = 1; root_bit = 1; end  // hubo resta   -> bit 1
            DECREASE: decrease = 1;
            FINISH:   done  = 1;
            default: ; // START, CHECK1, SHIFT1, ASSIGN1, CHECK2, CHECK3: sin senal
        endcase
    end

    always @(posedge clk) begin
        if (rst) begin
            state <= START; 
        end 
        else begin
            case (state)
                START:    state <= CHECK1;
                CHECK1:   state <= init ? LOAD : CHECK1;
                LOAD:     state <= SHIFT1;
                SHIFT1:   state <= SHIFT2;
                SHIFT2:   state <= ASSIGN1;
                ASSIGN1:  state <= CHECK2;
                // se resta cuando Resp >= Op
                CHECK2:   state <= resp_more_eq_op ? SUBSTRAC : ASSIGN2;
                ASSIGN2:  state <= DECREASE;
                SUBSTRAC: state <= ASSIGN3;
                ASSIGN3:  state <= DECREASE;
                DECREASE: state <= CHECK3;
                CHECK3:   state <= i_eq_zero ? FINISH : SHIFT2;
                FINISH:   state <= START;
                default:  state <= START;
            endcase
        end
    end

endmodule

Electronica Digital 1/ModuloRaizCuadrada/Reg_Rf.v
// Modulo del registro de la raiz (Rf)
module Reg_Rf (
    input clk,
    input rst,
    input load,
    input assi,
    input value,
    output reg [13:0] Rf
);

    always @(negedge clk or posedge rst) begin
        if (rst) begin
            Rf <= 14'd0;
        end
        else if (load) begin
            Rf <= 14'd0;
        end
        else if (assi) begin
            Rf <= {Rf[12:0], value};
        end
    end

endmodule

Electronica Digital 1/ModuloRaizCuadrada/Reg_RA.v
//Modulo del registro combinado Resp:A 
module Reg_RA (
    input clk,
    input rst,
    input load,
    input shift,
    input subs,
    input [15:0] A,
    input [15:0] Op,
    output reg [31:0] RA
);

    always @(negedge clk or posedge rst) begin
        if (rst) begin
            RA <= 32'd0;
        end
        else if (load) begin
            RA <= {16'd0, A};
        end
        else if (shift) begin
            RA <= RA << 2;
        end
        else if (subs) begin
            RA[31:16] <= RA[31:16] - Op;
        end
    end

endmodule

Electronica Digital 1/ModuloRaizCuadrada/Decrease.v
// Modulo de incremento I
module Decrease (
    input clk,
    input load,         
    input decrease,     
    output reg [5:0] i 
);

   
    always @(negedge clk) begin
        if (load) begin
            i <= 6'd8;         
        end 
        else if (decrease) begin
            i <= i - 1'b1;   
        end
    end

endmodule

Electronica Digital 1/ModuloRaizCuadrada/Comp.v
//Modulo que compara dos valores dependendiendo de lo que se requiera comparar

module Comp(
    input [15:0] a,
    input [15:0] b,
    output reg igual,
    output reg mayor
);

    always @(*) begin
        igual = (a == b);
        mayor = (a > b);
    end

endmodule

Electronica Digital 1/ModuloRaizCuadrada/RaizCuadrada.v
//Modulo de la raiz cuadrada 
module Raiz_Cuadrada (
    input clk,
    input rst,        
    input [15:0] A,         
    input init,         
    output [13:0] Rf,    
    output done   
);

    wire resp_eq_op;
    wire resp_gt_op;
    wire resp_more_eq_op;
    wire i_eq_zero;
    wire load;
    wire shift;     
    wire subs;
    wire assi;
    wire root_bit;
    wire decrease;
    wire [5:0]  i;
    wire [31:0] RA;
    wire [15:0] Op = {Rf, 2'b01};   

    Comp u_Comp_1(.a(RA[31:16]), .b(Op), .igual(resp_eq_op), .mayor(resp_gt_op));
    assign resp_more_eq_op = resp_eq_op | resp_gt_op;  

    Comp u_Comp_2(.a(i), .b(16'd0), .igual(i_eq_zero), .mayor());

    Decrease u_Decrease(.clk(clk), .load(load), .decrease(decrease), .i(i));

    Reg_RA u_Reg_RA(.clk(clk), .rst(rst), .load(load), .shift(shift), .subs(subs), .A(A), .Op(Op), .RA(RA));

    Reg_Rf u_Reg_Rf(.clk(clk), .rst(rst), .load(load), .assi(assi), .value(root_bit), .Rf(Rf));

    Control_RaizCuadrada u_Control_RaizCuadrada (.clk(clk),.rst(rst),.i_eq_zero(i_eq_zero),.resp_more_eq_op(resp_more_eq_op),.init(init),.load(load),
    .assi(assi),.root_bit(root_bit),.subs(subs),.decrease(decrease), .shift(shift), .done(done));

endmodule

Electronica Digital 1/ModuloRaizCuadrada/RaizCuadrada_TB.v
`timescale 1ns / 1ps

module RaizCuadrada_TB;

    reg  clk;
    reg  rst;
    reg  [15:0] A;
    reg  init;
    wire [13:0] Rf;
    wire done;

    integer errors = 0;
    integer tests  = 0;

    Raiz_Cuadrada uut (
        .clk(clk), .rst(rst), .A(A), .init(init), .Rf(Rf), .done(done)
    );

    parameter PERIOD = 20;

    // Generacion de reloj
    initial begin
        clk = 0;
        forever #(PERIOD/2) clk = ~clk;
    end

    // Raiz cuadrada entera de referencia (solo para el testbench, NO sintetizable)
    function [13:0] isqrt;
        input [15:0] value;
        integer r;
        begin
            r = 0;
            while ((r + 1) * (r + 1) <= value)
                r = r + 1;
            isqrt = r[13:0];
        end
    endfunction

    // Corre un caso: carga A, dispara init, espera "done" y compara Rf
    task run_test;
        input [15:0] value;
        reg   [13:0] expected;
        begin
            expected = isqrt(value);
            tests = tests + 1;

            A = value;
            @(negedge clk);
            init = 1;
            @(negedge clk);
            init = 0;

            wait (done == 1'b1);
            @(negedge clk);

            if (Rf !== expected) begin
                errors = errors + 1;
                $display("FALLO  A=%0d  Rf=%0d  esperado=%0d", value, Rf, expected);
            end
            else begin
                $display("OK     A=%0d  ->  raiz=%0d", value, Rf);
            end

            @(negedge clk);
        end
    endtask

    initial begin
        rst  = 1;
        A    = 0;
        init = 0;
        repeat (2) @(negedge clk);
        rst = 0;
        repeat (2) @(negedge clk);

        run_test(16'd0);      // raiz exacta = 0
        run_test(16'd1);      // raiz exacta = 1
        run_test(16'd4);      // raiz exacta = 2
        run_test(16'd8);      // no exacta -> 2 (resto 4)
        run_test(16'd9);      // raiz exacta = 3
        run_test(16'd15);     // no exacta -> 3 (resto 6)
        run_test(16'd16);     // raiz exacta = 4
        run_test(16'd255);    // no exacta -> 15 (resto 30)
        run_test(16'd1000);   // no exacta -> 31 (resto 39)
        run_test(16'd65535);  // maximo de 16 bits -> 255 (resto 510)

        $display("----------------------------------------");
        if (errors == 0)
            $display("TODAS LAS PRUEBAS PASARON (%0d/%0d)", tests, tests);
        else
            $display("%0d de %0d PRUEBAS FALLARON", errors, tests);

        $finish;
    end

    // Captura de formas de onda
    initial begin
        $dumpfile("RaizCuadrada_TB.vcd");
        $dumpvars(-1, uut);
    end

endmodule

Electronica Digital 1/ModuloRaizCuadrada/RaizCuadrada_TB.vcd
$date
	Sun Jul 12 13:04:29 2026
$end
$version
	Icarus Verilog
$end
$timescale
	1ps
$end
$scope module RaizCuadrada_TB $end
$scope module uut $end
$var wire 16 ! A [15:0] $end
$var wire 1 " clk $end
$var wire 1 # init $end
$var wire 1 $ resp_more_eq_op $end
$var wire 1 % rst $end
$var wire 1 & subs $end
$var wire 1 ' shift $end
$var wire 1 ( root_bit $end
$var wire 1 ) resp_gt_op $end
$var wire 1 * resp_eq_op $end
$var wire 1 + load $end
$var wire 1 , i_eq_zero $end
$var wire 6 - i [5:0] $end
$var wire 1 . done $end
$var wire 1 / decrease $end
$var wire 1 0 assi $end
$var wire 14 1 Rf [13:0] $end
$var wire 32 2 RA [31:0] $end
$var wire 16 3 Op [15:0] $end
$scope module u_Comp_1 $end
$var wire 16 4 a [15:0] $end
$var wire 16 5 b [15:0] $end
$var reg 1 * igual $end
$var reg 1 ) mayor $end
$upscope $end
$scope module u_Comp_2 $end
$var wire 16 6 a [15:0] $end
$var wire 16 7 b [15:0] $end
$var reg 1 , igual $end
$var reg 1 8 mayor $end
$upscope $end
$scope module u_Control_RaizCuadrada $end
$var wire 1 " clk $end
$var wire 1 , i_eq_zero $end
$var wire 1 # init $end
$var wire 1 $ resp_more_eq_op $end
$var wire 1 % rst $end
$var parameter 4 9 ASSIGN1 $end
$var parameter 4 : ASSIGN2 $end
$var parameter 4 ; ASSIGN3 $end
$var parameter 4 < CHECK1 $end
$var parameter 4 = CHECK2 $end
$var parameter 4 > CHECK3 $end
$var parameter 4 ? DECREASE $end
$var parameter 4 @ FINISH $end
$var parameter 4 A LOAD $end
$var parameter 4 B SHIFT1 $end
$var parameter 4 C SHIFT2 $end
$var parameter 4 D START $end
$var parameter 4 E SUBSTRAC $end
$var reg 1 0 assi $end
$var reg 1 / decrease $end
$var reg 1 . done $end
$var reg 1 + load $end
$var reg 1 ( root_bit $end
$var reg 1 ' shift $end
$var reg 4 F state [3:0] $end
$var reg 1 & subs $end
$upscope $end
$scope module u_Decrease $end
$var wire 1 " clk $end
$var wire 1 / decrease $end
$var wire 1 + load $end
$var reg 6 G i [5:0] $end
$upscope $end
$scope module u_Reg_RA $end
$var wire 16 H A [15:0] $end
$var wire 16 I Op [15:0] $end
$var wire 1 " clk $end
$var wire 1 + load $end
$var wire 1 % rst $end
$var wire 1 ' shift $end
$var wire 1 & subs $end
$var reg 32 J RA [31:0] $end
$upscope $end
$scope module u_Reg_Rf $end
$var wire 1 0 assi $end
$var wire 1 " clk $end
$var wire 1 + load $end
$var wire 1 % rst $end
$var wire 1 ( value $end
$var reg 14 K Rf [13:0] $end
$upscope $end
$upscope $end
$upscope $end
$enddefinitions $end
$comment Show the parameter values. $end
$dumpall
b1000 E
b0 D
b100 C
b11 B
b10 A
b1100 @
b1010 ?
b1011 >
b110 =
b1 <
b1001 ;
b111 :
b101 9
$end
#0
$dumpvars
b0 K
b0 J
b1 I
b0 H
bx G
bx F
x8
b0 7
b0xxxxxx 6
b1 5
b0 4
b1 3
b0 2
b0 1
x0
x/
x.
bx -
x,
x+
0*
0)
x(
x'
x&
1%
0$
0#
0"
b0 !
$end
#10000
0.
0&
0(
00
0/
0'
0+
b0 F
1"
#20000
0%
0"
#30000
b1 F
1"
#40000
1#
b10010000 !
b10010000 H
0"
#50000
1+
b10 F
1"
#60000
18
0,
b1000 6
b1000 -
b1000 G
b10010000 2
b10010000 J
0#
0"
#70000
0+
b11 F
1"
#80000
0"
#90000
1'
b100 F
1"
#100000
b1001000000 2
b1001000000 J
0"
#110000
0'
b101 F
1"
#120000
0"
#130000
b110 F
1"
#140000
0"
#150000
10
b111 F
1"
#160000
0"
#170000
1/
00
b1010 F
1"
#180000
b111 6
b111 -
b111 G
0"
#190000
0/
b1011 F
1"
#200000
0"
#210000
1'
b100 F
1"
#220000
b100100000000 2
b100100000000 J
0"
#230000
0'
b101 F
1"
#240000
0"
#250000
b110 F
1"
#260000
0"
#270000
10
b111 F
1"
#280000
0"
#290000
1/
00
b1010 F
1"
#300000
b110 6
b110 -
b110 G
0"
#310000
0/
b1011 F
1"
#320000
0"
#330000
1'
b100 F
1"
#340000
b10010000000000 2
b10010000000000 J
0"
#350000
0'
b101 F
1"
#360000
0"
#370000
b110 F
1"
#380000
0"
#390000
10
b111 F
1"
#400000
0"
#410000
1/
00
b1010 F
1"
#420000
b101 6
b101 -
b101 G
0"
#430000
0/
b1011 F
1"
#440000
0"
#450000
1'
b100 F
1"
#460000
b1001000000000000 2
b1001000000000000 J
0"
#470000
0'
b101 F
1"
#480000
0"
#490000
b110 F
1"
#500000
0"
#510000
10
b111 F
1"
#520000
0"
#530000
1/
00
b1010 F
1"
#540000
b100 6
b100 -
b100 G
0"
#550000
0/
b1011 F
1"
#560000
0"
#570000
1'
b100 F
1"
#580000
1$
1)
b10 4
b100100000000000000 2
b100100000000000000 J
0"
#590000
0'
b101 F
1"
#600000
0"
#610000
b110 F
1"
#620000
0"
#630000
1&
b1000 F
1"
#640000
0)
1*
b1 4
b10100000000000000 2
b10100000000000000 J
0"
#650000
1(
10
0&
b1001 F
1"
#660000
0$
0*
b101 3
b101 5
b101 I
b1 1
b1 K
0"
#670000
1/
0(
00
b1010 F
1"
#680000
b11 6
b11 -
b11 G
0"
#690000
0/
b1011 F
1"
#700000
0"
#710000
1'
b100 F
1"
#720000
1$
1*
b101 4
b1010000000000000000 2
b1010000000000000000 J
0"
#730000
0'
b101 F
1"
#740000
0"
#750000
b110 F
1"
#760000
0"
#770000
1&
b1000 F
1"
#780000
0$
0*
b0 4
b0 2
b0 J
0"
#790000
1(
10
0&
b1001 F
1"
#800000
b1101 3
b1101 5
b1101 I
b11 1
b11 K
0"
#810000
1/
0(
00
b1010 F
1"
#820000
b10 6
b10 -
b10 G
0"
#830000
0/
b1011 F
1"
#840000
0"
#850000
1'
b100 F
1"
#860000
0"
#870000
0'
b101 F
1"
#880000
0"
#890000
b110 F
1"
#900000
0"
#910000
10
b111 F
1"
#920000
b11001 3
b11001 5
b11001 I
b110 1
b110 K
0"
#930000
1/
00
b1010 F
1"
#940000
b1 6
b1 -
b1 G
0"
#950000
0/
b1011 F
1"
#960000
0"
#970000
1'
b100 F
1"
#980000
0"
#990000
0'
b101 F
1"
#1000000
0"
#1010000
b110 F
1"
#1020000
0"
#1030000
10
b111 F
1"
#1040000
b110001 3
b110001 5
b110001 I
b1100 1
b1100 K
0"
#1050000
1/
00
b1010 F
1"
#1060000
08
1,
b0 6
b0 -
b0 G
0"
#1070000
0/
b1011 F
1"
#1080000
0"
#1090000
1.
b1100 F
1"
#1100000
0"
#1110000
0.
b0 F
1"
#1120000
0"
#1130000
b1 F
1"
